Workbook

Sheet country_world_globalpetrolprice
A1: fid | B1: NAME_EN | C1: NAME_RU | D1: Потребление нефти/нефтепродуктов, барр./сут. | E1: Год потребления | F1: Потребление, млн барр./год | G1: Дизель/дистилляты, % потребления | H1: Бензин, % потребления | I1: LPG, % потребления | J1: Jet/керосин, % потребления | K1: Мазут/Residual Fuel Oil, % потребления | L1: Добыча нефти и жидкостей, барр./сут. | M1: Год добычи | N1: Добыча сырой нефти, барр./сут. | O1: Добыча NGPL, барр./сут. | P1: ВВП, млрд USD | Q1: Год ВВП | R1: Рост ВВП, % | S1: Год роста | T1: Инфляция CPI, % | U1: Год инфляции | V1: Цена бензина, USD | W1: Цена дизеля, USD | X1: Цена Jet/керосина, USD | Y1: Цена LPG, USD | Z1: Цена мазута, USD | AA1: Единица/тип цены | AB1: Дата цены | AC1: Источник нефть/нефтепродукты | AD1: Источник экономика | AE1: Источник цены | AF1: Комментарий | AG1: Статус цены топлива | AH1: ISO2 | AI1: ISO3 | AJ1: НПЗ Oilmap, шт. | AK1: Известная мощность Oilmap, барр./сут. | AL1: НПЗ Oilmap без мощности, шт. | AM1: Дата слоя Oilmap | AN1: НПЗ: статус свежей проверки | AO1: Год продуктовых долей | AP1: Год сырой нефти / конденсата | AQ1: Год NGPL | AR1: Дата проверки
A2: 1 | B2: Indonesia | C2: Индонезия | D2: 2153449.3 | E2: 2025 | F2: =IF(AND(ISNUMBER(D2),ISNUMBER(E2)),D2*(DATE(E2+1,1,1)-DATE(E2,1,1))/1000000,"н/д") -> 786.009 | G2: 31.704726 | H2: 30.451941 | I2: 14.642962 | J2: 7.8304447 | K2: 1.5610508 | L2: 852688.87 | M2: 2025 | N2: 581668.49 | O2: 20000 | P2: 1445.6426 | Q2: 2025 | R2: 5.108089 | S2: 2025 | T2: 1.9133344 | U2: 2025 | V2: 0.939 | W2: 1.438 | X2: н/д | Y2: н/д | Z2: н/д | AA2: Бензин/дизель/LPG: USD/л; Jet/мазут: исходные единицы | AB2: Бензин: 2026-09-14; Дизель: 2026-09-14; исходные даты для непроверенных значений: бензин: 2026-09-14; дизель/LPG: 2026-09-07; Jet/мазут: н/д | AC2: https://api.eia.gov/v2/international/data/?frequency=annual&facets[productId][]=53&facets[activityId][]=1&facets[unit][]=TBPD ; https://api.eia.gov/v2/international/data/?frequency=annual&facets[productId][]=57&facets[activityId][]=1&facets[unit][]=TBPD ; https://api.eia.gov/v2/international/data/?frequency=annual&facets[productId][]=58&facets[activityId][]=1&facets[unit][]=TBPD ; https://www.jodidata.org/_resources/files/downloads/oil-data/annual-csv/secondary/2025.csv ; Исходный источник: https://www.jodidata.org/oil/database/data-downloads.aspx ; https://www.worldometers.info/oil/indonesia-oil/ | AD2: https://api.worldbank.org/v2/country/IDN/indicator/NY.GDP.MKTP.CD?format=json ; https://api.worldbank.org/v2/country/IDN/indicator/NY.GDP.MKTP.KD.ZG?format=json ; https://api.worldbank.org/v2/country/IDN/indicator/FP.CPI.TOTL.ZG?format=json ; Исходный источник: https://data.worldbank.org/ | AE2: https://www.globalpetrolprices.com/Indonesia/gasoline_prices/ ; https://www.globalpetrolprices.com/Indonesia/diesel_prices/ ; Исходный источник: GlobalPetrolPrices (страновые значения только там, где они были явно помечены как страновые); Jet/мазут: н/д | AF2: Массовые оценки/медианы удалены в ходе аудита. Сохранившиеся исходные числовые значения не считаются подтверждёнными автоматически; требуется первичная проверка источника. Обновление 16.09.2026: Потребление и доли: JODI, нефтепродукты TOTPRODS, 12 месяцев 2025. Jet/мазут: национальные сопоставимые цены не найдены; исходные значения сохранены. | AG2: Бензин: проверено GPP; Дизель: проверено GPP; LPG: н/д; Jet/керосин: нет сопоставимой национальной цены; Мазут: нет сопоставимой национальной цены | AH2: ID | AI2: IDN | AJ2: ='Сводка НПЗ'!D2 -> 8 | AK2: =IF('Сводка НПЗ'!F2>0,'Сводка НПЗ'!E2,"") -> 1046370 | AL2: ='Сводка НПЗ'!G2 -> 0 | AM2: 2019-02-18 | AN2: Мощность: вторичная публикация EI; число НПЗ не подтверждено | AO2: 2025 | AP2: 2025 | AQ2: 2025 | AR2: 2026-09-16
A3: 2 | B3: Malaysia | C3: Малайзия | D3: 747111.57 | E3: 2024 | F3: =IF(AND(ISNUMBER(D3),ISNUMBER(E3)),D3*(DATE(E3+1,1,1)-DATE(E3,1,1))/1000000,"н/д") -> 273.44283 | G3: 26.813777 | H3: 43.478961 | I3: 11.014423 | J3: 7.1779446 | K3: 3.2695489 | L3: 604170.9 | M3: 2025 | N3: 512670.14 | O3: 39578.995 | P3: 472.19313 | Q3: 2025 | R3: 5.1712708 | S3: 2025 | T3: 1.3806087 | U3: 2025 | V3: 0.994 | W3: 1.216 | X3: н/д | Y3: н/д | Z3: н/д | AA3: Бензин/дизель/LPG: USD/л; Jet/мазут: исходные единицы | AB3: Бензин: 2026-09-14; Дизель: 2026-09-14; исходные даты для непроверенных значений: бензин: 2026-09-14; дизель/LPG: 2026-09-07; Jet/мазут: н/д | AC3: https://api.eia.gov/v2/international/data/?frequency=annual&facets[productId][]=53&facets[activityId][]=1&facets[unit][]=TBPD ; https://api.eia.gov/v2/international/data/?frequency=annual&facets[productId][]=57&facets[activityId][]=1&facets[unit][]=TBPD ; https://api.eia.gov/v2/international/data/?frequency=annual&facets[productId][]=58&facets[activityId][]=1&facets[unit][]=TBPD ; https://api.eia.gov/v2/international/data/?frequency=annual&facets[productId][]=5&facets[activityId][]=2&facets[unit][]=TBPD ; Исходный источник: https://www.jodidata.org/oil/database/data-downloads.aspx ; https://www.worldometers.info/oil/malaysia-oil/ | AD3: https://api.worldbank.org/v2/country/MYS/indicator/NY.GDP.MKTP.CD?format=json ; https://api.worldbank.org/v2/country/MYS/indicator/NY.GDP.MKTP.KD.ZG?format=json ; https://api.worldbank.org/v2/country/MYS/indicator/FP.CPI.TOTL.ZG?format=json ; Исходный источник: https://data.worldbank.org/ | AE3: https://www.globalpetrolprices.com/Malaysia/gasoline_prices/ ; https://www.globalpetrolprices.com/Malaysia/diesel_prices/ ; Исходный источник: GlobalPetrolPrices (страновые значения только там, где они были явно помечены как страновые); Jet/мазут: н/д | AF3: Массовые оценки/медианы удалены в ходе аудита. Сохранившиеся исходные числовые значения не считаются подтверждёнными автоматически; требуется первичная проверка источника. Обновление 16.09.2026: Потребление и доли: EIA, petroleum and other liquids, 2024; включает биотопливо. Jet/мазут: национальные сопоставимые цены не найдены; исходные значения сохранены. | AG3: Бензин: проверено GPP; Дизель: проверено GPP; LPG: н/д; Jet/керосин: нет сопоставимой национальной цены; Мазут: нет сопоставимой национальной цены | AH3: MY | AI3: MYS | AJ3: ='Сводка НПЗ'!D3 -> 6 | AK3: =IF('Сводка НПЗ'!F3>0,'Сводка НПЗ'!E3,"") -> 545000 | AL3: ='Сводка НПЗ'!G3 -> 0 | AM3: 2019-02-18 | AN3: Мощность: вторичная публикация EI; число НПЗ не подтверждено | AO3: 2024 | AP3: 2025 | AQ3: 2025 | AR3: 2026-09-16
A4: 3 | B4: Chile | C4: Чили | D4: 374295.89 | E4: 2025 | F4: =IF(AND(ISNUMBER(D4),ISNUMBER(E4)),D4*(DATE(E4+1,1,1)-DATE(E4,1,1))/1000000,"н/д") -> 136.618 | G4: 49.00205 | H4: 24.575751 | I4: 11.836068 | J4: 14.142434 | K4: 1.8786836 | L4: 21108.608 | M4: 2025 | N4: 1968.322 | O4: 11828.373 | P4: 357.37116 | Q4: 2025 | R4: 2.4592547 | S4: 2025 | T4: 4.212936 | U4: 2025 | V4: 1.522 | W4: 1.319 | X4: н/д | Y4: 0.715 | Z4: н/д | AA4: Бензин/дизель/LPG: USD/л; Jet/мазут: исходные единицы | AB4: Бензин: 2026-09-14; Дизель: 2026-09-14; LPG: 2026-09-14; исходные даты для непроверенных значений: бензин: 2026-09-14; дизель/LPG: 2026-09-07; Jet/мазут: н/д | AC4: https://api.eia.gov/v2/international/data/?frequency=annual&facets[productId][]=53&facets[activityId][]=1&facets[unit][]=TBPD ; https://api.eia.gov/v2/international/data/?frequency=annual&facets[productId][]=57&facets[activityId][]=1&facets[unit][]=TBPD ; https://api.eia.gov/v2/international/data/?frequency=annual&facets[productId][]=58&facets[activityId][]=1&facets[unit][]=TBPD ; https://www.jodidata.org/_resources/files/downloads/oil-data/annual-csv/secondary/2025.csv ; Исходный источник: https://www.jodidata.org/oil/database/data-downloads.aspx ; https://www.worldometers.info/oil/chile-oil/ | AD4: https://api.worldbank.org/v2/country/CHL/indicator/NY.GDP.MKTP.CD?format=json ; https://api.worldbank.org/v2/country/CHL/indicator/NY.GDP.MKTP.KD.ZG?format=json ; https://api.worldbank.org/v2/country/CHL/indicator/FP.CPI.TOTL.ZG?format=json ; Исходный источник: https://data.worldbank.org/ | AE4: https://www.globalpetrolprices.com/Chile/gasoline_prices/ ; https://www.globalpetrolprices.com/Chile/diesel_prices/ ; https://www.globalpetrolprices.com/Chile/lpg_prices/ ; Исходный источник: GlobalPetrolPrices (страновые значения только там, где они были явно помечены как страновые); Jet/мазут: н/д | AF4: Массовые оценки/медианы удалены в ходе аудита. Сохранившиеся исходные числовые значения не считаются подтверждёнными автоматически; требуется первичная проверка источника. Обновление 16.09.2026: Потребление и доли: JODI, нефтепродукты TOTPRODS, 12 месяцев 2025. Jet/мазут: национальные сопоставимые цены не найдены; исходные значения сохранены. | AG4: Бензин: проверено GPP; Дизель: проверено GPP; LPG: проверено GPP; Jet/керосин: нет сопоставимой национальной цены; Мазут: нет сопоставимой национальной цены | AH4: CL | AI4: CHL | AJ4: ='Сводка НПЗ'!D4 -> 3 | AK4: =IF('Сводка НПЗ'!F4>0,'Сводка НПЗ'!E4,"") -> 226750 | AL4: ='Сводка НПЗ'!G4 -> 0 | AM4: 2019-02-18 | AN4: Мощность: вторичная публикация EI; число НПЗ не подтверждено | AO4: 2025 | AP4: 2025 | AQ4: 2025 | AR4: 2026-09-16
A5: 4 | B5: Bolivia | C5: Боливия | D5: 103844.97 | E5: 2024 | F5: =IF(AND(ISNUMBER(D5),ISNUMBER(E5)),D5*(DATE(E5+1,1,1)-DATE(E5,1,1))/1000000,"н/д") -> 38.007258 | G5: 41.252249 | H5: 38.801499 | I5: 14.43811 | J5: 3.7013216 | K5: 0 | L5: 51865.89 | M5: 2025 | N5: 17660.805 | O5: 32000 | P5: 64.768948 | Q5: 2025 | R5: -1.5823757 | S5: 2025 | T5: 19.517121 | U5: 2025 | V5: 0.603 | W5: 0.85 | X5: н/д | Y5: н/д | Z5: н/д | AA5: Бензин/дизель/LPG: USD/л; Jet/мазут: исходные единицы | AB5: Бензин: 2026-09-14; Дизель: 2026-09-14; исходные даты для непроверенных значений: бензин: 2026-09-14; дизель/LPG: 2026-09-07; Jet/мазут: н/д | AC5: https://api.eia.gov/v2/international/data/?frequency=annual&facets[productId][]=53&facets[activityId][]=1&facets[unit][]=TBPD ; https://api.eia.gov/v2/international/data/?frequency=annual&facets[productId][]=57&facets[activityId][]=1&facets[unit][]=TBPD ; https://api.eia.gov/v2/international/data/?frequency=annual&facets[productId][]=58&facets[activityId][]=1&facets[unit][]=TBPD ; https://api.eia.gov/v2/international/data/?frequency=annual&facets[productId][]=5&facets[activityId][]=2&facets[unit][]=TBPD ; Исходный источник: https://www.jodidata.org/oil/database/data-downloads.aspx ; https://www.worldometers.info/oil/bolivia-oil/ | AD5: https://api.worldbank.org/v2/country/BOL/indicator/NY.GDP.MKTP.CD?format=json ; https://api.worldbank.org/v2/country/BOL/indicator/NY.GDP.MKTP.KD.ZG?format=json ; https://api.worldbank.org/v2/country/BOL/indicator/FP.CPI.TOTL.ZG?format=json ; Исходный источник: https://data.worldbank.org/ | AE5: https://www.globalpetrolprices.com/Bolivia/gasoline_prices/ ; https://www.globalpetrolprices.com/Bolivia/diesel_prices/ ; Исходный источник: GlobalPetrolPrices (страновые значения только там, где они были явно помечены как страновые); Jet/мазут: н/д | AF5: Массовые оценки/медианы удалены в ходе аудита. Сохранившиеся исходные числовые значения не считаются подтверждёнными автоматически; требуется первичная проверка источника. Обновление 16.09.2026: Потребление и доли: EIA, petroleum and other liquids, 2024; включает биотопливо. Jet/мазут: национальные сопоставимые цены не найдены; исходные значения сохранены. | AG5: Бензин: проверено GPP; Дизель: проверено GPP; LPG: н/д; Jet/керосин: нет сопоставимой национальной цены; Мазут: нет сопоставимой национальной цены | AH5: BO | AI5: BOL | AJ5: ='Сводка НПЗ'!D5 -> 2 | AK5: =IF('Сводка НПЗ'!F5>0,'Сводка НПЗ'!E5,"") -> 20000 | AL5: ='Сводка НПЗ'!G5 -> 1 | AM5: 2019-02-18 | AN5: Свежие число и мощность не подтверждены | AO5: 2024 | AP5: 2025 | AQ5: 2025 | AR5: 2026-09-16
A6: 5 | B6: Peru | C6: Перу | D6: 264380.45 | E6: 2024 | F6: =IF(AND(ISNUMBER(D6),ISNUMBER(E6)),D6*(DATE(E6+1,1,1)-DATE(E6,1,1))/1000000,"н/д") -> 96.763245 | G6: 41.462548 | H6: 19.301277 | I6: 27.160897 | J6: 5.8060151 | K6: 5.2555087 | L6: 123301.73 | M6: 2025 | N6: 44152.745 | O6: 73325.764 | P6: 334.85466 | Q6: 2025 | R6: 3.430564 | S6: 2025 | T6: 1.5312545 | U6: 2025 | V6: 1.723 | W6: 1.965 | X6: н/д | Y6: 0.642 | Z6: н/д | AA6: Бензин/дизель/LPG: USD/л; Jet/мазут: исходные единицы | AB6: Бензин: 2026-09-14; Дизель: 2026-09-14; LPG: 2026-09-14; исходные даты для непроверенных значений: бензин: 2026-09-14; дизель/LPG: 2026-09-07; Jet/мазут: н/д | AC6: https://api.eia.gov/v2/international/data/?frequency=annual&facets[productId][]=53&facets[activityId][]=1&facets[unit][]=TBPD ; https://api.eia.gov/v2/international/data/?frequency=annual&facets[productId][]=57&facets[activityId][]=1&facets[unit][]=TBPD ; https://api.eia.gov/v2/international/data/?frequency=annual&facets[productId][]=58&facets[activityId][]=1&facets[unit][]=TBPD ; https://api.eia.gov/v2/international/data/?frequency=annual&facets[productId][]=5&facets[activityId][]=2&facets[unit][]=TBPD ; Исходный источник: https://www.jodidata.org/oil/database/data-downloads.aspx ; https://www.worldometers.info/oil/peru-oil/ | AD6: https://api.worldbank.org/v2/country/PER/indicator/NY.GDP.MKTP.CD?format=json ; https://api.worldbank.org/v2/country/PER/indicator/NY.GDP.MKTP.KD.ZG?format=json ; https://api.worldbank.org/v2/country/PER/indicator/FP.CPI.TOTL.ZG?format=json ; Исходный источник: https://data.worldbank.org/ | AE6: https://www.globalpetrolprices.com/Peru/gasoline_prices/ ; https://www.globalpetrolprices.com/Peru/diesel_prices/ ; https://www.globalpetrolprices.com/Peru/lpg_prices/ ; Исходный источник: GlobalPetrolPrices (страновые значения только там, где они были явно помечены как страновые); Jet/мазут: н/д | AF6: Массовые оценки/медианы удалены в ходе аудита. Сохранившиеся исходные числовые значения не считаются подтверждёнными автоматически; требуется первичная проверка источника. Обновление 16.09.2026: Потребление и доли: EIA, petroleum and other liquids, 2024; включает биотопливо. Jet/мазут: национальные сопоставимые цены не найдены; исходные значения сохранены. | AG6: Бензин: проверено GPP; Дизель: проверено GPP; LPG: проверено GPP; Jet/керосин: нет сопоставимой национальной цены; Мазут: нет сопоставимой национальной цены | AH6: PE | AI6: PER | AJ6: ='Сводка НПЗ'!D6 -> 6 | AK6: =IF('Сводка НПЗ'!F6>0,'Сводка НПЗ'!E6,"") -> 165250 | AL6: ='Сводка НПЗ'!G6 -> 3 | AM6: 2019-02-18 | AN6: Мощность: вторичная публикация EI; число НПЗ не подтверждено | AO6: 2024 | AP6: 2025 | AQ6: 2025 | AR6: 2026-09-16
A7: 6 | B7: Argentina | C7: Аргентина | D7: 734572.71 | E7: 2024 | F7: =IF(AND(ISNUMBER(D7),ISNUMBER(E7)),D7*(DATE(E7+1,1,1)-DATE(E7,1,1))/1000000,"н/д") -> 268.85361 | G7: 29.76554 | H7: 26.23083 | I7: 7.3289834 | J7: 4.5606832 | K7: 1.9697892 | L7: 983537.17 | M7: 2025 | N7: 794004.45 | O7: 130000 | P7: 683.09789 | Q7: 2025 | R7: 4.3673333 | S7: 2025 | T7: 219.88393 | U7: 2024 | V7: 1.412 | W7: 1.518 | X7: н/д | Y7: н/д | Z7: н/д | AA7: Бензин/дизель/LPG: USD/л; Jet/мазут: исходные единицы | AB7: Бензин: 2026-09-14; Дизель: 2026-09-14; исходные даты для непроверенных значений: бензин: 2026-09-14; дизель/LPG: 2026-09-07; Jet/мазут: н/д | AC7: https://api.eia.gov/v2/international/data/?frequency=annual&facets[productId][]=53&facets[activityId][]=1&facets[unit][]=TBPD ; https://api.eia.gov/v2/international/data/?frequency=annual&facets[productId][]=57&facets[activityId][]=1&facets[unit][]=TBPD ; https://api.eia.gov/v2/international/data/?frequency=annual&facets[productId][]=58&facets[activityId][]=1&facets[unit][]=TBPD ; https://api.eia.gov/v2/international/data/?frequency=annual&facets[productId][]=5&facets[activityId][]=2&facets[unit][]=TBPD ; Исходный источник: https://www.jodidata.org/oil/database/data-downloads.aspx ; https://www.worldometers.info/oil/argentina-oil/ | AD7: https://api.worldbank.org/v2/country/ARG/indicator/NY.GDP.MKTP.CD?format=json ; https://api.worldbank.org/v2/country/ARG/indicator/NY.GDP.MKTP.KD.ZG?format=json ; https://api.worldbank.org/v2/country/ARG/indicator/FP.CPI.TOTL.ZG?format=json ; Исходный источник: https://data.worldbank.org/ | AE7: https://www.globalpetrolprices.com/Argentina/gasoline_prices/ ; https://www.globalpetrolprices.com/Argentina/diesel_prices/ ; Исходный источник: GlobalPetrolPrices (страновые значения только там, где они были явно помечены как страновые); Jet/мазут: н/д | AF7: Массовые оценки/медианы удалены в ходе аудита. Сохранившиеся исходные числовые значения не считаются подтверждёнными автоматически; требуется первичная проверка источника. Обновление 16.09.2026: Потребление и доли: EIA, petroleum and other liquids, 2024; включает биотопливо. Jet/мазут: национальные сопоставимые цены не найдены; исходные значения сохранены. | AG7: Бензин: проверено GPP; Дизель: проверено GPP; LPG: н/д; Jet/керосин: нет сопоставимой национальной цены; Мазут: нет сопоставимой национальной цены | AH7: AR | AI7: ARG | AJ7: ='Сводка НПЗ'!D7 -> 10 | AK7: =IF('Сводка НПЗ'!F7>0,'Сводка НПЗ'!E7,"") -> 615575 | AL7: ='Сводка НПЗ'!G7 -> 0 | AM7: 2019-02-18 | AN7: Мощность: вторичная публикация EI; число НПЗ не подтверждено | AO7: 2024 | AP7: 2025 | AQ7: 2025 | AR7: 2026-09-16
A8: 7 | B8: Dhekelia Cantonment | C8: Декелия | D8: н/д | E8: н/д | F8: =IF(AND(ISNUMBER(D8),ISNUMBER(E8)),D8*(DATE(E8+1,1,1)-DATE(E8,1,1))/1000000,"н/д") -> н/д | G8: н/д | H8: н/д | I8: н/д | J8: н/д | K8: н/д | L8: н/д | M8: н/д | N8: н/д | O8: н/д | P8: н/д | Q8: н/д | R8: н/д | S8: н/д | T8: н/д | U8: н/д | V8: н/д | W8: н/д | X8: н/д | Y8: н/д | Z8: н/д | AA8: бензин/дизель/LPG/Jet: USD/л; мазут: USD/т | AB8: бензин: 2026-09-14; дизель/LPG: 2026-09-07; Jet/мазут: н/д | AC8: https://www.jodidata.org/oil/database/data-downloads.aspx ; https://www.jodidata.org/oil/database/data-downloads.aspx | AD8: https://data.worldbank.org/ | AE8: GlobalPetrolPrices (страновые значения только там, где они были явно помечены как страновые); Jet/мазут: н/д | AF8: Массовые оценки/медианы удалены в ходе аудита. Сохранившиеся исходные числовые значения не считаются подтверждёнными автоматически; требуется первичная проверка источника. Обновление 16.09.2026: Потребление и доли: исходные значения, свежая сопоставимая серия не найдена. Jet/мазут: национальные сопоставимые цены не найдены; исходные значения сохранены. | AG8: Бензин: н/д; Дизель: н/д; LPG: н/д; Jet/керосин: нет сопоставимой национальной цены; Мазут: нет сопоставимой национальной цены | AH8: н/д | AI8: н/д | AJ8: ='Сводка НПЗ'!D8 -> 0 | AK8: =IF('Сводка НПЗ'!F8>0,'Сводка НПЗ'!E8,"") | AL8: ='Сводка НПЗ'!G8 -> 0 | AM8: 2019-02-18 | AN8: Свежие число и мощность не подтверждены | AR8: 2026-09-16
A9: 8 | B9: Cyprus | C9: Кипр | D9: 48869.041 | E9: 2025 | F9: =IF(AND(ISNUMBER(D9),ISNUMBER(E9)),D9*(DATE(E9+1,1,1)-DATE(E9,1,1))/1000000,"н/д") -> 17.8372 | G9: 32.566771 | H9: 16.440361 | I9: 3.7068598 | J9: н/д | K9: 26.346624 | L9: 0 | M9: 2025 | N9: 0 | O9: 0 | P9: 41.225787 | Q9: 2025 | R9: 3.7732535 | S9: 2025 | T9: 0.12652885 | U9: 2025 | V9: 1.907 | W9: 2.213 | X9: н/д | Y9: н/д | Z9: н/д | AA9: Бензин/дизель/LPG: USD/л; Jet/мазут: исходные единицы | AB9: Бензин: 2026-09-14; Дизель: 2026-09-14; исходные даты для непроверенных значений: бензин: 2026-09-14; дизель/LPG: 2026-09-07; Jet/мазут: н/д | AC9: https://api.eia.gov/v2/international/data/?frequency=annual&facets[productId][]=53&facets[activityId][]=1&facets[unit][]=TBPD ; https://api.eia.gov/v2/international/data/?frequency=annual&facets[productId][]=57&facets[activityId][]=1&facets[unit][]=TBPD ; https://api.eia.gov/v2/international/data/?frequency=annual&facets[productId][]=58&facets[activityId][]=1&facets[unit][]=TBPD ; https://www.jodidata.org/_resources/files/downloads/oil-data/annual-csv/secondary/2025.csv ; Исходный источник: https://www.jodidata.org/oil/database/data-downloads.aspx ; https://www.worldometers.info/oil/cyprus-oil/ | AD9: https://api.worldbank.org/v2/country/CYP/indicator/NY.GDP.MKTP.CD?format=json ; https://api.worldbank.org/v2/country/CYP/indicator/NY.GDP.MKTP.KD.ZG?format=json ; https://api.worldbank.org/v2/country/CYP/indicator/FP.CPI.TOTL.ZG?format=json ; Исходный источник: https://data.worldbank.org/ | AE9: https://www.globalpetrolprices.com/Cyprus/gasoline_prices/ ; https://www.globalpetrolprices.com/Cyprus/diesel_prices/ ; Исходный источник: GlobalPetrolPrices (страновые значения только там, где они были явно помечены как страновые); Jet/мазут: н/д | AF9: Массовые оценки/медианы удалены в ходе аудита. Сохранившиеся исходные числовые значения не считаются подтверждёнными автоматически; требуется первичная проверка источника. Обновление 16.09.2026: Потребление и доли: JODI, нефтепродукты TOTPRODS, 12 месяцев 2025. Jet/мазут: национальные сопоставимые цены не найдены; исходные значения сохранены. | AG9: Бензин: проверено GPP; Дизель: проверено GPP; LPG: н/д; Jet/керосин: нет сопоставимой национальной цены; Мазут: нет сопоставимой национальной цены | AH9: CY | AI9: CYP | AJ9: ='Сводка НПЗ'!D9 -> 0 | AK9: =IF('Сводка НПЗ'!F9>0,'Сводка НПЗ'!E9,"") | AL9: ='Сводка НПЗ'!G9 -> 0 | AM9: 2019-02-18 | AN9: Свежие число и мощность не подтверждены | AO9: 2025 | AP9: 2025 | AQ9: 2025 | AR9: 2026-09-16
A10: 9 | B10: India | C10: Индия | D10: 5477539.7 | E10: 2025 | F10: =IF(AND(ISNUMBER(D10),ISNUMBER(E10)),D10*(DATE(E10+1,1,1)-DATE(E10,1,1))/1000000,"н/д") -> 1999.302 | G10: 35.2424 | H10: 17.732723 | I10: 19.236856 | J10: 7.3199116 | K10: 2.0233017 | L10: 990278.1 | M10: 2025 | N10: 580600.35 | O10: 110560.13 | P10: 3956.0671 | Q10: 2025 | R10: 7.5666618 | S10: 2025 | T10: 2.3988495 | U10: 2025 | V10: 1.132 | W10: 1.022 | X10: н/д | Y10: 0.68 | Z10: н/д | AA10: Бензин/дизель/LPG: USD/л; Jet/мазут: исходные единицы | AB10: Бензин: 2026-09-14; Дизель: 2026-09-14; LPG: 2026-09-14; исходные даты для непроверенных значений: бензин: 2026-09-14; дизель/LPG: 2026-09-07; Jet/мазут: н/д | AC10: https://api.eia.gov/v2/international/data/?frequency=annual&facets[productId][]=53&facets[activityId][]=1&facets[unit][]=TBPD ; https://api.eia.gov/v2/international/data/?frequency=annual&facets[productId][]=57&facets[activityId][]=1&facets[unit][]=TBPD ; https://api.eia.gov/v2/international/data/?frequency=annual&facets[productId][]=58&facets[activityId][]=1&facets[unit][]=TBPD ; https://www.jodidata.org/_resources/files/downloads/oil-data/annual-csv/secondary/2025.csv ; Исходный источник: https://www.jodidata.org/oil/database/data-downloads.aspx ; https://www.worldometers.info/oil/india-oil/ | AD10: https://api.worldbank.org/v2/country/IND/indicator/NY.GDP.MKTP.CD?format=json ; https://api.worldbank.org/v2/country/IND/indicator/NY.GDP.MKTP.KD.ZG?format=json ; https://api.worldbank.org/v2/country/IND/indicator/FP.CPI.TOTL.ZG?format=json ; Исходный источник: https://data.worldbank.org/ | AE10: https://www.globalpetrolprices.com/India/gasoline_prices/ ; https://www.globalpetrolprices.com/India/diesel_prices/ ; https://www.globalpetrolprices.com/India/lpg_prices/ ; Исходный источник: GlobalPetrolPrices (страновые значения только там, где они были явно помечены как страновые); Jet/мазут: н/д | AF10: Массовые оценки/медианы удалены в ходе аудита. Сохранившиеся исходные числовые значения не считаются подтверждёнными автоматически; требуется первичная проверка источника. Обновление 16.09.2026: Потребление и доли: JODI, нефтепродукты TOTPRODS, 12 месяцев 2025. Jet/мазут: национальные сопоставимые цены не найдены; исходные значения сохранены. | AG10: Бензин: проверено GPP; Дизель: проверено GPP; LPG: проверено GPP; Jet/керосин: нет сопоставимой национальной цены; Мазут: нет сопоставимой национальной цены | AH10: IN | AI10: IND | AJ10: ='Сводка НПЗ'!D10 -> 17 | AK10: =IF('Сводка НПЗ'!F10>0,'Сводка НПЗ'!E10,"") -> 2385000 | AL10: ='Сводка НПЗ'!G10 -> 0 | AM10: 2019-02-18 | AN10: Проверен первичный источник; см. охват | AO10: 2025 | AP10: 2025 | AQ10: 2025 | AR10: 2026-09-16
A11: 10 | B11: People's Republic of China | C11: Китайская Народная Республика | D11: 16639725 | E11: 2025 | F11: =IF(AND(ISNUMBER(D11),ISNUMBER(E11)),D11*(DATE(E11+1,1,1)-DATE(E11,1,1))/1000000,"н/д") -> 6073.4995 | G11: 22.978391 | H11: 20.525819 | I11: 16.657754 | J11: н/д | K11: 4.8810399 | L11: 5446188.7 | M11: 2025 | N11: 4324684.9 | O11: 10000 | P11: 19498.039 | Q11: 2025 | R11: 4.9599489 | S11: 2025 | T11: 0.059564692 | U11: 2025 | V11: 1.326 | W11: 1.187 | X11: н/д | Y11: н/д | Z11: н/д | AA11: Бензин/дизель/LPG: USD/л; Jet/мазут: исходные единицы | AB11: Бензин: 2026-09-14; Дизель: 2026-09-14; исходные даты для непроверенных значений: бензин: 2026-09-14; дизель/LPG: 2026-09-07; Jet/мазут: н/д | AC11: https://api.eia.gov/v2/international/data/?frequency=annual&facets[productId][]=53&facets[activityId][]=1&facets[unit][]=TBPD ; https://api.eia.gov/v2/international/data/?frequency=annual&facets[productId][]=57&facets[activityId][]=1&facets[unit][]=TBPD ; https://api.eia.gov/v2/international/data/?frequency=annual&facets[productId][]=58&facets[activityId][]=1&facets[unit][]=TBPD ; https://www.jodidata.org/_resources/files/downloads/oil-data/annual-csv/secondary/2025.csv ; Исходный источник: https://www.jodidata.org/oil/database/data-downloads.aspx ; https://www.worldometers.info/oil/china-oil/ | AD11: https://api.worldbank.org/v2/country/CHN/indicator/NY.GDP.MKTP.CD?format=json ; https://api.worldbank.org/v2/country/CHN/indicator/NY.GDP.MKTP.KD.ZG?format=json ; https://api.worldbank.org/v2/country/CHN/indicator/FP.CPI.TOTL.ZG?format=json ; Исходный источник: https://data.worldbank.org/ | AE11: https://www.globalpetrolprices.com/China/gasoline_prices/ ; https://www.globalpetrolprices.com/China/diesel_prices/ ; Исходный источник: GlobalPetrolPrices (страновые значения только там, где они были явно помечены как страновые); Jet/мазут: н/д | AF11: Массовые оценки/медианы удалены в ходе аудита. Сохранившиеся исходные числовые значения не считаются подтверждёнными автоматически; требуется первичная проверка источника. Обновление 16.09.2026: Потребление и доли: JODI, нефтепродукты TOTPRODS, 12 месяцев 2025. Jet/мазут: национальные сопоставимые цены не найдены; исходные значения сохранены. | AG11: Бензин: проверено GPP; Дизель: проверено GPP; LPG: н/д; Jet/керосин: нет сопоставимой национальной цены; Мазут: нет сопоставимой национальной цены | AH11: CN | AI11: CHN | AJ11: ='Сводка НПЗ'!D11 -> 51 | AK11: =IF('Сводка НПЗ'!F11>0,'Сводка НПЗ'!E11,"") -> 5950000 | AL11: ='Сводка НПЗ'!G11 -> 0 | AM11: 2019-02-18 | AN11: Мощность: вторичная публикация EI; число НПЗ не подтверждено | AO11: 2025 | AP11: 2025 | AQ11: 2025 | AR11: 2026-09-16
A12: 11 | B12: Israel | C12: Израиль | D12: 221276.71 | E12: 2025 | F12: =IF(AND(ISNUMBER(D12),ISNUMBER(E12)),D12*(DATE(E12+1,1,1)-DATE(E12,1,1))/1000000,"н/д") -> 80.766 | G12: 27.973405 | H12: 33.947453 | I12: 6.3974938 | J12: 10.113167 | K12: 3.0978384 | L12: 25214.808 | M12: 2025 | N12: 19520.548 | O12: 0 | P12: 610.77784 | Q12: 2025 | R12: 2.9311497 | S12: 2025 | T12: 3.0414132 | U12: 2025 | V12: 2.632 | W12: 2.501 | X12: н/д | Y12: 1.088 | Z12: н/д | AA12: Бензин/дизель/LPG: USD/л; Jet/мазут: исходные единицы | AB12: Бензин: 2026-09-14; Дизель: 2026-09-14; LPG: 2026-09-14; исходные даты для непроверенных значений: бензин: 2026-09-14; дизель/LPG: 2026-09-07; Jet/мазут: н/д | AC12: https://api.eia.gov/v2/international/data/?frequency=annual&facets[productId][]=53&facets[activityId][]=1&facets[unit][]=TBPD ; https://api.eia.gov/v2/international/data/?frequency=annual&facets[productId][]=57&facets[activityId][]=1&facets[unit][]=TBPD ; https://api.eia.gov/v2/international/data/?frequency=annual&facets[productId][]=58&facets[activityId][]=1&facets[unit][]=TBPD ; https://api.eia.gov/v2/international/data/?frequency=annual&facets[productId][]=5&facets[activityId][]=2&facets[unit][]=TBPD ; Исходный источник: https://www.jodidata.org/oil/database/data-downloads.aspx ; https://www.worldometers.info/oil/israel-oil/ | AD12: https://api.worldbank.org/v2/country/ISR/indicator/NY.GDP.MKTP.CD?format=json ; https://api.worldbank.org/v2/country/ISR/indicator/NY.GDP.MKTP.KD.ZG?format=json ; https://api.worldbank.org/v2/country/ISR/indicator/FP.CPI.TOTL.ZG?format=json ; Исходный источник: https://data.worldbank.org/ | AE12: https://www.globalpetrolprices.com/Israel/gasoline_prices/ ; https://www.globalpetrolprices.com/Israel/diesel_prices/ ; https://www.globalpetrolprices.com/Israel/lpg_prices/ ; Исходный источник: GlobalPetrolPrices (страновые значения только там, где они были явно помечены как страновые); Jet/мазут: н/д | AF12: Массовые оценки/медианы удалены в ходе аудита. Сохранившиеся исходные числовые значения не считаются подтверждёнными автоматически; требуется первичная проверка источника. Обновление 16.09.2026: Потребление и доли: EIA, petroleum and other liquids, 2025; включает биотопливо. Jet/мазут: национальные сопоставимые цены не найдены; исходные значения сохранены. | AG12: Бензин: проверено GPP; Дизель: проверено GPP; LPG: проверено GPP; Jet/керосин: нет сопоставимой национальной цены; Мазут: нет сопоставимой национальной цены | AH12: IL | AI12: ISR | AJ12: ='Сводка НПЗ'!D12 -> 2 | AK12: =IF('Сводка НПЗ'!F12>0,'Сводка НПЗ'!E12,"") -> 240000 | AL12: ='Сводка НПЗ'!G12 -> 0 | AM12: 2019-02-18 | AN12: Мощность: вторичная публикация EI; число НПЗ не подтверждено | AO12: 2025 | AP12: 2025 | AQ12: 2025 | AR12: 2026-09-16
A13: 12 | B13: Palestine | C13: Палестина | D13: 34404.856 | E13: 2024 | F13: =IF(AND(ISNUMBER(D13),ISNUMBER(E13)),D13*(DATE(E13+1,1,1)-DATE(E13,1,1))/1000000,"н/д") -> 12.592177 | G13: 55.684153 | H13: 21.772048 | I13: 21.623253 | J13: 0.11518522 | K13: 0.14510722 | L13: 0 | M13: 2025 | N13: 0 | O13: 0 | P13: 17.1671 | Q13: 2025 | R13: 4.3444407 | S13: 2025 | T13: 9.8084012 | U13: 2025 | V13: н/д | W13: н/д | X13: н/д | Y13: н/д | Z13: н/д | AA13: бензин/дизель/LPG/Jet: USD/л; мазут: USD/т | AB13: бензин: 2026-09-14; дизель/LPG: 2026-09-07; Jet/мазут: н/д | AC13: https://api.eia.gov/v2/international/data/?frequency=annual&facets[productId][]=53&facets[activityId][]=1&facets[unit][]=TBPD ; https://api.eia.gov/v2/international/data/?frequency=annual&facets[productId][]=57&facets[activityId][]=1&facets[unit][]=TBPD ; https://api.eia.gov/v2/international/data/?frequency=annual&facets[productId][]=58&facets[activityId][]=1&facets[unit][]=TBPD ; https://api.eia.gov/v2/international/data/?frequency=annual&facets[productId][]=5&facets[activityId][]=2&facets[unit][]=TBPD ; Исходный источник: https://www.jodidata.org/oil/database/data-downloads.aspx ; https://www.worldometers.info/oil/state-of-palestine-oil/ | AD13: https://api.worldbank.org/v2/country/PSE/indicator/NY.GDP.MKTP.CD?format=json ; https://api.worldbank.org/v2/country/PSE/indicator/NY.GDP.MKTP.KD.ZG?format=json ; https://api.worldbank.org/v2/country/PSE/indicator/FP.CPI.TOTL.ZG?format=json ; Исходный источник: https://data.worldbank.org/ | AE13: GlobalPetrolPrices (страновые значения только там, где они были явно помечены как страновые); Jet/мазут: н/д | AF13: Массовые оценки/медианы удалены в ходе аудита. Сохранившиеся исходные числовые значения не считаются подтверждёнными автоматически; требуется первичная проверка источника. Обновление 16.09.2026: Потребление и доли: EIA, petroleum and other liquids, 2024; включает биотопливо. Jet/мазут: национальные сопоставимые цены не найдены; исходные значения сохранены. | AG13: Бензин: н/д; Дизель: н/д; LPG: н/д; Jet/керосин: нет сопоставимой национальной цены; Мазут: нет сопоставимой национальной цены | AH13: PS | AI13: PSE | AJ13: ='Сводка НПЗ'!D13 -> 0 | AK13: =IF('Сводка НПЗ'!F13>0,'Сводка НПЗ'!E13,"") | AL13: ='Сводка НПЗ'!G13 -> 0 | AM13: 2019-02-18 | AN13: Свежие число и мощность не подтверждены | AO13: 2024 | AP13: 2025 | AQ13: 2025 | AR13: 2026-09-16
A14: 13 | B14: Lebanon | C14: Ливан | D14: 114321.37 | E14: 2024 | F14: =IF(AND(ISNUMBER(D14),ISNUMBER(E14)),D14*(DATE(E14+1,1,1)-DATE(E14,1,1))/1000000,"н/д") -> 41.84162 | G14: 52.18751 | H14: 34.55931 | I14: 6.2332578 | J14: 3.6447105 | K14: 3.0353295 | L14: 0 | M14: 2025 | N14: 0 | O14: 0 | P14: 25.971643 | Q14: 2024 | R14: -7.0798919 | S14: 2024 | T14: 14.597596 | U14: 2025 | V14: 1.38 | W14: 1.341 | X14: н/д | Y14: 0.62 | Z14: н/д | AA14: Бензин/дизель/LPG: USD/л; Jet/мазут: исходные единицы | AB14: Бензин: 2026-09-14; Дизель: 2026-09-14; LPG: 2026-09-14; исходные даты для непроверенных значений: бензин: 2026-09-14; дизель/LPG: 2026-09-07; Jet/мазут: н/д | AC14: https://api.eia.gov/v2/international/data/?frequency=annual&facets[productId][]=53&facets[activityId][]=1&facets[unit][]=TBPD ; https://api.eia.gov/v2/international/data/?frequency=annual&facets[productId][]=57&facets[activityId][]=1&facets[unit][]=TBPD ; https://api.eia.gov/v2/international/data/?frequency=annual&facets[productId][]=58&facets[activityId][]=1&facets[unit][]=TBPD ; https://api.eia.gov/v2/international/data/?frequency=annual&facets[productId][]=5&facets[activityId][]=2&facets[unit][]=TBPD ; Исходный источник: https://www.jodidata.org/oil/database/data-downloads.aspx ; https://www.worldometers.info/oil/lebanon-oil/ | AD14: https://api.worldbank.org/v2/country/LBN/indicator/NY.GDP.MKTP.CD?format=json ; https://api.worldbank.org/v2/country/LBN/indicator/NY.GDP.MKTP.KD.ZG?format=json ; https://api.worldbank.org/v2/country/LBN/indicator/FP.CPI.TOTL.ZG?format=json ; Исходный источник: https://data.worldbank.org/ | AE14: https://www.globalpetrolprices.com/Lebanon/gasoline_prices/ ; https://www.globalpetrolprices.com/Lebanon/diesel_prices/ ; https://www.globalpetrolprices.com/Lebanon/lpg_prices/ ; Исходный источник: GlobalPetrolPrices (страновые значения только там, где они были явно помечены как страновые); Jet/мазут: н/д | AF14: Массовые оценки/медианы удалены в ходе аудита. Сохранившиеся исходные числовые значения не считаются подтверждёнными автоматически; требуется первичная проверка источника. Обновление 16.09.2026: Потребление и доли: EIA, petroleum and other liquids, 2024; включает биотопливо. Jet/мазут: национальные сопоставимые цены не найдены; исходные значения сохранены. | AG14: Бензин: проверено GPP; Дизель: проверено GPP; LPG: проверено GPP; Jet/керосин: нет сопоставимой национальной цены; Мазут: нет сопоставимой национальной цены | AH14: LB | AI14: LBN | AJ14: ='Сводка НПЗ'!D14 -> 0 | AK14: =IF('Сводка НПЗ'!F14>0,'Сводка НПЗ'!E14,"") | AL14: ='Сводка НПЗ'!G14 -> 0 | AM14: 2019-02-18 | AN14: Свежие число и мощность не подтверждены | AO14: 2024 | AP14: 2025 | AQ14: 2025 | AR14: 2026-09-16
A15: 14 | B15: Ethiopia | C15: Эфиопия | D15: 103689.34 | E15: 2024 | F15: =IF(AND(ISNUMBER(D15),ISNUMBER(E15)),D15*(DATE(E15+1,1,1)-DATE(E15,1,1))/1000000,"н/д") -> 37.950298 | G15: 48.396516 | H15: 16.638355 | I15: 0.3138225 | J15: 26.344966 | K15: 1.2432241 | L15: 0 | M15: 2025 | N15: 0 | O15: 0 | P15: 126.35876 | Q15: 2025 | R15: 9.7715182 | S15: 2025 | T15: 13.229643 | U15: 2025 | V15: 1.027 | W15: 1.106 | X15: н/д | Y15: н/д | Z15: н/д | AA15: Бензин/дизель/LPG: USD/л; Jet/мазут: исходные единицы | AB15: Бензин: 2026-09-14; Дизель: 2026-09-14; исходные даты для непроверенных значений: бензин: 2026-09-14; дизель/LPG: 2026-09-07; Jet/мазут: н/д | AC15: https://api.eia.gov/v2/international/data/?frequency=annual&facets[productId][]=53&facets[activityId][]=1&facets[unit][]=TBPD ; https://api.eia.gov/v2/international/data/?frequency=annual&facets[productId][]=57&facets[activityId][]=1&facets[unit][]=TBPD ; https://api.eia.gov/v2/international/data/?frequency=annual&facets[productId][]=58&facets[activityId][]=1&facets[unit][]=TBPD ; https://api.eia.gov/v2/international/data/?frequency=annual&facets[productId][]=5&facets[activityId][]=2&facets[unit][]=TBPD ; Исходный источник: https://www.jodidata.org/oil/database/data-downloads.aspx ; https://www.worldometers.info/oil/ethiopia-oil/ | AD15: https://api.worldbank.org/v2/country/ETH/indicator/NY.GDP.MKTP.CD?format=json ; https://api.worldbank.org/v2/country/ETH/indicator/NY.GDP.MKTP.KD.ZG?format=json ; https://api.worldbank.org/v2/country/ETH/indicator/FP.CPI.TOTL.ZG?format=json ; Исходный источник: https://data.worldbank.org/ | AE15: https://www.globalpetrolprices.com/Ethiopia/gasoline_prices/ ; https://www.globalpetrolprices.com/Ethiopia/diesel_prices/ ; Исходный источник: GlobalPetrolPrices (страновые значения только там, где они были явно помечены как страновые); Jet/мазут: н/д | AF15: Массовые оценки/медианы удалены в ходе аудита. Сохранившиеся исходные числовые значения не считаются подтверждёнными автоматически; требуется первичная проверка источника. Обновление 16.09.2026: Потребление и доли: EIA, petroleum and other liquids, 2024; включает биотопливо. Jet/мазут: национальные сопоставимые цены не найдены; исходные значения сохранены. | AG15: Бензин: проверено GPP; Дизель: проверено GPP; LPG: н/д; Jet/керосин: нет сопоставимой национальной цены; Мазут: нет сопоставимой национальной цены | AH15: ET | AI15: ETH | AJ15: ='Сводка НПЗ'!D15 -> 0 | AK15: =IF('Сводка НПЗ'!F15>0,'Сводка НПЗ'!E15,"") | AL15: ='Сводка НПЗ'!G15 -> 0 | AM15: 2019-02-18 | AN15: Свежие число и мощность не подтверждены | AO15: 2024 | AP15: 2025 | AQ15: 2025 | AR15: 2026-09-16
A16: 15 | B16: South Sudan | C16: Южный Судан | D16: 11889.538 | E16: 2024 | F16: =IF(AND(ISNUMBER(D16),ISNUMBER(E16)),D16*(DATE(E16+1,1,1)-DATE(E16,1,1))/1000000,"н/д") -> 4.351571 | G16: 74.536213 | H16: 9.4696737 | I16: 0.82199162 | J16: 15.172122 | K16: 0 | L16: 112657.53 | M16: 2025 | N16: 112657.53 | O16: 0 | P16: 12 | Q16: 2024 | R16: -10.8 | S16: 2024 | T16: 91.440822 | U16: 2024 | V16: н/д | W16: н/д | X16: н/д | Y16: н/д | Z16: н/д | AA16: бензин/дизель/LPG/Jet: USD/л; мазут: USD/т | AB16: бензин: 2026-09-14; дизель/LPG: 2026-09-07; Jet/мазут: н/д | AC16: https://api.eia.gov/v2/international/data/?frequency=annual&facets[productId][]=53&facets[activityId][]=1&facets[unit][]=TBPD ; https://api.eia.gov/v2/international/data/?frequency=annual&facets[productId][]=57&facets[activityId][]=1&facets[unit][]=TBPD ; https://api.eia.gov/v2/international/data/?frequency=annual&facets[productId][]=58&facets[activityId][]=1&facets[unit][]=TBPD ; https://api.eia.gov/v2/international/data/?frequency=annual&facets[productId][]=5&facets[activityId][]=2&facets[unit][]=TBPD ; Исходный источник: https://www.jodidata.org/oil/database/data-downloads.aspx ; https://www.worldometers.info/oil/south-sudan-oil/ | AD16: https://api.worldbank.org/v2/country/SSD/indicator/NY.GDP.MKTP.CD?format=json ; https://api.worldbank.org/v2/country/SSD/indicator/NY.GDP.MKTP.KD.ZG?format=json ; https://api.worldbank.org/v2/country/SSD/indicator/FP.CPI.TOTL.ZG?format=json ; Исходный источник: https://data.worldbank.org/ | AE16: GlobalPetrolPrices (страновые значения только там, где они были явно помечены как страновые); Jet/мазут: н/д | AF16: Массовые оценки/медианы удалены в ходе аудита. Сохранившиеся исходные числовые значения не считаются подтверждёнными автоматически; требуется первичная проверка источника. Обновление 16.09.2026: Потребление и доли: EIA, petroleum and other liquids, 2024; включает биотопливо. Jet/мазут: национальные сопоставимые цены не найдены; исходные значения сохранены. | AG16: Бензин: н/д; Дизель: н/д; LPG: н/д; Jet/керосин: нет сопоставимой национальной цены; Мазут: нет сопоставимой национальной цены | AH16: SS | AI16: SSD | AJ16: ='Сводка НПЗ'!D16 -> 0 | AK16: =IF('Сводка НПЗ'!F16>0,'Сводка НПЗ'!E16,"") | AL16: ='Сводка НПЗ'!G16 -> 0 | AM16: 2019-02-18 | AN16: Свежие число и мощность не подтверждены | AO16: 2024 | AP16: 2025 | AQ16: 2025 | AR16: 2026-09-16
A17: 16 | B17: Somalia | C17: Сомали | D17: 11150.205 | E17: 2024 | F17: =IF(AND(ISNUMBER(D17),ISNUMBER(E17)),D17*(DATE(E17+1,1,1)-DATE(E17,1,1))/1000000,"н/д") -> 4.0809749 | G17: 34.96256 | H17: 19.602187 | I17: 3.3576896 | J17: 36.22718 | K17: 5.850384 | L17: 0 | M17: 2025 | N17: 0 | O17: 0 | P17: 12.9952 | Q17: 2025 | R17: 2.991144 | S17: 2025 | T17: н/д | U17: н/д | V17: н/д | W17: н/д | X17: н/д | Y17: н/д | Z17: н/д | AA17: бензин/дизель/LPG/Jet: USD/л; мазут: USD/т | AB17: бензин: 2026-09-14; дизель/LPG: 2026-09-07; Jet/мазут: н/д | AC17: https://api.eia.gov/v2/international/data/?frequency=annual&facets[productId][]=53&facets[activityId][]=1&facets[unit][]=TBPD ; https://api.eia.gov/v2/international/data/?frequency=annual&facets[productId][]=57&facets[activityId][]=1&facets[unit][]=TBPD ; https://api.eia.gov/v2/international/data/?frequency=annual&facets[productId][]=58&facets[activityId][]=1&facets[unit][]=TBPD ; https://api.eia.gov/v2/international/data/?frequency=annual&facets[productId][]=5&facets[activityId][]=2&facets[unit][]=TBPD ; Исходный источник: https://www.jodidata.org/oil/database/data-downloads.aspx ; https://www.worldometers.info/oil/somalia-oil/ | AD17: https://api.worldbank.org/v2/country/SOM/indicator/NY.GDP.MKTP.CD?format=json ; https://api.worldbank.org/v2/country/SOM/indicator/NY.GDP.MKTP.KD.ZG?format=json ; https://api.worldbank.org/v2/country/SOM/indicator/FP.CPI.TOTL.ZG?format=json ; Исходный источник: https://data.worldbank.org/ | AE17: GlobalPetrolPrices (страновые значения только там, где они были явно помечены как страновые); Jet/мазут: н/д | AF17: Массовые оценки/медианы удалены в ходе аудита. Сохранившиеся исходные числовые значения не считаются подтверждёнными автоматически; требуется первичная проверка источника. Обновление 16.09.2026: Потребление и доли: EIA, petroleum and other liquids, 2024; включает биотопливо. Jet/мазут: национальные сопоставимые цены не найдены; исходные значения сохранены. | AG17: Бензин: н/д; Дизель: н/д; LPG: н/д; Jet/керосин: нет сопоставимой национальной цены; Мазут: нет сопоставимой национальной цены | AH17: SO | AI17: SOM | AJ17: ='Сводка НПЗ'!D17 -> 0 | AK17: =IF('Сводка НПЗ'!F17>0,'Сводка НПЗ'!E17,"") | AL17: ='Сводка НПЗ'!G17 -> 0 | AM17: 2019-02-18 | AN17: Свежие число и мощность не подтверждены | AO17: 2024 | AP17: 2025 | AQ17: 2025 | AR17: 2026-09-16
A18: 17 | B18: Kenya | C18: Кения | D18: 116161.21 | E18: 2024 | F18: =IF(AND(ISNUMBER(D18),ISNUMBER(E18)),D18*(DATE(E18+1,1,1)-DATE(E18,1,1))/1000000,"н/д") -> 42.515001 | G18: 38.902149 | H18: 29.855817 | I18: 11.354084 | J18: 14.43898 | K18: 3.8170384 | L18: 0 | M18: 2025 | N18: 0 | O18: 0 | P18: 135.94128 | Q18: 2025 | R18: 4.6326109 | S18: 2025 | T18: 4.0691288 | U18: 2025 | V18: 1.642 | W18: 1.673 | X18: н/д | Y18: н/д | Z18: н/д | AA18: Бензин/дизель/LPG: USD/л; Jet/мазут: исходные единицы | AB18: Бензин: 2026-09-14; Дизель: 2026-09-14; исходные даты для непроверенных значений: бензин: 2026-09-14; дизель/LPG: 2026-09-07; Jet/мазут: н/д | AC18: https://api.eia.gov/v2/international/data/?frequency=annual&facets[productId][]=53&facets[activityId][]=1&facets[unit][]=TBPD ; https://api.eia.gov/v2/international/data/?frequency=annual&facets[productId][]=57&facets[activityId][]=1&facets[unit][]=TBPD ; https://api.eia.gov/v2/international/data/?frequency=annual&facets[productId][]=58&facets[activityId][]=1&facets[unit][]=TBPD ; https://api.eia.gov/v2/international/data/?frequency=annual&facets[productId][]=5&facets[activityId][]=2&facets[unit][]=TBPD ; Исходный источник: https://www.jodidata.org/oil/database/data-downloads.aspx ; https://www.worldometers.info/oil/kenya-oil/ | AD18: https://api.worldbank.org/v2/country/KEN/indicator/NY.GDP.MKTP.CD?format=json ; https://api.worldbank.org/v2/country/KEN/indicator/NY.GDP.MKTP.KD.ZG?format=json ; https://api.worldbank.org/v2/country/KEN/indicator/FP.CPI.TOTL.ZG?format=json ; Исходный источник: https://data.worldbank.org/ | AE18: https://www.globalpetrolprices.com/Kenya/gasoline_prices/ ; https://www.globalpetrolprices.com/Kenya/diesel_prices/ ; Исходный источник: GlobalPetrolPrices (страновые значения только там, где они были явно помечены как страновые); Jet/мазут: н/д | AF18: Массовые оценки/медианы удалены в ходе аудита. Сохранившиеся исходные числовые значения не считаются подтверждёнными автоматически; требуется первичная проверка источника. Обновление 16.09.2026: Потребление и доли: EIA, petroleum and other liquids, 2024; включает биотопливо. Jet/мазут: национальные сопоставимые цены не найдены; исходные значения сохранены. | AG18: Бензин: проверено GPP; Дизель: проверено GPP; LPG: н/д; Jet/керосин: нет сопоставимой национальной цены; Мазут: нет сопоставимой национальной цены | AH18: KE | AI18: KEN | AJ18: ='Сводка НПЗ'!D18 -> 1 | AK18: =IF('Сводка НПЗ'!F18>0,'Сводка НПЗ'!E18,"") -> 90000 | AL18: ='Сводка НПЗ'!G18 -> 0 | AM18: 2019-02-18 | AN18: Свежие число и мощность не подтверждены | AO18: 2024 | AP18: 2025 | AQ18: 2025 | AR18: 2026-09-16
A19: 18 | B19: Malawi | C19: Малави | D19: 10525.095 | E19: 2024 | F19: =IF(AND(ISNUMBER(D19),ISNUMBER(E19)),D19*(DATE(E19+1,1,1)-DATE(E19,1,1))/1000000,"н/д") -> 3.8521846 | G19: 48.585008 | H19: 45.723156 | I19: 0.621792 | J19: 1.0201678 | K19: 0.44624301 | L19: 0 | M19: 2025 | N19: 0 | O19: 0 | P19: 14.918277 | Q19: 2025 | R19: 1.8851871 | S19: 2025 | T19: 28.370257 | U19: 2025 | V19: 3.242 | W19: 3.383 | X19: н/д | Y19: н/д | Z19: н/д | AA19: Бензин/дизель/LPG: USD/л; Jet/мазут: исходные единицы | AB19: Бензин: 2026-09-14; Дизель: 2026-09-14; исходные даты для непроверенных значений: бензин: 2026-09-14; дизель/LPG: 2026-09-07; Jet/мазут: н/д | AC19: https://api.eia.gov/v2/international/data/?frequency=annual&facets[productId][]=53&facets[activityId][]=1&facets[unit][]=TBPD ; https://api.eia.gov/v2/international/data/?frequency=annual&facets[productId][]=57&facets[activityId][]=1&facets[unit][]=TBPD ; https://api.eia.gov/v2/international/data/?frequency=annual&facets[productId][]=58&facets[activityId][]=1&facets[unit][]=TBPD ; https://api.eia.gov/v2/international/data/?frequency=annual&facets[productId][]=5&facets[activityId][]=2&facets[unit][]=TBPD ; Исходный источник: https://www.jodidata.org/oil/database/data-downloads.aspx ; https://www.worldometers.info/oil/malawi-oil/ | AD19: https://api.worldbank.org/v2/country/MWI/indicator/NY.GDP.MKTP.CD?format=json ; https://api.worldbank.org/v2/country/MWI/indicator/NY.GDP.MKTP.KD.ZG?format=json ; https://api.worldbank.org/v2/country/MWI/indicator/FP.CPI.TOTL.ZG?format=json ; Исходный источник: https://data.worldbank.org/ | AE19: https://www.globalpetrolprices.com/Malawi/gasoline_prices/ ; https://www.globalpetrolprices.com/Malawi/diesel_prices/ ; Исходный источник: GlobalPetrolPrices (страновые значения только там, где они были явно помечены как страновые); Jet/мазут: н/д | AF19: Массовые оценки/медианы удалены в ходе аудита. Сохранившиеся исходные числовые значения не считаются подтверждёнными автоматически; требуется первичная проверка источника. Обновление 16.09.2026: Потребление и доли: EIA, petroleum and other liquids, 2024; включает биотопливо. Jet/мазут: национальные сопоставимые цены не найдены; исходные значения сохранены. | AG19: Бензин: проверено GPP; Дизель: проверено GPP; LPG: н/д; Jet/керосин: нет сопоставимой национальной цены; Мазут: нет сопоставимой национальной цены | AH19: MW | AI19: MWI | AJ19: ='Сводка НПЗ'!D19 -> 0 | AK19: =IF('Сводка НПЗ'!F19>0,'Сводка НПЗ'!E19,"") | AL19: ='Сводка НПЗ'!G19 -> 0 | AM19: 2019-02-18 | AN19: Свежие число и мощность не подтверждены | AO19: 2024 | AP19: 2025 | AQ19: 2025 | AR19: 2026-09-16
A20: 19 | B20: Tanzania | C20: Танзания | D20: 83535.87 | E20: 2024 | F20: =IF(AND(ISNUMBER(D20),ISNUMBER(E20)),D20*(DATE(E20+1,1,1)-DATE(E20,1,1))/1000000,"н/д") -> 30.574129 | G20: 46.477096 | H20: 32.906473 | I20: 14.227915 | J20: 4.743333 | K20: 1.4099548 | L20: 0 | M20: 2025 | N20: 0 | O20: 0 | P20: 90.143496 | Q20: 2025 | R20: 5.8528683 | S20: 2025 | T20: 3.3269736 | U20: 2025 | V20: 1.435 | W20: 1.465 | X20: н/д | Y20: н/д | Z20: н/д | AA20: Бензин/дизель/LPG: USD/л; Jet/мазут: исходные единицы | AB20: Бензин: 2026-09-14; Дизель: 2026-09-14; исходные даты для непроверенных значений: бензин: 2026-09-14; дизель/LPG: 2026-09-07; Jet/мазут: н/д | AC20: https://api.eia.gov/v2/international/data/?frequency=annual&facets[productId][]=53&facets[activityId][]=1&facets[unit][]=TBPD ; https://api.eia.gov/v2/international/data/?frequency=annual&facets[productId][]=57&facets[activityId][]=1&facets[unit][]=TBPD ; https://api.eia.gov/v2/international/data/?frequency=annual&facets[productId][]=58&facets[activityId][]=1&facets[unit][]=TBPD ; https://api.eia.gov/v2/international/data/?frequency=annual&facets[productId][]=5&facets[activityId][]=2&facets[unit][]=TBPD ; Исходный источник: https://www.jodidata.org/oil/database/data-downloads.aspx ; https://www.worldometers.info/oil/tanzania-oil/ | AD20: https://api.worldbank.org/v2/country/TZA/indicator/NY.GDP.MKTP.CD?format=json ; https://api.worldbank.org/v2/country/TZA/indicator/NY.GDP.MKTP.KD.ZG?format=json ; https://api.worldbank.org/v2/country/TZA/indicator/FP.CPI.TOTL.ZG?format=json ; Исходный источник: https://data.worldbank.org/ | AE20: https://www.globalpetrolprices.com/Tanzania/gasoline_prices/ ; https://www.globalpetrolprices.com/Tanzania/diesel_prices/ ; Исходный источник: GlobalPetrolPrices (страновые значения только там, где они были явно помечены как страновые); Jet/мазут: н/д | AF20: Массовые оценки/медианы удалены в ходе аудита. Сохранившиеся исходные числовые значения не считаются подтверждёнными автоматически; требуется первичная проверка источника. Обновление 16.09.2026: Потребление и доли: EIA, petroleum and other liquids, 2024; включает биотопливо. Jet/мазут: национальные сопоставимые цены не найдены; исходные значения сохранены. | AG20: Бензин: проверено GPP; Дизель: проверено GPP; LPG: н/д; Jet/керосин: нет сопоставимой национальной цены; Мазут: нет сопоставимой национальной цены | AH20: TZ | AI20: TZA | AJ20: ='Сводка НПЗ'!D20 -> 1 | AK20: =IF('Сводка НПЗ'!F20>0,'Сводка НПЗ'!E20,"") -> 14900 | AL20: ='Сводка НПЗ'!G20 -> 0 | AM20: 2019-02-18 | AN20: Свежие число и мощность не подтверждены | AO20: 2024 | AP20: 2025 | AQ20: 2025 | AR20: 2026-09-16
A21: 20 | B21: Syria | C21: Сирия | D21: 123816.55 | E21: 2024 | F21: =IF(AND(ISNUMBER(D21),ISNUMBER(E21)),D21*(DATE(E21+1,1,1)-DATE(E21,1,1))/1000000,"н/д") -> 45.316857 | G21: 29.446712 | H21: 16.730229 | I21: 11.25903 | J21: 1.3123757 | K21: 38.606684 | L21: 81234.655 | M21: 2025 | N21: 75246.575 | O21: 7690.5808 | P21: 23.62 | Q21: 2024 | R21: 0.7 | S21: 2024 | T21: 13.4 | U21: 2019 | V21: 1.299 | W21: 1.068 | X21: н/д | Y21: н/д | Z21: н/д | AA21: Бензин/дизель/LPG: USD/л; Jet/мазут: исходные единицы | AB21: Бензин: 2026-09-14; Дизель: 2026-09-14; исходные даты для непроверенных значений: бензин: 2026-09-14; дизель/LPG: 2026-09-07; Jet/мазут: н/д | AC21: https://api.eia.gov/v2/international/data/?frequency=annual&facets[productId][]=53&facets[activityId][]=1&facets[unit][]=TBPD ; https://api.eia.gov/v2/international/data/?frequency=annual&facets[productId][]=57&facets[activityId][]=1&facets[unit][]=TBPD ; https://api.eia.gov/v2/international/data/?frequency=annual&facets[productId][]=58&facets[activityId][]=1&facets[unit][]=TBPD ; https://api.eia.gov/v2/international/data/?frequency=annual&facets[productId][]=5&facets[activityId][]=2&facets[unit][]=TBPD ; Исходный источник: https://www.jodidata.org/oil/database/data-downloads.aspx ; https://www.worldometers.info/oil/syria-oil/ | AD21: https://data.worldbank.org/ | AE21: https://www.globalpetrolprices.com/Syria/gasoline_prices/ ; https://www.globalpetrolprices.com/Syria/diesel_prices/ ; Исходный источник: GlobalPetrolPrices (страновые значения только там, где они были явно помечены как страновые); Jet/мазут: н/д | AF21: Массовые оценки/медианы удалены в ходе аудита. Сохранившиеся исходные числовые значения не считаются подтверждёнными автоматически; требуется первичная проверка источника. Обновление 16.09.2026: Потребление и доли: EIA, petroleum and other liquids, 2024; включает биотопливо. Jet/мазут: национальные сопоставимые цены не найдены; исходные значения сохранены. | AG21: Бензин: проверено GPP; Дизель: проверено GPP; LPG: н/д; Jet/керосин: нет сопоставимой национальной цены; Мазут: нет сопоставимой национальной цены | AH21: SY | AI21: SYR | AJ21: ='Сводка НПЗ'!D21 -> 2 | AK21: =IF('Сводка НПЗ'!F21>0,'Сводка НПЗ'!E21,"") -> 239865 | AL21: ='Сводка НПЗ'!G21 -> 0 | AM21: 2019-02-18 | AN21: Свежие число и мощность не подтверждены | AO21: 2024 | AP21: 2025 | AQ21: 2025 | AR21: 2026-09-16
A22: 21 | B22: Somaliland | C22: Сомалиленд | D22: н/д | E22: н/д | F22: =IF(AND(ISNUMBER(D22),ISNUMBER(E22)),D22*(DATE(E22+1,1,1)-DATE(E22,1,1))/1000000,"н/д") -> н/д | G22: н/д | H22: н/д | I22: н/д | J22: н/д | K22: н/д | L22: н/д | M22: н/д | N22: н/д | O22: н/д | P22: н/д | Q22: н/д | R22: н/д | S22: н/д | T22: н/д | U22: н/д | V22: н/д | W22: н/д | X22: н/д | Y22: н/д | Z22: н/д | AA22: бензин/дизель/LPG/Jet: USD/л; мазут: USD/т | AB22: бензин: 2026-09-14; дизель/LPG: 2026-09-07; Jet/мазут: н/д | AC22: https://www.jodidata.org/oil/database/data-downloads.aspx | AD22: https://data.worldbank.org/ | AE22: GlobalPetrolPrices (страновые значения только там, где они были явно помечены как страновые); Jet/мазут: н/д | AF22: Массовые оценки/медианы удалены в ходе аудита. Сохранившиеся исходные числовые значения не считаются подтверждёнными автоматически; требуется первичная проверка источника. Обновление 16.09.2026: Потребление и доли: исходные значения, свежая сопоставимая серия не найдена. Jet/мазут: национальные сопоставимые цены не найдены; исходные значения сохранены. | AG22: Бензин: н/д; Дизель: н/д; LPG: н/д; Jet/керосин: нет сопоставимой национальной цены; Мазут: нет сопоставимой национальной цены | AH22: н/д | AI22: н/д | AJ22: ='Сводка НПЗ'!D22 -> 0 | AK22: =IF('Сводка НПЗ'!F22>0,'Сводка НПЗ'!E22,"") | AL22: ='Сводка НПЗ'!G22 -> 0 | AM22: 2019-02-18 | AN22: Свежие число и мощность не подтверждены | AR22: 2026-09-16
A23: 22 | B23: France | C23: Франция | D23: 1512298.6 | E23: 2025 | F23: =IF(AND(ISNUMBER(D23),ISNUMBER(E23)),D23*(DATE(E23+1,1,1)-DATE(E23,1,1))/1000000,"н/д") -> 551.989 | G23: 49.173462 | H23: 18.512298 | I23: 6.4389689 | J23: 22.826759 | K23: 1.519052 | L23: 105888.77 | M23: 2025 | N23: 10221.83 | O23: 0 | P23: 3366.3159 | Q23: 2025 | R23: 0.84094996 | S23: 2025 | T23: 0.94377021 | U23: 2025 | V23: 2.425 | W23: 2.664 | X23: н/д | Y23: 1.192 | Z23: н/д | AA23: Бензин/дизель/LPG: USD/л; Jet/мазут: исходные единицы | AB23: Бензин: 2026-09-14; Дизель: 2026-09-14; LPG: 2026-09-14; исходные даты для непроверенных значений: бензин: 2026-09-14; дизель/LPG: 2026-09-07; Jet/мазут: н/д | AC23: https://api.eia.gov/v2/international/data/?frequency=annual&facets[productId][]=53&facets[activityId][]=1&facets[unit][]=TBPD ; https://api.eia.gov/v2/international/data/?frequency=annual&facets[productId][]=57&facets[activityId][]=1&facets[unit][]=TBPD ; https://api.eia.gov/v2/international/data/?frequency=annual&facets[productId][]=58&facets[activityId][]=1&facets[unit][]=TBPD ; https://www.jodidata.org/_resources/files/downloads/oil-data/annual-csv/secondary/2025.csv ; Исходный источник: https://www.jodidata.org/oil/database/data-downloads.aspx ; https://www.worldometers.info/oil/france-oil/ | AD23: https://api.worldbank.org/v2/country/FRA/indicator/NY.GDP.MKTP.CD?format=json ; https://api.worldbank.org/v2/country/FRA/indicator/NY.GDP.MKTP.KD.ZG?format=json ; https://api.worldbank.org/v2/country/FRA/indicator/FP.CPI.TOTL.ZG?format=json ; Исходный источник: https://data.worldbank.org/ | AE23: https://www.globalpetrolprices.com/France/gasoline_prices/ ; https://www.globalpetrolprices.com/France/diesel_prices/ ; https://www.globalpetrolprices.com/France/lpg_prices/ ; Исходный источник: GlobalPetrolPrices (страновые значения только там, где они были явно помечены как страновые); Jet/мазут: н/д | AF23: Массовые оценки/медианы удалены в ходе аудита. Сохранившиеся исходные числовые значения не считаются подтверждёнными автоматически; требуется первичная проверка источника. Обновление 16.09.2026: Потребление и доли: JODI, нефтепродукты TOTPRODS, 12 месяцев 2025. Jet/мазут: национальные сопоставимые цены не найдены; исходные значения сохранены. | AG23: Бензин: проверено GPP; Дизель: проверено GPP; LPG: проверено GPP; Jet/керосин: нет сопоставимой национальной цены; Мазут: нет сопоставимой национальной цены | AH23: FR | AI23: FRA | AJ23: ='Сводка НПЗ'!D23 -> 14 | AK23: =IF('Сводка НПЗ'!F23>0,'Сводка НПЗ'!E23,"") -> 2075000 | AL23: ='Сводка НПЗ'!G23 -> 1 | AM23: 2019-02-18 | AN23: Проверен первичный источник; см. охват | AO23: 2025 | AP23: 2025 | AQ23: 2025 | AR23: 2026-09-16
A24: 23 | B24: Suriname | C24: Суринам | D24: 14772.43 | E24: 2024 | F24: =IF(AND(ISNUMBER(D24),ISNUMBER(E24)),D24*(DATE(E24+1,1,1)-DATE(E24,1,1))/1000000,"н/д") -> 5.4067095 | G24: 43.899514 | H24: 32.881618 | I24: 5.1844541 | J24: 6.6453751 | K24: 9.9219725 | L24: 11659.956 | M24: 2025 | N24: 12089.451 | O24: 0 | P24: 4.5236578 | Q24: 2025 | R24: 1.7916915 | S24: 2025 | T24: 9.2054682 | U24: 2025 | V24: 1.28 | W24: 1.411 | X24: н/д | Y24: н/д | Z24: н/д | AA24: Бензин/дизель/LPG: USD/л; Jet/мазут: исходные единицы | AB24: Бензин: 2026-09-14; Дизель: 2026-09-14; исходные даты для непроверенных значений: бензин: 2026-09-14; дизель/LPG: 2026-09-07; Jet/мазут: н/д | AC24: https://api.eia.gov/v2/international/data/?frequency=annual&facets[productId][]=53&facets[activityId][]=1&facets[unit][]=TBPD ; https://api.eia.gov/v2/international/data/?frequency=annual&facets[productId][]=57&facets[activityId][]=1&facets[unit][]=TBPD ; https://api.eia.gov/v2/international/data/?frequency=annual&facets[productId][]=58&facets[activityId][]=1&facets[unit][]=TBPD ; https://api.eia.gov/v2/international/data/?frequency=annual&facets[productId][]=5&facets[activityId][]=2&facets[unit][]=TBPD ; Исходный источник: https://www.jodidata.org/oil/database/data-downloads.aspx ; https://www.worldometers.info/oil/suriname-oil/ | AD24: https://api.worldbank.org/v2/country/SUR/indicator/NY.GDP.MKTP.CD?format=json ; https://api.worldbank.org/v2/country/SUR/indicator/NY.GDP.MKTP.KD.ZG?format=json ; https://api.worldbank.org/v2/country/SUR/indicator/FP.CPI.TOTL.ZG?format=json ; Исходный источник: https://data.worldbank.org/ | AE24: https://www.globalpetrolprices.com/Suriname/gasoline_prices/ ; https://www.globalpetrolprices.com/Suriname/diesel_prices/ ; Исходный источник: GlobalPetrolPrices (страновые значения только там, где они были явно помечены как страновые); Jet/мазут: н/д | AF24: Массовые оценки/медианы удалены в ходе аудита. Сохранившиеся исходные числовые значения не считаются подтверждёнными автоматически; требуется первичная проверка источника. Обновление 16.09.2026: Потребление и доли: EIA, petroleum and other liquids, 2024; включает биотопливо. Jet/мазут: национальные сопоставимые цены не найдены; исходные значения сохранены. | AG24: Бензин: проверено GPP; Дизель: проверено GPP; LPG: н/д; Jet/керосин: нет сопоставимой национальной цены; Мазут: нет сопоставимой национальной цены | AH24: SR | AI24: SUR | AJ24: ='Сводка НПЗ'!D24 -> 1 | AK24: =IF('Сводка НПЗ'!F24>0,'Сводка НПЗ'!E24,"") -> 7000 | AL24: ='Сводка НПЗ'!G24 -> 0 | AM24: 2019-02-18 | AN24: Свежие число и мощность не подтверждены | AO24: 2024 | AP24: 2025 | AQ24: 2025 | AR24: 2026-09-16
A25: 24 | B25: Guyana | C25: Гайана | D25: 26760.004 | E25: 2024 | F25: =IF(AND(ISNUMBER(D25),ISNUMBER(E25)),D25*(DATE(E25+1,1,1)-DATE(E25,1,1))/1000000,"н/д") -> 9.7941613 | G25: 48.208332 | H25: 26.158059 | I25: 3.2432061 | J25: 2.1499594 | K25: 18.659559 | L25: 747432.14 | M25: 2025 | N25: 747432.14 | O25: 0 | P25: 27.097477 | Q25: 2025 | R25: 19.33601 | S25: 2025 | T25: 3.3298234 | U25: 2025 | V25: 1.092 | W25: 1.14 | X25: н/д | Y25: н/д | Z25: н/д | AA25: Бензин/дизель/LPG: USD/л; Jet/мазут: исходные единицы | AB25: Бензин: 2026-09-14; Дизель: 2026-09-14; исходные даты для непроверенных значений: бензин: 2026-09-14; дизель/LPG: 2026-09-07; Jet/мазут: н/д | AC25: https://api.eia.gov/v2/international/data/?frequency=annual&facets[productId][]=53&facets[activityId][]=1&facets[unit][]=TBPD ; https://api.eia.gov/v2/international/data/?frequency=annual&facets[productId][]=57&facets[activityId][]=1&facets[unit][]=TBPD ; https://api.eia.gov/v2/international/data/?frequency=annual&facets[productId][]=58&facets[activityId][]=1&facets[unit][]=TBPD ; https://api.eia.gov/v2/international/data/?frequency=annual&facets[productId][]=5&facets[activityId][]=2&facets[unit][]=TBPD ; Исходный источник: https://www.jodidata.org/oil/database/data-downloads.aspx ; https://www.worldometers.info/oil/guyana-oil/ | AD25: https://api.worldbank.org/v2/country/GUY/indicator/NY.GDP.MKTP.CD?format=json ; https://api.worldbank.org/v2/country/GUY/indicator/NY.GDP.MKTP.KD.ZG?format=json ; https://api.worldbank.org/v2/country/GUY/indicator/FP.CPI.TOTL.ZG?format=json ; Исходный источник: https://data.worldbank.org/ | AE25: https://www.globalpetrolprices.com/Guyana/gasoline_prices/ ; https://www.globalpetrolprices.com/Guyana/diesel_prices/ ; Исходный источник: GlobalPetrolPrices (страновые значения только там, где они были явно помечены как страновые); Jet/мазут: н/д | AF25: Массовые оценки/медианы удалены в ходе аудита. Сохранившиеся исходные числовые значения не считаются подтверждёнными автоматически; требуется первичная проверка источника. Обновление 16.09.2026: Потребление и доли: EIA, petroleum and other liquids, 2024; включает биотопливо. Jet/мазут: национальные сопоставимые цены не найдены; исходные значения сохранены. | AG25: Бензин: проверено GPP; Дизель: проверено GPP; LPG: н/д; Jet/керосин: нет сопоставимой национальной цены; Мазут: нет сопоставимой национальной цены | AH25: GY | AI25: GUY | AJ25: ='Сводка НПЗ'!D25 -> 0 | AK25: =IF('Сводка НПЗ'!F25>0,'Сводка НПЗ'!E25,"") | AL25: ='Сводка НПЗ'!G25 -> 0 | AM25: 2019-02-18 | AN25: Свежие число и мощность не подтверждены | AO25: 2024 | AP25: 2025 | AQ25: 2025 | AR25: 2026-09-16
A26: 25 | B26: South Korea | C26: Республика Корея | D26: 2832032.9 | E26: 2025 | F26: =IF(AND(ISNUMBER(D26),ISNUMBER(E26)),D26*(DATE(E26+1,1,1)-DATE(E26,1,1))/1000000,"н/д") -> 1033.692 | G26: 15.293948 | H26: 9.3552635 | I26: 12.468666 | J26: 12.550624 | K26: 6.4841597 | L26: 110659.66 | M26: 2025 | N26: 0 | O26: 0 | P26: 1872.375 | Q26: 2025 | R26: 1.0070184 | S26: 2025 | T26: 2.1230942 | U26: 2025 | V26: 1.413 | W26: 1.401 | X26: н/д | Y26: 0.835 | Z26: н/д | AA26: Бензин/дизель/LPG: USD/л; Jet/мазут: исходные единицы | AB26: Бензин: 2026-09-14; Дизель: 2026-09-14; LPG: 2026-09-14; исходные даты для непроверенных значений: бензин: 2026-09-14; дизель/LPG: 2026-09-07; Jet/мазут: н/д | AC26: https://api.eia.gov/v2/international/data/?frequency=annual&facets[productId][]=53&facets[activityId][]=1&facets[unit][]=TBPD ; https://api.eia.gov/v2/international/data/?frequency=annual&facets[productId][]=57&facets[activityId][]=1&facets[unit][]=TBPD ; https://api.eia.gov/v2/international/data/?frequency=annual&facets[productId][]=58&facets[activityId][]=1&facets[unit][]=TBPD ; https://www.jodidata.org/_resources/files/downloads/oil-data/annual-csv/secondary/2025.csv ; Исходный источник: https://www.jodidata.org/oil/database/data-downloads.aspx ; https://www.worldometers.info/oil/south-korea-oil/ | AD26: https://api.worldbank.org/v2/country/KOR/indicator/NY.GDP.MKTP.CD?format=json ; https://api.worldbank.org/v2/country/KOR/indicator/NY.GDP.MKTP.KD.ZG?format=json ; https://api.worldbank.org/v2/country/KOR/indicator/FP.CPI.TOTL.ZG?format=json ; Исходный источник: https://data.worldbank.org/ | AE26: https://www.globalpetrolprices.com/South-Korea/gasoline_prices/ ; https://www.globalpetrolprices.com/South-Korea/diesel_prices/ ; https://www.globalpetrolprices.com/South-Korea/lpg_prices/ ; Исходный источник: GlobalPetrolPrices (страновые значения только там, где они были явно помечены как страновые); Jet/мазут: н/д | AF26: Массовые оценки/медианы удалены в ходе аудита. Сохранившиеся исходные числовые значения не считаются подтверждёнными автоматически; требуется первичная проверка источника. Обновление 16.09.2026: Потребление и доли: JODI, нефтепродукты TOTPRODS, 12 месяцев 2025. Jet/мазут: национальные сопоставимые цены не найдены; исходные значения сохранены. | AG26: Бензин: проверено GPP; Дизель: проверено GPP; LPG: проверено GPP; Jet/керосин: нет сопоставимой национальной цены; Мазут: нет сопоставимой национальной цены | AH26: KR | AI26: KOR | AJ26: ='Сводка НПЗ'!D26 -> 6 | AK26: =IF('Сводка НПЗ'!F26>0,'Сводка НПЗ'!E26,"") -> 2654500 | AL26: ='Сводка НПЗ'!G26 -> 0 | AM26: 2019-02-18 | AN26: Мощность: вторичная публикация EI; число НПЗ не подтверждено | AO26: 2025 | AP26: 2025 | AQ26: 2025 | AR26: 2026-09-16
A27: 26 | B27: North Korea | C27: КНДР | D27: 18921.402 | E27: 2024 | F27: =IF(AND(ISNUMBER(D27),ISNUMBER(E27)),D27*(DATE(E27+1,1,1)-DATE(E27,1,1))/1000000,"н/д") -> 6.9252331 | G27: 27.435143 | H27: 24.257936 | I27: 0.089724573 | J27: 4.4867125 | K27: 43.730483 | L27: 101.15509 | M27: 2025 | N27: 0 | O27: 0 | P27: н/д | Q27: н/д | R27: н/д | S27: н/д | T27: н/д | U27: н/д | V27: н/д | W27: н/д | X27: н/д | Y27: н/д | Z27: н/д | AA27: бензин/дизель/LPG/Jet: USD/л; мазут: USD/т | AB27: бензин: 2026-09-14; дизель/LPG: 2026-09-07; Jet/мазут: н/д | AC27: https://api.eia.gov/v2/international/data/?frequency=annual&facets[productId][]=53&facets[activityId][]=1&facets[unit][]=TBPD ; https://api.eia.gov/v2/international/data/?frequency=annual&facets[productId][]=57&facets[activityId][]=1&facets[unit][]=TBPD ; https://api.eia.gov/v2/international/data/?frequency=annual&facets[productId][]=58&facets[activityId][]=1&facets[unit][]=TBPD ; https://api.eia.gov/v2/international/data/?frequency=annual&facets[productId][]=5&facets[activityId][]=2&facets[unit][]=TBPD ; Исходный источник: https://www.jodidata.org/oil/database/data-downloads.aspx ; https://www.worldometers.info/oil/north-korea-oil/ | AD27: https://data.worldbank.org/ | AE27: GlobalPetrolPrices (страновые значения только там, где они были явно помечены как страновые); Jet/мазут: н/д | AF27: Массовые оценки/медианы удалены в ходе аудита. Сохранившиеся исходные числовые значения не считаются подтверждёнными автоматически; требуется первичная проверка источника. Обновление 16.09.2026: Потребление и доли: EIA, petroleum and other liquids, 2024; включает биотопливо. Jet/мазут: национальные сопоставимые цены не найдены; исходные значения сохранены. | AG27: Бензин: н/д; Дизель: н/д; LPG: н/д; Jet/керосин: нет сопоставимой национальной цены; Мазут: нет сопоставимой национальной цены | AH27: KP | AI27: PRK | AJ27: ='Сводка НПЗ'!D27 -> 2 | AK27: =IF('Сводка НПЗ'!F27>0,'Сводка НПЗ'!E27,"") -> 45000 | AL27: ='Сводка НПЗ'!G27 -> 1 | AM27: 2019-02-18 | AN27: Свежие число и мощность не подтверждены | AO27: 2024 | AP27: 2025 | AQ27: 2025 | AR27: 2026-09-16
A28: 27 | B28: Morocco | C28: Марокко | D28: 330769.86 | E28: 2025 | F28: =IF(AND(ISNUMBER(D28),ISNUMBER(E28)),D28*(DATE(E28+1,1,1)-DATE(E28,1,1))/1000000,"н/д") -> 120.731 | G28: 40.888753 | H28: 6.1744705 | I28: 29.794833 | J28: 13.31103 | K28: 6.3691181 | L28: 25 | M28: 2025 | N28: 25 | O28: 0 | P28: 182.37425 | Q28: 2025 | R28: 4.5952435 | S28: 2025 | T28: 0.70190215 | U28: 2025 | V28: 1.582 | W28: 1.59 | X28: н/д | Y28: н/д | Z28: н/д | AA28: Бензин/дизель/LPG: USD/л; Jet/мазут: исходные единицы | AB28: Бензин: 2026-09-14; Дизель: 2026-09-14; исходные даты для непроверенных значений: бензин: 2026-09-14; дизель/LPG: 2026-09-07; Jet/мазут: н/д | AC28: https://api.eia.gov/v2/international/data/?frequency=annual&facets[productId][]=53&facets[activityId][]=1&facets[unit][]=TBPD ; https://api.eia.gov/v2/international/data/?frequency=annual&facets[productId][]=57&facets[activityId][]=1&facets[unit][]=TBPD ; https://api.eia.gov/v2/international/data/?frequency=annual&facets[productId][]=58&facets[activityId][]=1&facets[unit][]=TBPD ; https://www.jodidata.org/_resources/files/downloads/oil-data/annual-csv/secondary/2025.csv ; Исходный источник: https://www.jodidata.org/oil/database/data-downloads.aspx ; https://www.worldometers.info/oil/morocco-oil/ | AD28: https://api.worldbank.org/v2/country/MAR/indicator/NY.GDP.MKTP.CD?format=json ; https://api.worldbank.org/v2/country/MAR/indicator/NY.GDP.MKTP.KD.ZG?format=json ; https://api.worldbank.org/v2/country/MAR/indicator/FP.CPI.TOTL.ZG?format=json ; Исходный источник: https://data.worldbank.org/ | AE28: https://www.globalpetrolprices.com/Morocco/gasoline_prices/ ; https://www.globalpetrolprices.com/Morocco/diesel_prices/ ; Исходный источник: GlobalPetrolPrices (страновые значения только там, где они были явно помечены как страновые); Jet/мазут: н/д | AF28: Массовые оценки/медианы удалены в ходе аудита. Сохранившиеся исходные числовые значения не считаются подтверждёнными автоматически; требуется первичная проверка источника. Обновление 16.09.2026: Потребление и доли: JODI, нефтепродукты TOTPRODS, 12 месяцев 2025. Jet/мазут: национальные сопоставимые цены не найдены; исходные значения сохранены. | AG28: Бензин: проверено GPP; Дизель: проверено GPP; LPG: н/д; Jet/керосин: нет сопоставимой национальной цены; Мазут: нет сопоставимой национальной цены | AH28: MA | AI28: MAR | AJ28: ='Сводка НПЗ'!D28 -> 2 | AK28: =IF('Сводка НПЗ'!F28>0,'Сводка НПЗ'!E28,"") -> 154900 | AL28: ='Сводка НПЗ'!G28 -> 0 | AM28: 2019-02-18 | AN28: Свежие число и мощность не подтверждены | AO28: 2025 | AP28: 2025 | AQ28: 2025 | AR28: 2026-09-16
A29: 28 | B29: Western Sahara | C29: Западная Сахара | D29: 1979.2619 | E29: 2024 | F29: =IF(AND(ISNUMBER(D29),ISNUMBER(E29)),D29*(DATE(E29+1,1,1)-DATE(E29,1,1))/1000000,"н/д") -> 0.72440987 | G29: 53.864543 | H29: 8.031924 | I29: 0 | J29: 9.8307319 | K29: 22.996441 | L29: 0 | M29: 2025 | N29: 0 | O29: 0 | P29: н/д | Q29: н/д | R29: н/д | S29: н/д | T29: н/д | U29: н/д | V29: н/д | W29: н/д | X29: н/д | Y29: н/д | Z29: н/д | AA29: бензин/дизель/LPG/Jet: USD/л; мазут: USD/т | AB29: бензин: 2026-09-14; дизель/LPG: 2026-09-07; Jet/мазут: н/д | AC29: https://api.eia.gov/v2/international/data/?frequency=annual&facets[productId][]=53&facets[activityId][]=1&facets[unit][]=TBPD ; https://api.eia.gov/v2/international/data/?frequency=annual&facets[productId][]=57&facets[activityId][]=1&facets[unit][]=TBPD ; https://api.eia.gov/v2/international/data/?frequency=annual&facets[productId][]=58&facets[activityId][]=1&facets[unit][]=TBPD ; https://api.eia.gov/v2/international/data/?frequency=annual&facets[productId][]=5&facets[activityId][]=2&facets[unit][]=TBPD ; Исходный источник: https://www.jodidata.org/oil/database/data-downloads.aspx ; https://www.worldometers.info/oil/western-sahara-oil/ | AD29: https://data.worldbank.org/ | AE29: GlobalPetrolPrices (страновые значения только там, где они были явно помечены как страновые); Jet/мазут: н/д | AF29: Массовые оценки/медианы удалены в ходе аудита. Сохранившиеся исходные числовые значения не считаются подтверждёнными автоматически; требуется первичная проверка источника. Обновление 16.09.2026: Потребление и доли: EIA, petroleum and other liquids, 2024; включает биотопливо. Jet/мазут: национальные сопоставимые цены не найдены; исходные значения сохранены. | AG29: Бензин: н/д; Дизель: н/д; LPG: н/д; Jet/керосин: нет сопоставимой национальной цены; Мазут: нет сопоставимой национальной цены | AH29: EH | AI29: ESH | AJ29: ='Сводка НПЗ'!D29 -> 0 | AK29: =IF('Сводка НПЗ'!F29>0,'Сводка НПЗ'!E29,"") | AL29: ='Сводка НПЗ'!G29 -> 0 | AM29: 2019-02-18 | AN29: Свежие число и мощность не подтверждены | AO29: 2024 | AP29: 2025 | AQ29: 2025 | AR29: 2026-09-16
A30: 29 | B30: Costa Rica | C30: Коста-Рика | D30: 64988 | E30: 2024 | F30: =IF(AND(ISNUMBER(D30),ISNUMBER(E30)),D30*(DATE(E30+1,1,1)-DATE(E30,1,1))/1000000,"н/д") -> 23.785608 | G30: 35.129014 | H30: 36.283917 | I30: 11.051988 | J30: 8.4914307 | K30: 5.2503687 | L30: 400 | M30: 2025 | N30: 0 | O30: 0 | P30: 102.90492 | Q30: 2025 | R30: 4.5603355 | S30: 2025 | T30: -0.073671441 | U30: 2025 | V30: 1.625 | W30: 1.54 | X30: н/д | Y30: н/д | Z30: н/д | AA30: Бензин/дизель/LPG: USD/л; Jet/мазут: исходные единицы | AB30: Бензин: 2026-09-14; Дизель: 2026-09-14; исходные даты для непроверенных значений: бензин: 2026-09-14; дизель/LPG: 2026-09-07; Jet/мазут: н/д | AC30: https://api.eia.gov/v2/international/data/?frequency=annual&facets[productId][]=53&facets[activityId][]=1&facets[unit][]=TBPD ; https://api.eia.gov/v2/international/data/?frequency=annual&facets[productId][]=57&facets[activityId][]=1&facets[unit][]=TBPD ; https://api.eia.gov/v2/international/data/?frequency=annual&facets[productId][]=58&facets[activityId][]=1&facets[unit][]=TBPD ; https://api.eia.gov/v2/international/data/?frequency=annual&facets[productId][]=5&facets[activityId][]=2&facets[unit][]=TBPD ; Исходный источник: https://www.jodidata.org/oil/database/data-downloads.aspx ; https://www.worldometers.info/oil/costa-rica-oil/ | AD30: https://api.worldbank.org/v2/country/CRI/indicator/NY.GDP.MKTP.CD?format=json ; https://api.worldbank.org/v2/country/CRI/indicator/NY.GDP.MKTP.KD.ZG?format=json ; https://api.worldbank.org/v2/country/CRI/indicator/FP.CPI.TOTL.ZG?format=json ; Исходный источник: https://data.worldbank.org/ | AE30: https://www.globalpetrolprices.com/Costa-Rica/gasoline_prices/ ; https://www.globalpetrolprices.com/Costa-Rica/diesel_prices/ ; Исходный источник: GlobalPetrolPrices (страновые значения только там, где они были явно помечены как страновые); Jet/мазут: н/д | AF30: Массовые оценки/медианы удалены в ходе аудита. Сохранившиеся исходные числовые значения не считаются подтверждёнными автоматически; требуется первичная проверка источника. Обновление 16.09.2026: Потребление и доли: EIA, petroleum and other liquids, 2024; включает биотопливо. Jet/мазут: национальные сопоставимые цены не найдены; исходные значения сохранены. | AG30: Бензин: проверено GPP; Дизель: проверено GPP; LPG: н/д; Jet/керосин: нет сопоставимой национальной цены; Мазут: нет сопоставимой национальной цены | AH30: CR | AI30: CRI | AJ30: ='Сводка НПЗ'!D30 -> 1 | AK30: =IF('Сводка НПЗ'!F30>0,'Сводка НПЗ'!E30,"") -> 25000 | AL30: ='Сводка НПЗ'!G30 -> 0 | AM30: 2019-02-18 | AN30: Свежие число и мощность не подтверждены | AO30: 2024 | AP30: 2025 | AQ30: 2025 | AR30: 2026-09-16
A31: 30 | B31: Nicaragua | C31: Никарагуа | D31: 35626.248 | E31: 2024 | F31: =IF(AND(ISNUMBER(D31),ISNUMBER(E31)),D31*(DATE(E31+1,1,1)-DATE(E31,1,1))/1000000,"н/д") -> 13.039207 | G31: 35.971216 | H31: 20.79491 | I31: 13.202873 | J31: 1.8295454 | K31: 21.870105 | L31: -1.1756338 | M31: 2025 | N31: 0 | O31: 0 | P31: 22.237167 | Q31: 2025 | R31: 4.9235256 | S31: 2025 | T31: 2.0813213 | U31: 2025 | V31: 1.333 | W31: 1.176 | X31: н/д | Y31: н/д | Z31: н/д | AA31: Бензин/дизель/LPG: USD/л; Jet/мазут: исходные единицы | AB31: Бензин: 2026-09-14; Дизель: 2026-09-14; исходные даты для непроверенных значений: бензин: 2026-09-14; дизель/LPG: 2026-09-07; Jet/мазут: н/д | AC31: https://api.eia.gov/v2/international/data/?frequency=annual&facets[productId][]=53&facets[activityId][]=1&facets[unit][]=TBPD ; https://api.eia.gov/v2/international/data/?frequency=annual&facets[productId][]=57&facets[activityId][]=1&facets[unit][]=TBPD ; https://api.eia.gov/v2/international/data/?frequency=annual&facets[productId][]=58&facets[activityId][]=1&facets[unit][]=TBPD ; https://api.eia.gov/v2/international/data/?frequency=annual&facets[productId][]=5&facets[activityId][]=2&facets[unit][]=TBPD ; Исходный источник: https://www.jodidata.org/oil/database/data-downloads.aspx ; https://www.worldometers.info/oil/nicaragua-oil/ | AD31: https://api.worldbank.org/v2/country/NIC/indicator/NY.GDP.MKTP.CD?format=json ; https://api.worldbank.org/v2/country/NIC/indicator/NY.GDP.MKTP.KD.ZG?format=json ; https://api.worldbank.org/v2/country/NIC/indicator/FP.CPI.TOTL.ZG?format=json ; Исходный источник: https://data.worldbank.org/ | AE31: https://www.globalpetrolprices.com/Nicaragua/gasoline_prices/ ; https://www.globalpetrolprices.com/Nicaragua/diesel_prices/ ; Исходный источник: GlobalPetrolPrices (страновые значения только там, где они были явно помечены как страновые); Jet/мазут: н/д | AF31: Массовые оценки/медианы удалены в ходе аудита. Сохранившиеся исходные числовые значения не считаются подтверждёнными автоматически; требуется первичная проверка источника. Обновление 16.09.2026: Потребление и доли: EIA, petroleum and other liquids, 2024; включает биотопливо. Jet/мазут: национальные сопоставимые цены не найдены; исходные значения сохранены. | AG31: Бензин: проверено GPP; Дизель: проверено GPP; LPG: н/д; Jet/керосин: нет сопоставимой национальной цены; Мазут: нет сопоставимой национальной цены | AH31: NI | AI31: NIC | AJ31: ='Сводка НПЗ'!D31 -> 1 | AK31: =IF('Сводка НПЗ'!F31>0,'Сводка НПЗ'!E31,"") -> 20000 | AL31: ='Сводка НПЗ'!G31 -> 0 | AM31: 2019-02-18 | AN31: Свежие число и мощность не подтверждены | AO31: 2024 | AP31: 2025 | AQ31: 2025 | AR31: 2026-09-16
A32: 31 | B32: Republic of the Congo | C32: Республика Конго | D32: 14100.282 | E32: 2024 | F32: =IF(AND(ISNUMBER(D32),ISNUMBER(E32)),D32*(DATE(E32+1,1,1)-DATE(E32,1,1))/1000000,"н/д") -> 5.1607033 | G32: 51.222497 | H32: 35.990487 | I32: 2.3086645 | J32: 7.4177787 | K32: 0.13254922 | L32: 249033.31 | M32: 2025 | N32: 241235.62 | O32: 8000 | P32: 16.306634 | Q32: 2025 | R32: 3.0829273 | S32: 2025 | T32: 2.4006956 | U32: 2025 | V32: н/д | W32: н/д | X32: н/д | Y32: н/д | Z32: н/д | AA32: бензин/дизель/LPG/Jet: USD/л; мазут: USD/т | AB32: бензин: 2026-09-14; дизель/LPG: 2026-09-07; Jet/мазут: н/д | AC32: https://api.eia.gov/v2/international/data/?frequency=annual&facets[productId][]=53&facets[activityId][]=1&facets[unit][]=TBPD ; https://api.eia.gov/v2/international/data/?frequency=annual&facets[productId][]=57&facets[activityId][]=1&facets[unit][]=TBPD ; https://api.eia.gov/v2/international/data/?frequency=annual&facets[productId][]=58&facets[activityId][]=1&facets[unit][]=TBPD ; https://api.eia.gov/v2/international/data/?frequency=annual&facets[productId][]=5&facets[activityId][]=2&facets[unit][]=TBPD ; Исходный источник: https://www.jodidata.org/oil/database/data-downloads.aspx ; https://www.worldometers.info/oil/congo-oil/ | AD32: https://api.worldbank.org/v2/country/COG/indicator/NY.GDP.MKTP.CD?format=json ; https://api.worldbank.org/v2/country/COG/indicator/NY.GDP.MKTP.KD.ZG?format=json ; https://api.worldbank.org/v2/country/COG/indicator/FP.CPI.TOTL.ZG?format=json ; Исходный источник: https://data.worldbank.org/ | AE32: GlobalPetrolPrices (страновые значения только там, где они были явно помечены как страновые); Jet/мазут: н/д | AF32: Массовые оценки/медианы удалены в ходе аудита. Сохранившиеся исходные числовые значения не считаются подтверждёнными автоматически; требуется первичная проверка источника. Обновление 16.09.2026: Потребление и доли: EIA, petroleum and other liquids, 2024; включает биотопливо. Jet/мазут: национальные сопоставимые цены не найдены; исходные значения сохранены. | AG32: Бензин: н/д; Дизель: н/д; LPG: н/д; Jet/керосин: нет сопоставимой национальной цены; Мазут: нет сопоставимой национальной цены | AH32: CG | AI32: COG | AJ32: ='Сводка НПЗ'!D32 -> 1 | AK32: =IF('Сводка НПЗ'!F32>0,'Сводка НПЗ'!E32,"") -> 21000 | AL32: ='Сводка НПЗ'!G32 -> 0 | AM32: 2019-02-18 | AN32: Свежие число и мощность не подтверждены | AO32: 2024 | AP32: 2025 | AQ32: 2025 | AR32: 2026-09-16
A33: 32 | B33: Democratic Republic of the Congo | C33: Демократическая Республика Конго | D33: 25052.996 | E33: 2024 | F33: =IF(AND(ISNUMBER(D33),ISNUMBER(E33)),D33*(DATE(E33+1,1,1)-DATE(E33,1,1))/1000000,"н/д") -> 9.1693966 | G33: 57.039449 | H33: 34.281457 | I33: 0 | J33: 7.1019722 | K33: 1.342031 | L33: 16000 | M33: 2025 | N33: 16000 | O33: 0 | P33: 91.030531 | Q33: 2025 | R33: 5.7592447 | S33: 2025 | T33: н/д | U33: н/д | V33: 1.146 | W33: 1.139 | X33: н/д | Y33: н/д | Z33: н/д | AA33: Бензин/дизель/LPG: USD/л; Jet/мазут: исходные единицы | AB33: Бензин: 2026-09-14; Дизель: 2026-09-14; исходные даты для непроверенных значений: бензин: 2026-09-14; дизель/LPG: 2026-09-07; Jet/мазут: н/д | AC33: https://api.eia.gov/v2/international/data/?frequency=annual&facets[productId][]=53&facets[activityId][]=1&facets[unit][]=TBPD ; https://api.eia.gov/v2/international/data/?frequency=annual&facets[productId][]=57&facets[activityId][]=1&facets[unit][]=TBPD ; https://api.eia.gov/v2/international/data/?frequency=annual&facets[productId][]=58&facets[activityId][]=1&facets[unit][]=TBPD ; https://api.eia.gov/v2/international/data/?frequency=annual&facets[productId][]=5&facets[activityId][]=2&facets[unit][]=TBPD ; Исходный источник: https://www.jodidata.org/oil/database/data-downloads.aspx ; https://www.worldometers.info/oil/democratic-republic-of-the-congo-oil/ | AD33: https://api.worldbank.org/v2/country/COD/indicator/NY.GDP.MKTP.CD?format=json ; https://api.worldbank.org/v2/country/COD/indicator/NY.GDP.MKTP.KD.ZG?format=json ; https://api.worldbank.org/v2/country/COD/indicator/FP.CPI.TOTL.ZG?format=json ; Исходный источник: https://data.worldbank.org/ | AE33: https://www.globalpetrolprices.com/Democratic-Republic-of-the-Congo/gasoline_prices/ ; https://www.globalpetrolprices.com/Democratic-Republic-of-the-Congo/diesel_prices/ ; Исходный источник: GlobalPetrolPrices (страновые значения только там, где они были явно помечены как страновые); Jet/мазут: н/д | AF33: Массовые оценки/медианы удалены в ходе аудита. Сохранившиеся исходные числовые значения не считаются подтверждёнными автоматически; требуется первичная проверка источника. Обновление 16.09.2026: Потребление и доли: EIA, petroleum and other liquids, 2024; включает биотопливо. Jet/мазут: национальные сопоставимые цены не найдены; исходные значения сохранены. | AG33: Бензин: проверено GPP; Дизель: проверено GPP; LPG: н/д; Jet/керосин: нет сопоставимой национальной цены; Мазут: нет сопоставимой национальной цены | AH33: CD | AI33: COD | AJ33: ='Сводка НПЗ'!D33 -> 0 | AK33: =IF('Сводка НПЗ'!F33>0,'Сводка НПЗ'!E33,"") | AL33: ='Сводка НПЗ'!G33 -> 0 | AM33: 2019-02-18 | AN33: Свежие число и мощность не подтверждены | AO33: 2024 | AP33: 2025 | AQ33: 2025 | AR33: 2026-09-16
A34: 33 | B34: Bhutan | C34: Бутан | D34: 5453.0578 | E34: 2024 | F34: =IF(AND(ISNUMBER(D34),ISNUMBER(E34)),D34*(DATE(E34+1,1,1)-DATE(E34,1,1))/1000000,"н/д") -> 1.9958191 | G34: 60.96432 | H34: 25.205873 | I34: 5.0322821 | J34: 1.6778871 | K34: 0.95390598 | L34: 0 | M34: 2025 | N34: 0 | O34: 0 | P34: 3.5793201 | Q34: 2025 | R34: 8.0050272 | S34: 2025 | T34: 3.5551366 | U34: 2025 | V34: 1.032 | W34: 1.087 | X34: н/д | Y34: н/д | Z34: н/д | AA34: Бензин/дизель/LPG: USD/л; Jet/мазут: исходные единицы | AB34: Бензин: 2026-09-14; Дизель: 2026-09-14; исходные даты для непроверенных значений: бензин: 2026-09-14; дизель/LPG: 2026-09-07; Jet/мазут: н/д | AC34: https://api.eia.gov/v2/international/data/?frequency=annual&facets[productId][]=53&facets[activityId][]=1&facets[unit][]=TBPD ; https://api.eia.gov/v2/international/data/?frequency=annual&facets[productId][]=57&facets[activityId][]=1&facets[unit][]=TBPD ; https://api.eia.gov/v2/international/data/?frequency=annual&facets[productId][]=58&facets[activityId][]=1&facets[unit][]=TBPD ; https://api.eia.gov/v2/international/data/?frequency=annual&facets[productId][]=5&facets[activityId][]=2&facets[unit][]=TBPD ; Исходный источник: https://www.jodidata.org/oil/database/data-downloads.aspx ; https://www.worldometers.info/oil/bhutan-oil/ | AD34: https://api.worldbank.org/v2/country/BTN/indicator/NY.GDP.MKTP.CD?format=json ; https://api.worldbank.org/v2/country/BTN/indicator/NY.GDP.MKTP.KD.ZG?format=json ; https://api.worldbank.org/v2/country/BTN/indicator/FP.CPI.TOTL.ZG?format=json ; Исходный источник: https://data.worldbank.org/ | AE34: https://www.globalpetrolprices.com/Bhutan/gasoline_prices/ ; https://www.globalpetrolprices.com/Bhutan/diesel_prices/ ; Исходный источник: GlobalPetrolPrices (страновые значения только там, где они были явно помечены как страновые); Jet/мазут: н/д | AF34: Массовые оценки/медианы удалены в ходе аудита. Сохранившиеся исходные числовые значения не считаются подтверждёнными автоматически; требуется первичная проверка источника. Обновление 16.09.2026: Потребление и доли: EIA, petroleum and other liquids, 2024; включает биотопливо. Jet/мазут: национальные сопоставимые цены не найдены; исходные значения сохранены. | AG34: Бензин: проверено GPP; Дизель: проверено GPP; LPG: н/д; Jet/керосин: нет сопоставимой национальной цены; Мазут: нет сопоставимой национальной цены | AH34: BT | AI34: BTN | AJ34: ='Сводка НПЗ'!D34 -> 0 | AK34: =IF('Сводка НПЗ'!F34>0,'Сводка НПЗ'!E34,"") | AL34: ='Сводка НПЗ'!G34 -> 0 | AM34: 2019-02-18 | AN34: Свежие число и мощность не подтверждены | AO34: 2024 | AP34: 2025 | AQ34: 2025 | AR34: 2026-09-16
A35: 34 | B35: Ukraine | C35: Украина | D35: 205640.7 | E35: 2024 | F35: =IF(AND(ISNUMBER(D35),ISNUMBER(E35)),D35*(DATE(E35+1,1,1)-DATE(E35,1,1))/1000000,"н/д") -> 75.264498 | G35: 52.179052 | H35: 20.455947 | I35: 15.887266 | J35: 0.68672775 | K35: 0.35492147 | L35: 57918.614 | M35: 2025 | N35: 31230.737 | O35: 19484.811 | P35: 214.23331 | Q35: 2025 | R35: 1.8215238 | S35: 2025 | T35: 12.730334 | U35: 2025 | V35: 1.976 | W35: 2.217 | X35: н/д | Y35: 1 | Z35: н/д | AA35: Бензин/дизель/LPG: USD/л; Jet/мазут: исходные единицы | AB35: Бензин: 2026-09-14; Дизель: 2026-09-14; LPG: 2026-09-14; исходные даты для непроверенных значений: бензин: 2026-09-14; дизель/LPG: 2026-09-07; Jet/мазут: н/д | AC35: https://api.eia.gov/v2/international/data/?frequency=annual&facets[productId][]=53&facets[activityId][]=1&facets[unit][]=TBPD ; https://api.eia.gov/v2/international/data/?frequency=annual&facets[productId][]=57&facets[activityId][]=1&facets[unit][]=TBPD ; https://api.eia.gov/v2/international/data/?frequency=annual&facets[productId][]=58&facets[activityId][]=1&facets[unit][]=TBPD ; https://api.eia.gov/v2/international/data/?frequency=annual&facets[productId][]=5&facets[activityId][]=2&facets[unit][]=TBPD ; Исходный источник: https://www.jodidata.org/oil/database/data-downloads.aspx ; https://www.worldometers.info/oil/ukraine-oil/ | AD35: https://api.worldbank.org/v2/country/UKR/indicator/NY.GDP.MKTP.CD?format=json ; https://api.worldbank.org/v2/country/UKR/indicator/NY.GDP.MKTP.KD.ZG?format=json ; https://api.worldbank.org/v2/country/UKR/indicator/FP.CPI.TOTL.ZG?format=json ; Исходный источник: https://data.worldbank.org/ | AE35: https://www.globalpetrolprices.com/Ukraine/gasoline_prices/ ; https://www.globalpetrolprices.com/Ukraine/diesel_prices/ ; https://www.globalpetrolprices.com/Ukraine/lpg_prices/ ; Исходный источник: GlobalPetrolPrices (страновые значения только там, где они были явно помечены как страновые); Jet/мазут: н/д | AF35: Массовые оценки/медианы удалены в ходе аудита. Сохранившиеся исходные числовые значения не считаются подтверждёнными автоматически; требуется первичная проверка источника. Обновление 16.09.2026: Потребление и доли: EIA, petroleum and other liquids, 2024; включает биотопливо. Jet/мазут: национальные сопоставимые цены не найдены; исходные значения сохранены. | AG35: Бензин: проверено GPP; Дизель: проверено GPP; LPG: проверено GPP; Jet/керосин: нет сопоставимой национальной цены; Мазут: нет сопоставимой национальной цены | AH35: UA | AI35: UKR | AJ35: ='Сводка НПЗ'!D35 -> 6 | AK35: =IF('Сводка НПЗ'!F35>0,'Сводка НПЗ'!E35,"") -> 685000 | AL35: ='Сводка НПЗ'!G35 -> 0 | AM35: 2019-02-18 | AN35: Мощность: вторичная публикация EI; число НПЗ не подтверждено | AO35: 2024 | AP35: 2025 | AQ35: 2025 | AR35: 2026-09-16
A36: 35 | B36: Belarus | C36: Белоруссия | D36: 116199.73 | E36: 2024 | F36: =IF(AND(ISNUMBER(D36),ISNUMBER(E36)),D36*(DATE(E36+1,1,1)-DATE(E36,1,1))/1000000,"н/д") -> 42.5291 | G36: 48.33454 | H36: 20.152029 | I36: 3.5828722 | J36: 2.4680227 | K36: 10.269611 | L36: 26009.49 | M36: 2025 | N36: 25730.49 | O36: 0 | P36: 93.397216 | Q36: 2025 | R36: 1.3 | S36: 2025 | T36: 6.5987795 | U36: 2025 | V36: 0.894 | W36: 0.894 | X36: н/д | Y36: 0.442 | Z36: н/д | AA36: Бензин/дизель/LPG: USD/л; Jet/мазут: исходные единицы | AB36: Бензин: 2026-09-14; Дизель: 2026-09-14; LPG: 2026-09-14; исходные даты для непроверенных значений: бензин: 2026-09-14; дизель/LPG: 2026-09-07; Jet/мазут: н/д | AC36: https://api.eia.gov/v2/international/data/?frequency=annual&facets[productId][]=53&facets[activityId][]=1&facets[unit][]=TBPD ; https://api.eia.gov/v2/international/data/?frequency=annual&facets[productId][]=57&facets[activityId][]=1&facets[unit][]=TBPD ; https://api.eia.gov/v2/international/data/?frequency=annual&facets[productId][]=58&facets[activityId][]=1&facets[unit][]=TBPD ; https://api.eia.gov/v2/international/data/?frequency=annual&facets[productId][]=5&facets[activityId][]=2&facets[unit][]=TBPD ; Исходный источник: https://www.jodidata.org/oil/database/data-downloads.aspx ; https://www.worldometers.info/oil/belarus-oil/ | AD36: https://api.worldbank.org/v2/country/BLR/indicator/NY.GDP.MKTP.CD?format=json ; https://api.worldbank.org/v2/country/BLR/indicator/NY.GDP.MKTP.KD.ZG?format=json ; https://api.worldbank.org/v2/country/BLR/indicator/FP.CPI.TOTL.ZG?format=json ; Исходный источник: https://data.worldbank.org/ | AE36: https://www.globalpetrolprices.com/Belarus/gasoline_prices/ ; https://www.globalpetrolprices.com/Belarus/diesel_prices/ ; https://www.globalpetrolprices.com/Belarus/lpg_prices/ ; Исходный источник: GlobalPetrolPrices (страновые значения только там, где они были явно помечены как страновые); Jet/мазут: н/д | AF36: Массовые оценки/медианы удалены в ходе аудита. Сохранившиеся исходные числовые значения не считаются подтверждёнными автоматически; требуется первичная проверка источника. Обновление 16.09.2026: Потребление и доли: EIA, petroleum and other liquids, 2024; включает биотопливо. Jet/мазут: национальные сопоставимые цены не найдены; исходные значения сохранены. | AG36: Бензин: проверено GPP; Дизель: проверено GPP; LPG: проверено GPP; Jet/керосин: нет сопоставимой национальной цены; Мазут: нет сопоставимой национальной цены | AH36: BY | AI36: BLR | AJ36: ='Сводка НПЗ'!D36 -> 2 | AK36: =IF('Сводка НПЗ'!F36>0,'Сводка НПЗ'!E36,"") -> 183000 | AL36: ='Сводка НПЗ'!G36 -> 0 | AM36: 2019-02-18 | AN36: Мощность: вторичная публикация EI; число НПЗ не подтверждено | AO36: 2024 | AP36: 2025 | AQ36: 2025 | AR36: 2026-09-16
A37: 36 | B37: Namibia | C37: Намибия | D37: 24412.718 | E37: 2024 | F37: =IF(AND(ISNUMBER(D37),ISNUMBER(E37)),D37*(DATE(E37+1,1,1)-DATE(E37,1,1))/1000000,"н/д") -> 8.9350549 | G37: 57.161853 | H37: 25.161401 | I37: 2.2722323 | J37: 9.2286969 | K37: 3.990464 | L37: 0 | M37: 2025 | N37: 0 | O37: 0 | P37: 15.080341 | Q37: 2025 | R37: 1.7301815 | S37: 2025 | T37: 3.5107454 | U37: 2025 | V37: 1.554 | W37: 1.726 | X37: н/д | Y37: н/д | Z37: н/д | AA37: Бензин/дизель/LPG: USD/л; Jet/мазут: исходные единицы | AB37: Бензин: 2026-09-14; Дизель: 2026-09-14; исходные даты для непроверенных значений: бензин: 2026-09-14; дизель/LPG: 2026-09-07; Jet/мазут: н/д | AC37: https://api.eia.gov/v2/international/data/?frequency=annual&facets[productId][]=53&facets[activityId][]=1&facets[unit][]=TBPD ; https://api.eia.gov/v2/international/data/?frequency=annual&facets[productId][]=57&facets[activityId][]=1&facets[unit][]=TBPD ; https://api.eia.gov/v2/international/data/?frequency=annual&facets[productId][]=58&facets[activityId][]=1&facets[unit][]=TBPD ; https://api.eia.gov/v2/international/data/?frequency=annual&facets[productId][]=5&facets[activityId][]=2&facets[unit][]=TBPD ; Исходный источник: https://www.jodidata.org/oil/database/data-downloads.aspx ; https://www.worldometers.info/oil/namibia-oil/ | AD37: https://api.worldbank.org/v2/country/NAM/indicator/NY.GDP.MKTP.CD?format=json ; https://api.worldbank.org/v2/country/NAM/indicator/NY.GDP.MKTP.KD.ZG?format=json ; https://api.worldbank.org/v2/country/NAM/indicator/FP.CPI.TOTL.ZG?format=json ; Исходный источник: https://data.worldbank.org/ | AE37: https://www.globalpetrolprices.com/Namibia/gasoline_prices/ ; https://www.globalpetrolprices.com/Namibia/diesel_prices/ ; Исходный источник: GlobalPetrolPrices (страновые значения только там, где они были явно помечены как страновые); Jet/мазут: н/д | AF37: Массовые оценки/медианы удалены в ходе аудита. Сохранившиеся исходные числовые значения не считаются подтверждёнными автоматически; требуется первичная проверка источника. Обновление 16.09.2026: Потребление и доли: EIA, petroleum and other liquids, 2024; включает биотопливо. Jet/мазут: национальные сопоставимые цены не найдены; исходные значения сохранены. | AG37: Бензин: проверено GPP; Дизель: проверено GPP; LPG: н/д; Jet/керосин: нет сопоставимой национальной цены; Мазут: нет сопоставимой национальной цены | AH37: NA | AI37: NAM | AJ37: ='Сводка НПЗ'!D37 -> 0 | AK37: =IF('Сводка НПЗ'!F37>0,'Сводка НПЗ'!E37,"") | AL37: ='Сводка НПЗ'!G37 -> 0 | AM37: 2019-02-18 | AN37: Свежие число и мощность не подтверждены | AO37: 2024 | AP37: 2025 | AQ37: 2025 | AR37: 2026-09-16
A38: 37 | B38: South Africa | C38: ЮАР | D38: 612110.42 | E38: 2024 | F38: =IF(AND(ISNUMBER(D38),ISNUMBER(E38)),D38*(DATE(E38+1,1,1)-DATE(E38,1,1))/1000000,"н/д") -> 224.03241 | G38: 44.399559 | H38: 24.490969 | I38: 0.82373389 | J38: 9.0499079 | K38: 3.8445191 | L38: 95209.682 | M38: 2025 | N38: 370.91507 | O38: 1625.4904 | P38: 427.18433 | Q38: 2025 | R38: 1.1146261 | S38: 2025 | T38: 3.2055047 | U38: 2025 | V38: 1.63 | W38: 1.962 | X38: н/д | Y38: н/д | Z38: н/д | AA38: Бензин/дизель/LPG: USD/л; Jet/мазут: исходные единицы | AB38: Бензин: 2026-09-14; Дизель: 2026-09-14; исходные даты для непроверенных значений: бензин: 2026-09-14; дизель/LPG: 2026-09-07; Jet/мазут: н/д | AC38: https://api.eia.gov/v2/international/data/?frequency=annual&facets[productId][]=53&facets[activityId][]=1&facets[unit][]=TBPD ; https://api.eia.gov/v2/international/data/?frequency=annual&facets[productId][]=57&facets[activityId][]=1&facets[unit][]=TBPD ; https://api.eia.gov/v2/international/data/?frequency=annual&facets[productId][]=58&facets[activityId][]=1&facets[unit][]=TBPD ; https://api.eia.gov/v2/international/data/?frequency=annual&facets[productId][]=5&facets[activityId][]=2&facets[unit][]=TBPD ; Исходный источник: https://www.jodidata.org/oil/database/data-downloads.aspx ; https://www.worldometers.info/oil/south-africa-oil/ | AD38: https://api.worldbank.org/v2/country/ZAF/indicator/NY.GDP.MKTP.CD?format=json ; https://api.worldbank.org/v2/country/ZAF/indicator/NY.GDP.MKTP.KD.ZG?format=json ; https://api.worldbank.org/v2/country/ZAF/indicator/FP.CPI.TOTL.ZG?format=json ; Исходный источник: https://data.worldbank.org/ | AE38: https://www.globalpetrolprices.com/South-Africa/gasoline_prices/ ; https://www.globalpetrolprices.com/South-Africa/diesel_prices/ ; Исходный источник: GlobalPetrolPrices (страновые значения только там, где они были явно помечены как страновые); Jet/мазут: н/д | AF38: Массовые оценки/медианы удалены в ходе аудита. Сохранившиеся исходные числовые значения не считаются подтверждёнными автоматически; требуется первичная проверка источника. Обновление 16.09.2026: Потребление и доли: EIA, petroleum and other liquids, 2024; включает биотопливо. Jet/мазут: национальные сопоставимые цены не найдены; исходные значения сохранены. | AG38: Бензин: проверено GPP; Дизель: проверено GPP; LPG: н/д; Jet/керосин: нет сопоставимой национальной цены; Мазут: нет сопоставимой национальной цены | AH38: ZA | AI38: ZAF | AJ38: ='Сводка НПЗ'!D38 -> 4 | AK38: =IF('Сводка НПЗ'!F38>0,'Сводка НПЗ'!E38,"") -> 496500 | AL38: ='Сводка НПЗ'!G38 -> 0 | AM38: 2019-02-18 | AN38: Мощность: вторичная публикация EI; число НПЗ не подтверждено | AO38: 2024 | AP38: 2025 | AQ38: 2025 | AR38: 2026-09-16
A39: 38 | B39: Saint Martin | C39: Сен-Мартен | D39: н/д | E39: н/д | F39: =IF(AND(ISNUMBER(D39),ISNUMBER(E39)),D39*(DATE(E39+1,1,1)-DATE(E39,1,1))/1000000,"н/д") -> н/д | G39: н/д | H39: н/д | I39: н/д | J39: н/д | K39: н/д | L39: н/д | M39: н/д | N39: н/д | O39: н/д | P39: н/д | Q39: н/д | R39: н/д | S39: н/д | T39: н/д | U39: н/д | V39: н/д | W39: н/д | X39: н/д | Y39: н/д | Z39: н/д | AA39: бензин/дизель/LPG/Jet: USD/л; мазут: USD/т | AB39: бензин: 2026-09-14; дизель/LPG: 2026-09-07; Jet/мазут: н/д | AC39: https://www.jodidata.org/oil/database/data-downloads.aspx | AD39: https://data.worldbank.org/ | AE39: GlobalPetrolPrices (страновые значения только там, где они были явно помечены как страновые); Jet/мазут: н/д | AF39: Массовые оценки/медианы удалены в ходе аудита. Сохранившиеся исходные числовые значения не считаются подтверждёнными автоматически; требуется первичная проверка источника. Обновление 16.09.2026: Потребление и доли: исходные значения, свежая сопоставимая серия не найдена. Jet/мазут: национальные сопоставимые цены не найдены; исходные значения сохранены. | AG39: Бензин: н/д; Дизель: н/д; LPG: н/д; Jet/керосин: нет сопоставимой национальной цены; Мазут: нет сопоставимой национальной цены | AH39: MF | AI39: MAF | AJ39: ='Сводка НПЗ'!D39 -> 0 | AK39: =IF('Сводка НПЗ'!F39>0,'Сводка НПЗ'!E39,"") | AL39: ='Сводка НПЗ'!G39 -> 0 | AM39: 2019-02-18 | AN39: Свежие число и мощность не подтверждены | AR39: 2026-09-16
A40: 39 | B40: Sint Maarten | C40: Синт-Мартен | D40: н/д | E40: н/д | F40: =IF(AND(ISNUMBER(D40),ISNUMBER(E40)),D40*(DATE(E40+1,1,1)-DATE(E40,1,1))/1000000,"н/д") -> н/д | G40: н/д | H40: н/д | I40: н/д | J40: н/д | K40: н/д | L40: н/д | M40: н/д | N40: н/д | O40: н/д | P40: 1.8877285 | Q40: 2025 | R40: 3.4 | S40: 2025 | T40: н/д | U40: н/д | V40: н/д | W40: н/д | X40: н/д | Y40: н/д | Z40: н/д | AA40: бензин/дизель/LPG/Jet: USD/л; мазут: USD/т | AB40: бензин: 2026-09-14; дизель/LPG: 2026-09-07; Jet/мазут: н/д | AC40: https://www.jodidata.org/oil/database/data-downloads.aspx | AD40: https://api.worldbank.org/v2/country/SXM/indicator/NY.GDP.MKTP.CD?format=json ; https://api.worldbank.org/v2/country/SXM/indicator/NY.GDP.MKTP.KD.ZG?format=json ; https://api.worldbank.org/v2/country/SXM/indicator/FP.CPI.TOTL.ZG?format=json ; Исходный источник: https://data.worldbank.org/ | AE40: GlobalPetrolPrices (страновые значения только там, где они были явно помечены как страновые); Jet/мазут: н/д | AF40: Массовые оценки/медианы удалены в ходе аудита. Сохранившиеся исходные числовые значения не считаются подтверждёнными автоматически; требуется первичная проверка источника. Обновление 16.09.2026: Потребление и доли: исходные значения, свежая сопоставимая серия не найдена. Jet/мазут: национальные сопоставимые цены не найдены; исходные значения сохранены. | AG40: Бензин: н/д; Дизель: н/д; LPG: н/д; Jet/керосин: нет сопоставимой национальной цены; Мазут: нет сопоставимой национальной цены | AH40: SX | AI40: SXM | AJ40: ='Сводка НПЗ'!D40 -> 0 | AK40: =IF('Сводка НПЗ'!F40>0,'Сводка НПЗ'!E40,"") | AL40: ='Сводка НПЗ'!G40 -> 0 | AM40: 2019-02-18 | AN40: Свежие число и мощность не подтверждены | AR40: 2026-09-16
A41: 40 | B41: Oman | C41: Оман | D41: 230821.23 | E41: 2024 | F41: =IF(AND(ISNUMBER(D41),ISNUMBER(E41)),D41*(DATE(E41+1,1,1)-DATE(E41,1,1))/1000000,"н/д") -> 84.480569 | G41: 21.812013 | H41: 32.398157 | I41: 3.7561676 | J41: 4.2701462 | K41: 17.875472 | L41: 1011409.1 | M41: 2025 | N41: 1002069.2 | O41: 8000 | P41: 109.60478 | Q41: 2025 | R41: 2.3978738 | S41: 2025 | T41: 0.96774194 | U41: 2025 | V41: 0.622 | W41: 0.671 | X41: н/д | Y41: н/д | Z41: н/д | AA41: Бензин/дизель/LPG: USD/л; Jet/мазут: исходные единицы | AB41: Бензин: 2026-09-14; Дизель: 2026-09-14; исходные даты для непроверенных значений: бензин: 2026-09-14; дизель/LPG: 2026-09-07; Jet/мазут: н/д | AC41: https://api.eia.gov/v2/international/data/?frequency=annual&facets[productId][]=53&facets[activityId][]=1&facets[unit][]=TBPD ; https://api.eia.gov/v2/international/data/?frequency=annual&facets[productId][]=57&facets[activityId][]=1&facets[unit][]=TBPD ; https://api.eia.gov/v2/international/data/?frequency=annual&facets[productId][]=58&facets[activityId][]=1&facets[unit][]=TBPD ; https://api.eia.gov/v2/international/data/?frequency=annual&facets[productId][]=5&facets[activityId][]=2&facets[unit][]=TBPD ; Исходный источник: https://www.jodidata.org/oil/database/data-downloads.aspx ; https://www.worldometers.info/oil/oman-oil/ | AD41: https://api.worldbank.org/v2/country/OMN/indicator/NY.GDP.MKTP.CD?format=json ; https://api.worldbank.org/v2/country/OMN/indicator/NY.GDP.MKTP.KD.ZG?format=json ; https://api.worldbank.org/v2/country/OMN/indicator/FP.CPI.TOTL.ZG?format=json ; Исходный источник: https://data.worldbank.org/ | AE41: https://www.globalpetrolprices.com/Oman/gasoline_prices/ ; https://www.globalpetrolprices.com/Oman/diesel_prices/ ; Исходный источник: GlobalPetrolPrices (страновые значения только там, где они были явно помечены как страновые); Jet/мазут: н/д | AF41: Массовые оценки/медианы удалены в ходе аудита. Сохранившиеся исходные числовые значения не считаются подтверждёнными автоматически; требуется первичная проверка источника. Обновление 16.09.2026: Потребление и доли: EIA, petroleum and other liquids, 2024; включает биотопливо. Jet/мазут: национальные сопоставимые цены не найдены; исходные значения сохранены. | AG41: Бензин: проверено GPP; Дизель: проверено GPP; LPG: н/д; Jet/керосин: нет сопоставимой национальной цены; Мазут: нет сопоставимой национальной цены | AH41: OM | AI41: OMN | AJ41: ='Сводка НПЗ'!D41 -> 1 | AK41: =IF('Сводка НПЗ'!F41>0,'Сводка НПЗ'!E41,"") -> 106000 | AL41: ='Сводка НПЗ'!G41 -> 0 | AM41: 2019-02-18 | AN41: Мощность: вторичная публикация EI; число НПЗ не подтверждено | AO41: 2024 | AP41: 2025 | AQ41: 2025 | AR41: 2026-09-16
A42: 41 | B42: Uzbekistan | C42: Узбекистан | D42: 135563.95 | E42: 2024 | F42: =IF(AND(ISNUMBER(D42),ISNUMBER(E42)),D42*(DATE(E42+1,1,1)-DATE(E42,1,1))/1000000,"н/д") -> 49.616407 | G42: 16.644502 | H42: 30.70265 | I42: 20.348885 | J42: 3.9905747 | K42: 12.033021 | L42: 49685.61 | M42: 2025 | N42: 29583.86 | O42: 0 | P42: 147.03808 | Q42: 2025 | R42: 7.6996248 | S42: 2025 | T42: 8.7963885 | U42: 2025 | V42: 1.496 | W42: 1.356 | X42: н/д | Y42: н/д | Z42: н/д | AA42: Бензин/дизель/LPG: USD/л; Jet/мазут: исходные единицы | AB42: Бензин: 2026-09-14; Дизель: 2026-09-14; исходные даты для непроверенных значений: бензин: 2026-09-14; дизель/LPG: 2026-09-07; Jet/мазут: н/д | AC42: https://api.eia.gov/v2/international/data/?frequency=annual&facets[productId][]=53&facets[activityId][]=1&facets[unit][]=TBPD ; https://api.eia.gov/v2/international/data/?frequency=annual&facets[productId][]=57&facets[activityId][]=1&facets[unit][]=TBPD ; https://api.eia.gov/v2/international/data/?frequency=annual&facets[productId][]=58&facets[activityId][]=1&facets[unit][]=TBPD ; https://api.eia.gov/v2/international/data/?frequency=annual&facets[productId][]=5&facets[activityId][]=2&facets[unit][]=TBPD ; Исходный источник: https://www.jodidata.org/oil/database/data-downloads.aspx ; https://www.worldometers.info/oil/uzbekistan-oil/ | AD42: https://api.worldbank.org/v2/country/UZB/indicator/NY.GDP.MKTP.CD?format=json ; https://api.worldbank.org/v2/country/UZB/indicator/NY.GDP.MKTP.KD.ZG?format=json ; https://api.worldbank.org/v2/country/UZB/indicator/FP.CPI.TOTL.ZG?format=json ; Исходный источник: https://data.worldbank.org/ | AE42: https://www.globalpetrolprices.com/Uzbekistan/gasoline_prices/ ; https://www.globalpetrolprices.com/Uzbekistan/diesel_prices/ ; Исходный источник: GlobalPetrolPrices (страновые значения только там, где они были явно помечены как страновые); Jet/мазут: н/д | AF42: Массовые оценки/медианы удалены в ходе аудита. Сохранившиеся исходные числовые значения не считаются подтверждёнными автоматически; требуется первичная проверка источника. Обновление 16.09.2026: Потребление и доли: EIA, petroleum and other liquids, 2024; включает биотопливо. Jet/мазут: национальные сопоставимые цены не найдены; исходные значения сохранены. | AG42: Бензин: проверено GPP; Дизель: проверено GPP; LPG: н/д; Jet/керосин: нет сопоставимой национальной цены; Мазут: нет сопоставимой национальной цены | AH42: UZ | AI42: UZB | AJ42: ='Сводка НПЗ'!D42 -> 3 | AK42: =IF('Сводка НПЗ'!F42>0,'Сводка НПЗ'!E42,"") -> 66000 | AL42: ='Сводка НПЗ'!G42 -> 2 | AM42: 2019-02-18 | AN42: Мощность: вторичная публикация EI; число НПЗ не подтверждено | AO42: 2024 | AP42: 2025 | AQ42: 2025 | AR42: 2026-09-16
A43: 42 | B43: Kazakhstan | C43: Казахстан | D43: 412115.5 | E43: 2024 | F43: =IF(AND(ISNUMBER(D43),ISNUMBER(E43)),D43*(DATE(E43+1,1,1)-DATE(E43,1,1))/1000000,"н/д") -> 150.83427 | G43: 28.154376 | H43: 28.472621 | I43: 11.733245 | J43: 4.5495891 | K43: 3.8519591 | L43: 2149550.4 | M43: 2025 | N43: 2046610.2 | O43: 100403.61 | P43: 306.23921 | Q43: 2025 | R43: 6.5 | S43: 2025 | T43: 11.387945 | U43: 2025 | V43: 0.721 | W43: 0.773 | X43: н/д | Y43: 0.251 | Z43: н/д | AA43: Бензин/дизель/LPG: USD/л; Jet/мазут: исходные единицы | AB43: Бензин: 2026-09-14; Дизель: 2026-09-14; LPG: 2026-09-14; исходные даты для непроверенных значений: бензин: 2026-09-14; дизель/LPG: 2026-09-07; Jet/мазут: н/д | AC43: https://api.eia.gov/v2/international/data/?frequency=annual&facets[productId][]=53&facets[activityId][]=1&facets[unit][]=TBPD ; https://api.eia.gov/v2/international/data/?frequency=annual&facets[productId][]=57&facets[activityId][]=1&facets[unit][]=TBPD ; https://api.eia.gov/v2/international/data/?frequency=annual&facets[productId][]=58&facets[activityId][]=1&facets[unit][]=TBPD ; https://api.eia.gov/v2/international/data/?frequency=annual&facets[productId][]=5&facets[activityId][]=2&facets[unit][]=TBPD ; Исходный источник: https://www.jodidata.org/oil/database/data-downloads.aspx ; https://www.worldometers.info/oil/kazakhstan-oil/ | AD43: https://api.worldbank.org/v2/country/KAZ/indicator/NY.GDP.MKTP.CD?format=json ; https://api.worldbank.org/v2/country/KAZ/indicator/NY.GDP.MKTP.KD.ZG?format=json ; https://api.worldbank.org/v2/country/KAZ/indicator/FP.CPI.TOTL.ZG?format=json ; Исходный источник: https://data.worldbank.org/ | AE43: https://www.globalpetrolprices.com/Kazakhstan/gasoline_prices/ ; https://www.globalpetrolprices.com/Kazakhstan/diesel_prices/ ; https://www.globalpetrolprices.com/Kazakhstan/lpg_prices/ ; Исходный источник: GlobalPetrolPrices (страновые значения только там, где они были явно помечены как страновые); Jet/мазут: н/д | AF43: Массовые оценки/медианы удалены в ходе аудита. Сохранившиеся исходные числовые значения не считаются подтверждёнными автоматически; требуется первичная проверка источника. Обновление 16.09.2026: Потребление и доли: EIA, petroleum and other liquids, 2024; включает биотопливо. Jet/мазут: национальные сопоставимые цены не найдены; исходные значения сохранены. | AG43: Бензин: проверено GPP; Дизель: проверено GPP; LPG: проверено GPP; Jet/керосин: нет сопоставимой национальной цены; Мазут: нет сопоставимой национальной цены | AH43: KZ | AI43: KAZ | AJ43: ='Сводка НПЗ'!D43 -> 3 | AK43: =IF('Сводка НПЗ'!F43>0,'Сводка НПЗ'!E43,"") -> 427066 | AL43: ='Сводка НПЗ'!G43 -> 0 | AM43: 2019-02-18 | AN43: Проверен первичный источник; см. охват | AO43: 2024 | AP43: 2025 | AQ43: 2025 | AR43: 2026-09-16
A44: 43 | B44: Tajikistan | C44: Таджикистан | D44: 32747.986 | E44: 2024 | F44: =IF(AND(ISNUMBER(D44),ISNUMBER(E44)),D44*(DATE(E44+1,1,1)-DATE(E44,1,1))/1000000,"н/д") -> 11.985763 | G44: 27.242415 | H44: 24.841373 | I44: 39.876466 | J44: 4.7236283 | K44: 0.21730081 | L44: 316 | M44: 2025 | N44: 316 | O44: 0 | P44: 17.660627 | Q44: 2025 | R44: 8.4000005 | S44: 2025 | T44: н/д | U44: н/д | V44: н/д | W44: н/д | X44: н/д | Y44: н/д | Z44: н/д | AA44: бензин/дизель/LPG/Jet: USD/л; мазут: USD/т | AB44: бензин: 2026-09-14; дизель/LPG: 2026-09-07; Jet/мазут: н/д | AC44: https://api.eia.gov/v2/international/data/?frequency=annual&facets[productId][]=53&facets[activityId][]=1&facets[unit][]=TBPD ; https://api.eia.gov/v2/international/data/?frequency=annual&facets[productId][]=57&facets[activityId][]=1&facets[unit][]=TBPD ; https://api.eia.gov/v2/international/data/?frequency=annual&facets[productId][]=58&facets[activityId][]=1&facets[unit][]=TBPD ; https://api.eia.gov/v2/international/data/?frequency=annual&facets[productId][]=5&facets[activityId][]=2&facets[unit][]=TBPD ; Исходный источник: https://www.jodidata.org/oil/database/data-downloads.aspx ; https://www.worldometers.info/oil/tajikistan-oil/ | AD44: https://api.worldbank.org/v2/country/TJK/indicator/NY.GDP.MKTP.CD?format=json ; https://api.worldbank.org/v2/country/TJK/indicator/NY.GDP.MKTP.KD.ZG?format=json ; https://api.worldbank.org/v2/country/TJK/indicator/FP.CPI.TOTL.ZG?format=json ; Исходный источник: https://data.worldbank.org/ | AE44: GlobalPetrolPrices (страновые значения только там, где они были явно помечены как страновые); Jet/мазут: н/д | AF44: Массовые оценки/медианы удалены в ходе аудита. Сохранившиеся исходные числовые значения не считаются подтверждёнными автоматически; требуется первичная проверка источника. Обновление 16.09.2026: Потребление и доли: EIA, petroleum and other liquids, 2024; включает биотопливо. Jet/мазут: национальные сопоставимые цены не найдены; исходные значения сохранены. | AG44: Бензин: н/д; Дизель: н/д; LPG: н/д; Jet/керосин: нет сопоставимой национальной цены; Мазут: нет сопоставимой национальной цены | AH44: TJ | AI44: TJK | AJ44: ='Сводка НПЗ'!D44 -> 0 | AK44: =IF('Сводка НПЗ'!F44>0,'Сводка НПЗ'!E44,"") | AL44: ='Сводка НПЗ'!G44 -> 0 | AM44: 2019-02-18 | AN44: Свежие число и мощность не подтверждены | AO44: 2024 | AP44: 2025 | AQ44: 2025 | AR44: 2026-09-16
A45: 44 | B45: Lithuania | C45: Литва | D45: 53404.841 | E45: 2025 | F45: =IF(AND(ISNUMBER(D45),ISNUMBER(E45)),D45*(DATE(E45+1,1,1)-DATE(E45,1,1))/1000000,"н/д") -> 19.492767 | G45: 63.7971 | H45: 15.042246 | I45: 7.7957121 | J45: н/д | K45: 0.033089197 | L45: 8891.803 | M45: 2025 | N45: 700 | O45: 0 | P45: 95.210151 | Q45: 2025 | R45: 2.9200766 | S45: 2025 | T45: 3.7917051 | U45: 2025 | V45: 2.111 | W45: 2.308 | X45: н/д | Y45: 1.037 | Z45: н/д | AA45: Бензин/дизель/LPG: USD/л; Jet/мазут: исходные единицы | AB45: Бензин: 2026-09-14; Дизель: 2026-09-14; LPG: 2026-09-14; исходные даты для непроверенных значений: бензин: 2026-09-14; дизель/LPG: 2026-09-07; Jet/мазут: н/д | AC45: https://api.eia.gov/v2/international/data/?frequency=annual&facets[productId][]=53&facets[activityId][]=1&facets[unit][]=TBPD ; https://api.eia.gov/v2/international/data/?frequency=annual&facets[productId][]=57&facets[activityId][]=1&facets[unit][]=TBPD ; https://api.eia.gov/v2/international/data/?frequency=annual&facets[productId][]=58&facets[activityId][]=1&facets[unit][]=TBPD ; https://www.jodidata.org/_resources/files/downloads/oil-data/annual-csv/secondary/2025.csv ; Исходный источник: https://www.jodidata.org/oil/database/data-downloads.aspx ; https://www.worldometers.info/oil/lithuania-oil/ | AD45: https://api.worldbank.org/v2/country/LTU/indicator/NY.GDP.MKTP.CD?format=json ; https://api.worldbank.org/v2/country/LTU/indicator/NY.GDP.MKTP.KD.ZG?format=json ; https://api.worldbank.org/v2/country/LTU/indicator/FP.CPI.TOTL.ZG?format=json ; Исходный источник: https://data.worldbank.org/ | AE45: https://www.globalpetrolprices.com/Lithuania/gasoline_prices/ ; https://www.globalpetrolprices.com/Lithuania/diesel_prices/ ; https://www.globalpetrolprices.com/Lithuania/lpg_prices/ ; Исходный источник: GlobalPetrolPrices (страновые значения только там, где они были явно помечены как страновые); Jet/мазут: н/д | AF45: Массовые оценки/медианы удалены в ходе аудита. Сохранившиеся исходные числовые значения не считаются подтверждёнными автоматически; требуется первичная проверка источника. Обновление 16.09.2026: Потребление и доли: JODI, нефтепродукты TOTPRODS, 12 месяцев 2025. Jet/мазут: национальные сопоставимые цены не найдены; исходные значения сохранены. | AG45: Бензин: проверено GPP; Дизель: проверено GPP; LPG: проверено GPP; Jet/керосин: нет сопоставимой национальной цены; Мазут: нет сопоставимой национальной цены | AH45: LT | AI45: LTU | AJ45: ='Сводка НПЗ'!D45 -> 1 | AK45: =IF('Сводка НПЗ'!F45>0,'Сводка НПЗ'!E45,"") -> 263000 | AL45: ='Сводка НПЗ'!G45 -> 0 | AM45: 2019-02-18 | AN45: Проверен первичный источник; см. охват | AO45: 2025 | AP45: 2025 | AQ45: 2025 | AR45: 2026-09-16
A46: 45 | B46: Brazil | C46: Бразилия | D46: 3268781.2 | E46: 2024 | F46: =IF(AND(ISNUMBER(D46),ISNUMBER(E46)),D46*(DATE(E46+1,1,1)-DATE(E46,1,1))/1000000,"н/д") -> 1196.3739 | G46: 35.54335 | H46: 34.869825 | I46: 7.2257839 | J46: 3.7120827 | K46: 2.64981 | L46: 4655066.3 | M46: 2025 | N46: 3769407 | O46: 82809.042 | P46: 2279.9201 | Q46: 2025 | R46: 2.2857465 | S46: 2025 | T46: 5.0167528 | U46: 2025 | V46: 1.274 | W46: 1.278 | X46: н/д | Y46: н/д | Z46: н/д | AA46: Бензин/дизель/LPG: USD/л; Jet/мазут: исходные единицы | AB46: Бензин: 2026-09-14; Дизель: 2026-09-14; исходные даты для непроверенных значений: бензин: 2026-09-14; дизель/LPG: 2026-09-07; Jet/мазут: н/д | AC46: https://api.eia.gov/v2/international/data/?frequency=annual&facets[productId][]=53&facets[activityId][]=1&facets[unit][]=TBPD ; https://api.eia.gov/v2/international/data/?frequency=annual&facets[productId][]=57&facets[activityId][]=1&facets[unit][]=TBPD ; https://api.eia.gov/v2/international/data/?frequency=annual&facets[productId][]=58&facets[activityId][]=1&facets[unit][]=TBPD ; https://api.eia.gov/v2/international/data/?frequency=annual&facets[productId][]=5&facets[activityId][]=2&facets[unit][]=TBPD ; Исходный источник: https://www.jodidata.org/oil/database/data-downloads.aspx ; https://www.worldometers.info/oil/ | AD46: https://api.worldbank.org/v2/country/BRA/indicator/NY.GDP.MKTP.CD?format=json ; https://api.worldbank.org/v2/country/BRA/indicator/NY.GDP.MKTP.KD.ZG?format=json ; https://api.worldbank.org/v2/country/BRA/indicator/FP.CPI.TOTL.ZG?format=json ; Исходный источник: https://data.worldbank.org/ | AE46: https://www.globalpetrolprices.com/Brazil/gasoline_prices/ ; https://www.globalpetrolprices.com/Brazil/diesel_prices/ ; Исходный источник: GlobalPetrolPrices (страновые значения только там, где они были явно помечены как страновые); Jet/мазут: н/д | AF46: Массовые оценки/медианы удалены в ходе аудита. Сохранившиеся исходные числовые значения не считаются подтверждёнными автоматически; требуется первичная проверка источника. Обновление 16.09.2026: Потребление и доли: EIA, petroleum and other liquids, 2024; включает биотопливо. Jet/мазут: национальные сопоставимые цены не найдены; исходные значения сохранены. | AG46: Бензин: проверено GPP; Дизель: проверено GPP; LPG: н/д; Jet/керосин: нет сопоставимой национальной цены; Мазут: нет сопоставимой национальной цены | AH46: BR | AI46: BRA | AJ46: ='Сводка НПЗ'!D46 -> 13 | AK46: =IF('Сводка НПЗ'!F46>0,'Сводка НПЗ'!E46,"") -> 1972500 | AL46: ='Сводка НПЗ'!G46 -> 0 | AM46: 2019-02-18 | AN46: Мощность: вторичная публикация EI; число НПЗ не подтверждено | AO46: 2024 | AP46: 2025 | AQ46: 2025 | AR46: 2026-09-16
A47: 46 | B47: Uruguay | C47: Уругвай | D47: 55247.102 | E47: 2024 | F47: =IF(AND(ISNUMBER(D47),ISNUMBER(E47)),D47*(DATE(E47+1,1,1)-DATE(E47,1,1))/1000000,"н/д") -> 20.220439 | G47: 41.913794 | H47: 24.894195 | I47: 6.9665071 | J47: 3.6997533 | K47: 8.2969729 | L47: 1411.5513 | M47: 2025 | N47: 0 | O47: 0 | P47: 85.347696 | Q47: 2025 | R47: 1.7847112 | S47: 2025 | T47: 4.6503272 | U47: 2025 | V47: 2.204 | W47: 1.459 | X47: н/д | Y47: н/д | Z47: н/д | AA47: Бензин/дизель/LPG: USD/л; Jet/мазут: исходные единицы | AB47: Бензин: 2026-09-14; Дизель: 2026-09-14; исходные даты для непроверенных значений: бензин: 2026-09-14; дизель/LPG: 2026-09-07; Jet/мазут: н/д | AC47: https://api.eia.gov/v2/international/data/?frequency=annual&facets[productId][]=53&facets[activityId][]=1&facets[unit][]=TBPD ; https://api.eia.gov/v2/international/data/?frequency=annual&facets[productId][]=57&facets[activityId][]=1&facets[unit][]=TBPD ; https://api.eia.gov/v2/international/data/?frequency=annual&facets[productId][]=58&facets[activityId][]=1&facets[unit][]=TBPD ; https://api.eia.gov/v2/international/data/?frequency=annual&facets[productId][]=5&facets[activityId][]=2&facets[unit][]=TBPD ; Исходный источник: https://www.jodidata.org/oil/database/data-downloads.aspx ; https://www.worldometers.info/oil/ | AD47: https://api.worldbank.org/v2/country/URY/indicator/NY.GDP.MKTP.CD?format=json ; https://api.worldbank.org/v2/country/URY/indicator/NY.GDP.MKTP.KD.ZG?format=json ; https://api.worldbank.org/v2/country/URY/indicator/FP.CPI.TOTL.ZG?format=json ; Исходный источник: https://data.worldbank.org/ | AE47: https://www.globalpetrolprices.com/Uruguay/gasoline_prices/ ; https://www.globalpetrolprices.com/Uruguay/diesel_prices/ ; Исходный источник: GlobalPetrolPrices (страновые значения только там, где они были явно помечены как страновые); Jet/мазут: н/д | AF47: Массовые оценки/медианы удалены в ходе аудита. Сохранившиеся исходные числовые значения не считаются подтверждёнными автоматически; требуется первичная проверка источника. Обновление 16.09.2026: Потребление и доли: EIA, petroleum and other liquids, 2024; включает биотопливо. Jet/мазут: национальные сопоставимые цены не найдены; исходные значения сохранены. | AG47: Бензин: проверено GPP; Дизель: проверено GPP; LPG: н/д; Jet/керосин: нет сопоставимой национальной цены; Мазут: нет сопоставимой национальной цены | AH47: UY | AI47: URY | AJ47: ='Сводка НПЗ'!D47 -> 1 | AK47: =IF('Сводка НПЗ'!F47>0,'Сводка НПЗ'!E47,"") -> 40000 | AL47: ='Сводка НПЗ'!G47 -> 0 | AM47: 2019-02-18 | AN47: Свежие число и мощность не подтверждены | AO47: 2024 | AP47: 2025 | AQ47: 2025 | AR47: 2026-09-16
A48: 47 | B48: Mongolia | C48: Монголия | D48: 48219.792 | E48: 2024 | F48: =IF(AND(ISNUMBER(D48),ISNUMBER(E48)),D48*(DATE(E48+1,1,1)-DATE(E48,1,1))/1000000,"н/д") -> 17.648444 | G48: 58.529561 | H48: 36.26943 | I48: 0 | J48: 5.0808306 | K48: 0.12017887 | L48: 13671.847 | M48: 2025 | N48: 13671.847 | O48: 0 | P48: 25.369107 | Q48: 2025 | R48: 6.8439142 | S48: 2025 | T48: 8.6053649 | U48: 2025 | V48: 1.783 | W48: 1.59 | X48: н/д | Y48: 0.817 | Z48: н/д | AA48: Бензин/дизель/LPG: USD/л; Jet/мазут: исходные единицы | AB48: Бензин: 2026-09-14; Дизель: 2026-09-14; LPG: 2026-09-14; исходные даты для непроверенных значений: бензин: 2026-09-14; дизель/LPG: 2026-09-07; Jet/мазут: н/д | AC48: https://api.eia.gov/v2/international/data/?frequency=annual&facets[productId][]=53&facets[activityId][]=1&facets[unit][]=TBPD ; https://api.eia.gov/v2/international/data/?frequency=annual&facets[productId][]=57&facets[activityId][]=1&facets[unit][]=TBPD ; https://api.eia.gov/v2/international/data/?frequency=annual&facets[productId][]=58&facets[activityId][]=1&facets[unit][]=TBPD ; https://api.eia.gov/v2/international/data/?frequency=annual&facets[productId][]=5&facets[activityId][]=2&facets[unit][]=TBPD ; Исходный источник: https://www.jodidata.org/oil/database/data-downloads.aspx ; https://www.worldometers.info/oil/ | AD48: https://api.worldbank.org/v2/country/MNG/indicator/NY.GDP.MKTP.CD?format=json ; https://api.worldbank.org/v2/country/MNG/indicator/NY.GDP.MKTP.KD.ZG?format=json ; https://api.worldbank.org/v2/country/MNG/indicator/FP.CPI.TOTL.ZG?format=json ; Исходный источник: https://data.worldbank.org/ | AE48: https://www.globalpetrolprices.com/Mongolia/gasoline_prices/ ; https://www.globalpetrolprices.com/Mongolia/diesel_prices/ ; https://www.globalpetrolprices.com/Mongolia/lpg_prices/ ; Исходный источник: GlobalPetrolPrices (страновые значения только там, где они были явно помечены как страновые); Jet/мазут: н/д | AF48: Массовые оценки/медианы удалены в ходе аудита. Сохранившиеся исходные числовые значения не считаются подтверждёнными автоматически; требуется первичная проверка источника. Обновление 16.09.2026: Потребление и доли: EIA, petroleum and other liquids, 2024; включает биотопливо. Jet/мазут: национальные сопоставимые цены не найдены; исходные значения сохранены. | AG48: Бензин: проверено GPP; Дизель: проверено GPP; LPG: проверено GPP; Jet/керосин: нет сопоставимой национальной цены; Мазут: нет сопоставимой национальной цены | AH48: MN | AI48: MNG | AJ48: ='Сводка НПЗ'!D48 -> 0 | AK48: =IF('Сводка НПЗ'!F48>0,'Сводка НПЗ'!E48,"") | AL48: ='Сводка НПЗ'!G48 -> 0 | AM48: 2019-02-18 | AN48: Свежие число и мощность не подтверждены | AO48: 2024 | AP48: 2025 | AQ48: 2025 | AR48: 2026-09-16
A49: 48 | B49: Russia | C49: Россия | D49: 3801859.2 | E49: 2024 | F49: =IF(AND(ISNUMBER(D49),ISNUMBER(E49)),D49*(DATE(E49+1,1,1)-DATE(E49,1,1))/1000000,"н/д") -> 1391.4805 | G49: 23.76771 | H49: 23.97313 | I49: 23.666814 | J49: 6.2864237 | K49: 1.3951007 | L49: 10534548 | M49: 2025 | N49: 9885109 | O49: 621678.17 | P49: 2561.3102 | Q49: 2025 | R49: 1.0011766 | S49: 2025 | T49: 8.7198694 | U49: 2025 | V49: 0.884 | W49: 0.968 | X49: н/д | Y49: 0.429 | Z49: н/д | AA49: Бензин/дизель/LPG: USD/л; Jet/мазут: исходные единицы | AB49: Бензин: 2026-09-14; Дизель: 2026-09-14; LPG: 2026-09-14; исходные даты для непроверенных значений: бензин: 2026-09-14; дизель/LPG: 2026-09-07; Jet/мазут: н/д | AC49: https://api.eia.gov/v2/international/data/?frequency=annual&facets[productId][]=53&facets[activityId][]=1&facets[unit][]=TBPD ; https://api.eia.gov/v2/international/data/?frequency=annual&facets[productId][]=57&facets[activityId][]=1&facets[unit][]=TBPD ; https://api.eia.gov/v2/international/data/?frequency=annual&facets[productId][]=58&facets[activityId][]=1&facets[unit][]=TBPD ; https://api.eia.gov/v2/international/data/?frequency=annual&facets[productId][]=5&facets[activityId][]=2&facets[unit][]=TBPD ; Исходный источник: https://www.jodidata.org/oil/database/data-downloads.aspx ; https://www.worldometers.info/oil/ | AD49: https://api.worldbank.org/v2/country/RUS/indicator/NY.GDP.MKTP.CD?format=json ; https://api.worldbank.org/v2/country/RUS/indicator/NY.GDP.MKTP.KD.ZG?format=json ; https://api.worldbank.org/v2/country/RUS/indicator/FP.CPI.TOTL.ZG?format=json ; Исходный источник: https://data.worldbank.org/ | AE49: https://www.globalpetrolprices.com/Russia/gasoline_prices/ ; https://www.globalpetrolprices.com/Russia/diesel_prices/ ; https://www.globalpetrolprices.com/Russia/lpg_prices/ ; Исходный источник: GlobalPetrolPrices (страновые значения только там, где они были явно помечены как страновые); Jet/мазут: н/д | AF49: Массовые оценки/медианы удалены в ходе аудита. Сохранившиеся исходные числовые значения не считаются подтверждёнными автоматически; требуется первичная проверка источника. Обновление 16.09.2026: Потребление и доли: EIA, petroleum and other liquids, 2024; включает биотопливо. Jet/мазут: национальные сопоставимые цены не найдены; исходные значения сохранены. | AG49: Бензин: проверено GPP; Дизель: проверено GPP; LPG: проверено GPP; Jet/керосин: нет сопоставимой национальной цены; Мазут: нет сопоставимой национальной цены | AH49: RU | AI49: RUS | AJ49: ='Сводка НПЗ'!D49 -> 41 | AK49: =IF('Сводка НПЗ'!F49>0,'Сводка НПЗ'!E49,"") -> 5513129 | AL49: ='Сводка НПЗ'!G49 -> 0 | AM49: 2019-02-18 | AN49: Мощность: вторичная публикация EI; число НПЗ не подтверждено | AO49: 2024 | AP49: 2025 | AQ49: 2025 | AR49: 2026-09-16
A50: 49 | B50: Czech Republic | C50: Чехия | D50: 218926.03 | E50: 2025 | F50: =IF(AND(ISNUMBER(D50),ISNUMBER(E50)),D50*(DATE(E50+1,1,1)-DATE(E50,1,1))/1000000,"н/д") -> 79.908 | G50: 51.542599 | H50: 19.372779 | I50: 5.3421435 | J50: 9.151324 | K50: 0.44394804 | L50: 10891.301 | M50: 2025 | N50: 1345.5507 | O50: 0 | P50: 391.02696 | Q50: 2025 | R50: 2.5804667 | S50: 2025 | T50: 2.4599637 | U50: 2025 | V50: 2.076 | W50: 2.251 | X50: н/д | Y50: 1.031 | Z50: н/д | AA50: Бензин/дизель/LPG: USD/л; Jet/мазут: исходные единицы | AB50: Бензин: 2026-09-14; Дизель: 2026-09-14; LPG: 2026-09-14; исходные даты для непроверенных значений: бензин: 2026-09-14; дизель/LPG: 2026-09-07; Jet/мазут: н/д | AC50: https://api.eia.gov/v2/international/data/?frequency=annual&facets[productId][]=53&facets[activityId][]=1&facets[unit][]=TBPD ; https://api.eia.gov/v2/international/data/?frequency=annual&facets[productId][]=57&facets[activityId][]=1&facets[unit][]=TBPD ; https://api.eia.gov/v2/international/data/?frequency=annual&facets[productId][]=58&facets[activityId][]=1&facets[unit][]=TBPD ; https://www.jodidata.org/_resources/files/downloads/oil-data/annual-csv/secondary/2025.csv ; Исходный источник: https://www.jodidata.org/oil/database/data-downloads.aspx ; https://www.worldometers.info/oil/ | AD50: https://api.worldbank.org/v2/country/CZE/indicator/NY.GDP.MKTP.CD?format=json ; https://api.worldbank.org/v2/country/CZE/indicator/NY.GDP.MKTP.KD.ZG?format=json ; https://api.worldbank.org/v2/country/CZE/indicator/FP.CPI.TOTL.ZG?format=json ; Исходный источник: https://data.worldbank.org/ | AE50: https://www.globalpetrolprices.com/Czech-Republic/gasoline_prices/ ; https://www.globalpetrolprices.com/Czech-Republic/diesel_prices/ ; https://www.globalpetrolprices.com/Czech-Republic/lpg_prices/ ; Исходный источник: GlobalPetrolPrices (страновые значения только там, где они были явно помечены как страновые); Jet/мазут: н/д | AF50: Массовые оценки/медианы удалены в ходе аудита. Сохранившиеся исходные числовые значения не считаются подтверждёнными автоматически; требуется первичная проверка источника. Обновление 16.09.2026: Потребление и доли: JODI, нефтепродукты TOTPRODS, 12 месяцев 2025. Jet/мазут: национальные сопоставимые цены не найдены; исходные значения сохранены. | AG50: Бензин: проверено GPP; Дизель: проверено GPP; LPG: проверено GPP; Jet/керосин: нет сопоставимой национальной цены; Мазут: нет сопоставимой национальной цены | AH50: CZ | AI50: CZE | AJ50: ='Сводка НПЗ'!D50 -> 4 | AK50: =IF('Сводка НПЗ'!F50>0,'Сводка НПЗ'!E50,"") -> 190000 | AL50: ='Сводка НПЗ'!G50 -> 1 | AM50: 2019-02-18 | AN50: Проверен первичный источник; см. охват | AO50: 2025 | AP50: 2025 | AQ50: 2025 | AR50: 2026-09-16
A51: 50 | B51: Germany | C51: Германия | D51: 2172808.2 | E51: 2025 | F51: =IF(AND(ISNUMBER(D51),ISNUMBER(E51)),D51*(DATE(E51+1,1,1)-DATE(E51,1,1))/1000000,"н/д") -> 793.075 | G51: 42.092808 | H51: 21.892274 | I51: 4.5605775 | J51: 17.742731 | K51: 2.2951045 | L51: 185636.79 | M51: 2025 | N51: 31579.964 | O51: 0 | P51: 5050.9229 | Q51: 2025 | R51: 0.23957834 | S51: 2025 | T51: 2.1717877 | U51: 2025 | V51: 2.671 | W51: 2.813 | X51: н/д | Y51: 1.294 | Z51: н/д | AA51: Бензин/дизель/LPG: USD/л; Jet/мазут: исходные единицы | AB51: Бензин: 2026-09-14; Дизель: 2026-09-14; LPG: 2026-09-14; исходные даты для непроверенных значений: бензин: 2026-09-14; дизель/LPG: 2026-09-07; Jet/мазут: н/д | AC51: https://api.eia.gov/v2/international/data/?frequency=annual&facets[productId][]=53&facets[activityId][]=1&facets[unit][]=TBPD ; https://api.eia.gov/v2/international/data/?frequency=annual&facets[productId][]=57&facets[activityId][]=1&facets[unit][]=TBPD ; https://api.eia.gov/v2/international/data/?frequency=annual&facets[productId][]=58&facets[activityId][]=1&facets[unit][]=TBPD ; https://www.jodidata.org/_resources/files/downloads/oil-data/annual-csv/secondary/2025.csv ; Исходный источник: https://www.jodidata.org/oil/database/data-downloads.aspx ; https://www.worldometers.info/oil/germany-oil/ | AD51: https://api.worldbank.org/v2/country/DEU/indicator/NY.GDP.MKTP.CD?format=json ; https://api.worldbank.org/v2/country/DEU/indicator/NY.GDP.MKTP.KD.ZG?format=json ; https://api.worldbank.org/v2/country/DEU/indicator/FP.CPI.TOTL.ZG?format=json ; Исходный источник: https://data.worldbank.org/ | AE51: https://www.globalpetrolprices.com/Germany/gasoline_prices/ ; https://www.globalpetrolprices.com/Germany/diesel_prices/ ; https://www.globalpetrolprices.com/Germany/lpg_prices/ ; Исходный источник: GlobalPetrolPrices (страновые значения только там, где они были явно помечены как страновые); Jet/мазут: н/д | AF51: Массовые оценки/медианы удалены в ходе аудита. Сохранившиеся исходные числовые значения не считаются подтверждёнными автоматически; требуется первичная проверка источника. Обновление 16.09.2026: Потребление и доли: JODI, нефтепродукты TOTPRODS, 12 месяцев 2025. Jet/мазут: национальные сопоставимые цены не найдены; исходные значения сохранены. | AG51: Бензин: проверено GPP; Дизель: проверено GPP; LPG: проверено GPP; Jet/керосин: нет сопоставимой национальной цены; Мазут: нет сопоставимой национальной цены | AH51: DE | AI51: DEU | AJ51: ='Сводка НПЗ'!D51 -> 15 | AK51: =IF('Сводка НПЗ'!F51>0,'Сводка НПЗ'!E51,"") -> 2335861 | AL51: ='Сводка НПЗ'!G51 -> 2 | AM51: 2019-02-18 | AN51: Проверен первичный источник; см. охват | AO51: 2025 | AP51: 2025 | AQ51: 2025 | AR51: 2026-09-16
A52: 51 | B52: Estonia | C52: Эстония | D52: 22912.329 | E52: 2025 | F52: =IF(AND(ISNUMBER(D52),ISNUMBER(E52)),D52*(DATE(E52+1,1,1)-DATE(E52,1,1))/1000000,"н/д") -> 8.363 | G52: 72.253976 | H52: 21.117422 | I52: 1.9418869 | J52: 0.56534736 | K52: 4.3961497 | L52: 22098.948 | M52: 2025 | N52: 0 | O52: 0 | P52: 47.030834 | Q52: 2025 | R52: 0.58430846 | S52: 2025 | T52: 4.8292075 | U52: 2025 | V52: 2.048 | W52: 2.14 | X52: н/д | Y52: 1.119 | Z52: н/д | AA52: Бензин/дизель/LPG: USD/л; Jet/мазут: исходные единицы | AB52: Бензин: 2026-09-14; Дизель: 2026-09-14; LPG: 2026-09-14; исходные даты для непроверенных значений: бензин: 2026-09-14; дизель/LPG: 2026-09-07; Jet/мазут: н/д | AC52: https://api.eia.gov/v2/international/data/?frequency=annual&facets[productId][]=53&facets[activityId][]=1&facets[unit][]=TBPD ; https://api.eia.gov/v2/international/data/?frequency=annual&facets[productId][]=57&facets[activityId][]=1&facets[unit][]=TBPD ; https://api.eia.gov/v2/international/data/?frequency=annual&facets[productId][]=58&facets[activityId][]=1&facets[unit][]=TBPD ; https://www.jodidata.org/_resources/files/downloads/oil-data/annual-csv/secondary/2025.csv ; Исходный источник: https://www.jodidata.org/oil/database/data-downloads.aspx | AD52: https://api.worldbank.org/v2/country/EST/indicator/NY.GDP.MKTP.CD?format=json ; https://api.worldbank.org/v2/country/EST/indicator/NY.GDP.MKTP.KD.ZG?format=json ; https://api.worldbank.org/v2/country/EST/indicator/FP.CPI.TOTL.ZG?format=json ; Исходный источник: https://data.worldbank.org/ | AE52: https://www.globalpetrolprices.com/Estonia/gasoline_prices/ ; https://www.globalpetrolprices.com/Estonia/diesel_prices/ ; https://www.globalpetrolprices.com/Estonia/lpg_prices/ ; Исходный источник: GlobalPetrolPrices (страновые значения только там, где они были явно помечены как страновые); Jet/мазут: н/д | AF52: Массовые оценки/медианы удалены в ходе аудита. Сохранившиеся исходные числовые значения не считаются подтверждёнными автоматически; требуется первичная проверка источника. Обновление 16.09.2026: Потребление и доли: JODI, нефтепродукты TOTPRODS, 12 месяцев 2025. Jet/мазут: национальные сопоставимые цены не найдены; исходные значения сохранены. | AG52: Бензин: проверено GPP; Дизель: проверено GPP; LPG: проверено GPP; Jet/керосин: нет сопоставимой национальной цены; Мазут: нет сопоставимой национальной цены | AH52: EE | AI52: EST | AJ52: ='Сводка НПЗ'!D52 -> 0 | AK52: =IF('Сводка НПЗ'!F52>0,'Сводка НПЗ'!E52,"") | AL52: ='Сводка НПЗ'!G52 -> 0 | AM52: 2019-02-18 | AN52: Свежие число и мощность не подтверждены | AO52: 2025 | AP52: 2025 | AQ52: 2025 | AR52: 2026-09-16
A53: 52 | B53: Latvia | C53: Латвия | D53: 32816.438 | E53: 2025 | F53: =IF(AND(ISNUMBER(D53),ISNUMBER(E53)),D53*(DATE(E53+1,1,1)-DATE(E53,1,1))/1000000,"н/д") -> 11.978 | G53: 67.014193 | H53: 11.851728 | I53: 7.4570045 | J53: 17.104692 | K53: 0 | L53: 1595 | M53: 2025 | N53: 0 | O53: 0 | P53: 48.618869 | Q53: 2025 | R53: 2.1378686 | S53: 2025 | T53: 3.7457732 | U53: 2025 | V53: 2.239 | W53: 2.407 | X53: н/д | Y53: 1.183 | Z53: н/д | AA53: Бензин/дизель/LPG: USD/л; Jet/мазут: исходные единицы | AB53: Бензин: 2026-09-14; Дизель: 2026-09-14; LPG: 2026-09-14; исходные даты для непроверенных значений: бензин: 2026-09-14; дизель/LPG: 2026-09-07; Jet/мазут: н/д | AC53: https://api.eia.gov/v2/international/data/?frequency=annual&facets[productId][]=53&facets[activityId][]=1&facets[unit][]=TBPD ; https://api.eia.gov/v2/international/data/?frequency=annual&facets[productId][]=57&facets[activityId][]=1&facets[unit][]=TBPD ; https://api.eia.gov/v2/international/data/?frequency=annual&facets[productId][]=58&facets[activityId][]=1&facets[unit][]=TBPD ; https://www.jodidata.org/_resources/files/downloads/oil-data/annual-csv/secondary/2025.csv ; Исходный источник: https://www.jodidata.org/oil/database/data-downloads.aspx ; https://www.worldometers.info/oil/ | AD53: https://api.worldbank.org/v2/country/LVA/indicator/NY.GDP.MKTP.CD?format=json ; https://api.worldbank.org/v2/country/LVA/indicator/NY.GDP.MKTP.KD.ZG?format=json ; https://api.worldbank.org/v2/country/LVA/indicator/FP.CPI.TOTL.ZG?format=json ; Исходный источник: https://data.worldbank.org/ | AE53: https://www.globalpetrolprices.com/Latvia/gasoline_prices/ ; https://www.globalpetrolprices.com/Latvia/diesel_prices/ ; https://www.globalpetrolprices.com/Latvia/lpg_prices/ ; Исходный источник: GlobalPetrolPrices (страновые значения только там, где они были явно помечены как страновые); Jet/мазут: н/д | AF53: Массовые оценки/медианы удалены в ходе аудита. Сохранившиеся исходные числовые значения не считаются подтверждёнными автоматически; требуется первичная проверка источника. Обновление 16.09.2026: Потребление и доли: JODI, нефтепродукты TOTPRODS, 12 месяцев 2025. Jet/мазут: национальные сопоставимые цены не найдены; исходные значения сохранены. | AG53: Бензин: проверено GPP; Дизель: проверено GPP; LPG: проверено GPP; Jet/керосин: нет сопоставимой национальной цены; Мазут: нет сопоставимой национальной цены | AH53: LV | AI53: LVA | AJ53: ='Сводка НПЗ'!D53 -> 0 | AK53: =IF('Сводка НПЗ'!F53>0,'Сводка НПЗ'!E53,"") | AL53: ='Сводка НПЗ'!G53 -> 0 | AM53: 2019-02-18 | AN53: Свежие число и мощность не подтверждены | AO53: 2025 | AP53: 2025 | AQ53: 2025 | AR53: 2026-09-16
A54: 53 | B54: Norway | C54: Норвегия | D54: 219912.33 | E54: 2025 | F54: =IF(AND(ISNUMBER(D54),ISNUMBER(E54)),D54*(DATE(E54+1,1,1)-DATE(E54,1,1))/1000000,"н/д") -> 80.268 | G54: 39.071411 | H54: 6.4637215 | I54: 22.053122 | J54: 17.386107 | K54: 0 | L54: 2051847.5 | M54: 2025 | N54: 1858464.2 | O54: 187033.51 | P54: 530.75572 | Q54: 2025 | R54: 1.0852819 | S54: 2025 | T54: 3.0556248 | U54: 2025 | V54: 3.164 | W54: 3.036 | X54: н/д | Y54: н/д | Z54: н/д | AA54: Бензин/дизель/LPG: USD/л; Jet/мазут: исходные единицы | AB54: Бензин: 2026-09-14; Дизель: 2026-09-14; исходные даты для непроверенных значений: бензин: 2026-09-14; дизель/LPG: 2026-09-07; Jet/мазут: н/д | AC54: https://api.eia.gov/v2/international/data/?frequency=annual&facets[productId][]=53&facets[activityId][]=1&facets[unit][]=TBPD ; https://api.eia.gov/v2/international/data/?frequency=annual&facets[productId][]=57&facets[activityId][]=1&facets[unit][]=TBPD ; https://api.eia.gov/v2/international/data/?frequency=annual&facets[productId][]=58&facets[activityId][]=1&facets[unit][]=TBPD ; https://www.jodidata.org/_resources/files/downloads/oil-data/annual-csv/secondary/2025.csv ; Исходный источник: https://www.jodidata.org/oil/database/data-downloads.aspx ; https://www.worldometers.info/oil/ | AD54: https://api.worldbank.org/v2/country/NOR/indicator/NY.GDP.MKTP.CD?format=json ; https://api.worldbank.org/v2/country/NOR/indicator/NY.GDP.MKTP.KD.ZG?format=json ; https://api.worldbank.org/v2/country/NOR/indicator/FP.CPI.TOTL.ZG?format=json ; Исходный источник: https://data.worldbank.org/ | AE54: https://www.globalpetrolprices.com/Norway/gasoline_prices/ ; https://www.globalpetrolprices.com/Norway/diesel_prices/ ; Исходный источник: GlobalPetrolPrices (страновые значения только там, где они были явно помечены как страновые); Jet/мазут: н/д | AF54: Массовые оценки/медианы удалены в ходе аудита. Сохранившиеся исходные числовые значения не считаются подтверждёнными автоматически; требуется первичная проверка источника. Обновление 16.09.2026: Потребление и доли: JODI, нефтепродукты TOTPRODS, 12 месяцев 2025. Jet/мазут: национальные сопоставимые цены не найдены; исходные значения сохранены. | AG54: Бензин: проверено GPP; Дизель: проверено GPP; LPG: н/д; Jet/керосин: нет сопоставимой национальной цены; Мазут: нет сопоставимой национальной цены | AH54: NO | AI54: NOR | AJ54: ='Сводка НПЗ'!D54 -> 2 | AK54: =IF('Сводка НПЗ'!F54>0,'Сводка НПЗ'!E54,"") -> 200000 | AL54: ='Сводка НПЗ'!G54 -> 0 | AM54: 2019-02-18 | AN54: Проверен первичный источник; см. охват | AO54: 2025 | AP54: 2025 | AQ54: 2025 | AR54: 2026-09-16
A55: 54 | B55: Sweden | C55: Швеция | D55: 281676.71 | E55: 2025 | F55: =IF(AND(ISNUMBER(D55),ISNUMBER(E55)),D55*(DATE(E55+1,1,1)-DATE(E55,1,1))/1000000,"н/д") -> 102.812 | G55: 39.987608 | H55: 17.17747 | I55: 10.301132 | J55: 11.573357 | K55: 7.9862759 | L55: 13917.813 | M55: 2025 | N55: 0 | O55: 0 | P55: 668.99866 | Q55: 2025 | R55: 1.5431637 | S55: 2025 | T55: 0.67986929 | U55: 2025 | V55: 1.896 | W55: 2.356 | X55: н/д | Y55: н/д | Z55: н/д | AA55: Бензин/дизель/LPG: USD/л; Jet/мазут: исходные единицы | AB55: Бензин: 2026-09-14; Дизель: 2026-09-14; исходные даты для непроверенных значений: бензин: 2026-09-14; дизель/LPG: 2026-09-07; Jet/мазут: н/д | AC55: https://api.eia.gov/v2/international/data/?frequency=annual&facets[productId][]=53&facets[activityId][]=1&facets[unit][]=TBPD ; https://api.eia.gov/v2/international/data/?frequency=annual&facets[productId][]=57&facets[activityId][]=1&facets[unit][]=TBPD ; https://api.eia.gov/v2/international/data/?frequency=annual&facets[productId][]=58&facets[activityId][]=1&facets[unit][]=TBPD ; https://www.jodidata.org/_resources/files/downloads/oil-data/annual-csv/secondary/2025.csv ; Исходный источник: https://www.jodidata.org/oil/database/data-downloads.aspx ; https://www.worldometers.info/oil/ | AD55: https://api.worldbank.org/v2/country/SWE/indicator/NY.GDP.MKTP.CD?format=json ; https://api.worldbank.org/v2/country/SWE/indicator/NY.GDP.MKTP.KD.ZG?format=json ; https://api.worldbank.org/v2/country/SWE/indicator/FP.CPI.TOTL.ZG?format=json ; Исходный источник: https://data.worldbank.org/ | AE55: https://www.globalpetrolprices.com/Sweden/gasoline_prices/ ; https://www.globalpetrolprices.com/Sweden/diesel_prices/ ; Исходный источник: GlobalPetrolPrices (страновые значения только там, где они были явно помечены как страновые); Jet/мазут: н/д | AF55: Массовые оценки/медианы удалены в ходе аудита. Сохранившиеся исходные числовые значения не считаются подтверждёнными автоматически; требуется первичная проверка источника. Обновление 16.09.2026: Потребление и доли: JODI, нефтепродукты TOTPRODS, 12 месяцев 2025. Jet/мазут: национальные сопоставимые цены не найдены; исходные значения сохранены. | AG55: Бензин: проверено GPP; Дизель: проверено GPP; LPG: н/д; Jet/керосин: нет сопоставимой национальной цены; Мазут: нет сопоставимой национальной цены | AH55: SE | AI55: SWE | AJ55: ='Сводка НПЗ'!D55 -> 5 | AK55: =IF('Сводка НПЗ'!F55>0,'Сводка НПЗ'!E55,"") -> 416000 | AL55: ='Сводка НПЗ'!G55 -> 0 | AM55: 2019-02-18 | AN55: Проверен первичный источник; см. охват | AO55: 2025 | AP55: 2025 | AQ55: 2025 | AR55: 2026-09-16
A56: 55 | B56: Finland | C56: Финляндия | D56: 168227.4 | E56: 2025 | F56: =IF(AND(ISNUMBER(D56),ISNUMBER(E56)),D56*(DATE(E56+1,1,1)-DATE(E56,1,1))/1000000,"н/д") -> 61.403 | G56: 40.785011 | H56: 17.75239 | I56: 18.929368 | J56: 20.404866 | K56: 3.3193818 | L56: 16787.699 | M56: 2025 | N56: 0 | O56: 0 | P56: 317.03937 | Q56: 2025 | R56: 0.17344451 | S56: 2025 | T56: 0.33787466 | U56: 2025 | V56: 2.602 | W56: 2.775 | X56: н/д | Y56: н/д | Z56: н/д | AA56: Бензин/дизель/LPG: USD/л; Jet/мазут: исходные единицы | AB56: Бензин: 2026-09-14; Дизель: 2026-09-14; исходные даты для непроверенных значений: бензин: 2026-09-14; дизель/LPG: 2026-09-07; Jet/мазут: н/д | AC56: https://api.eia.gov/v2/international/data/?frequency=annual&facets[productId][]=53&facets[activityId][]=1&facets[unit][]=TBPD ; https://api.eia.gov/v2/international/data/?frequency=annual&facets[productId][]=57&facets[activityId][]=1&facets[unit][]=TBPD ; https://api.eia.gov/v2/international/data/?frequency=annual&facets[productId][]=58&facets[activityId][]=1&facets[unit][]=TBPD ; https://www.jodidata.org/_resources/files/downloads/oil-data/annual-csv/secondary/2025.csv ; Исходный источник: https://www.jodidata.org/oil/database/data-downloads.aspx | AD56: https://api.worldbank.org/v2/country/FIN/indicator/NY.GDP.MKTP.CD?format=json ; https://api.worldbank.org/v2/country/FIN/indicator/NY.GDP.MKTP.KD.ZG?format=json ; https://api.worldbank.org/v2/country/FIN/indicator/FP.CPI.TOTL.ZG?format=json ; Исходный источник: https://data.worldbank.org/ | AE56: https://www.globalpetrolprices.com/Finland/gasoline_prices/ ; https://www.globalpetrolprices.com/Finland/diesel_prices/ ; Исходный источник: GlobalPetrolPrices (страновые значения только там, где они были явно помечены как страновые); Jet/мазут: н/д | AF56: Массовые оценки/медианы удалены в ходе аудита. Сохранившиеся исходные числовые значения не считаются подтверждёнными автоматически; требуется первичная проверка источника. Обновление 16.09.2026: Потребление и доли: JODI, нефтепродукты TOTPRODS, 12 месяцев 2025. Jet/мазут: национальные сопоставимые цены не найдены; исходные значения сохранены. | AG56: Бензин: проверено GPP; Дизель: проверено GPP; LPG: н/д; Jet/керосин: нет сопоставимой национальной цены; Мазут: нет сопоставимой национальной цены | AH56: FI | AI56: FIN | AJ56: ='Сводка НПЗ'!D56 -> 2 | AK56: =IF('Сводка НПЗ'!F56>0,'Сводка НПЗ'!E56,"") -> 200000 | AL56: ='Сводка НПЗ'!G56 -> 0 | AM56: 2019-02-18 | AN56: Проверен первичный источник; см. охват | AO56: 2025 | AP56: 2025 | AQ56: 2025 | AR56: 2026-09-16
A57: 56 | B57: Vietnam | C57: Вьетнам | D57: 555217.94 | E57: 2024 | F57: =IF(AND(ISNUMBER(D57),ISNUMBER(E57)),D57*(DATE(E57+1,1,1)-DATE(E57,1,1))/1000000,"н/д") -> 203.20977 | G57: 38.439785 | H57: 31.483948 | I57: 13.401392 | J57: 10.653617 | K57: 1.6675361 | L57: 199074.03 | M57: 2025 | N57: 164669.96 | O57: 24000 | P57: 514.69722 | Q57: 2025 | R57: 8.01883 | S57: 2025 | T57: 3.3099931 | U57: 2025 | V57: 0.968 | W57: 1.108 | X57: н/д | Y57: н/д | Z57: н/д | AA57: Бензин/дизель/LPG: USD/л; Jet/мазут: исходные единицы | AB57: Бензин: 2026-09-14; Дизель: 2026-09-14; исходные даты для непроверенных значений: бензин: 2026-09-14; дизель/LPG: 2026-09-07; Jet/мазут: н/д | AC57: https://api.eia.gov/v2/international/data/?frequency=annual&facets[productId][]=53&facets[activityId][]=1&facets[unit][]=TBPD ; https://api.eia.gov/v2/international/data/?frequency=annual&facets[productId][]=57&facets[activityId][]=1&facets[unit][]=TBPD ; https://api.eia.gov/v2/international/data/?frequency=annual&facets[productId][]=58&facets[activityId][]=1&facets[unit][]=TBPD ; https://api.eia.gov/v2/international/data/?frequency=annual&facets[productId][]=5&facets[activityId][]=2&facets[unit][]=TBPD ; Исходный источник: https://www.jodidata.org/oil/database/data-downloads.aspx | AD57: https://api.worldbank.org/v2/country/VNM/indicator/NY.GDP.MKTP.CD?format=json ; https://api.worldbank.org/v2/country/VNM/indicator/NY.GDP.MKTP.KD.ZG?format=json ; https://api.worldbank.org/v2/country/VNM/indicator/FP.CPI.TOTL.ZG?format=json ; Исходный источник: https://data.worldbank.org/ | AE57: https://www.globalpetrolprices.com/Vietnam/gasoline_prices/ ; https://www.globalpetrolprices.com/Vietnam/diesel_prices/ ; Исходный источник: GlobalPetrolPrices (страновые значения только там, где они были явно помечены как страновые); Jet/мазут: н/д | AF57: Массовые оценки/медианы удалены в ходе аудита. Сохранившиеся исходные числовые значения не считаются подтверждёнными автоматически; требуется первичная проверка источника. Обновление 16.09.2026: Потребление и доли: EIA, petroleum and other liquids, 2024; включает биотопливо. Jet/мазут: национальные сопоставимые цены не найдены; исходные значения сохранены. | AG57: Бензин: проверено GPP; Дизель: проверено GPP; LPG: н/д; Jet/керосин: нет сопоставимой национальной цены; Мазут: нет сопоставимой национальной цены | AH57: VN | AI57: VNM | AJ57: ='Сводка НПЗ'!D57 -> 0 | AK57: =IF('Сводка НПЗ'!F57>0,'Сводка НПЗ'!E57,"") | AL57: ='Сводка НПЗ'!G57 -> 0 | AM57: 2019-02-18 | AN57: Мощность: вторичная публикация EI; число НПЗ не подтверждено | AO57: 2024 | AP57: 2025 | AQ57: 2025 | AR57: 2026-09-16
A58: 57 | B58: Cambodia | C58: Камбоджа | D58: 73533.18 | E58: 2024 | F58: =IF(AND(ISNUMBER(D58),ISNUMBER(E58)),D58*(DATE(E58+1,1,1)-DATE(E58,1,1))/1000000,"н/д") -> 26.913144 | G58: 52.943632 | H58: 26.684688 | I58: 15.995374 | J58: 2.2414761 | K58: 1.6535479 | L58: 0 | M58: 2025 | N58: 0 | O58: 0 | P58: 51.267066 | Q58: 2025 | R58: 5.3493208 | S58: 2025 | T58: 2.3512711 | U58: 2025 | V58: 1.505 | W58: 1.345 | X58: н/д | Y58: н/д | Z58: н/д | AA58: Бензин/дизель/LPG: USD/л; Jet/мазут: исходные единицы | AB58: Бензин: 2026-09-14; Дизель: 2026-09-14; исходные даты для непроверенных значений: бензин: 2026-09-14; дизель/LPG: 2026-09-07; Jet/мазут: н/д | AC58: https://api.eia.gov/v2/international/data/?frequency=annual&facets[productId][]=53&facets[activityId][]=1&facets[unit][]=TBPD ; https://api.eia.gov/v2/international/data/?frequency=annual&facets[productId][]=57&facets[activityId][]=1&facets[unit][]=TBPD ; https://api.eia.gov/v2/international/data/?frequency=annual&facets[productId][]=58&facets[activityId][]=1&facets[unit][]=TBPD ; https://api.eia.gov/v2/international/data/?frequency=annual&facets[productId][]=5&facets[activityId][]=2&facets[unit][]=TBPD ; Исходный источник: https://www.jodidata.org/oil/database/data-downloads.aspx | AD58: https://api.worldbank.org/v2/country/KHM/indicator/NY.GDP.MKTP.CD?format=json ; https://api.worldbank.org/v2/country/KHM/indicator/NY.GDP.MKTP.KD.ZG?format=json ; https://api.worldbank.org/v2/country/KHM/indicator/FP.CPI.TOTL.ZG?format=json ; Исходный источник: https://data.worldbank.org/ | AE58: https://www.globalpetrolprices.com/Cambodia/gasoline_prices/ ; https://www.globalpetrolprices.com/Cambodia/diesel_prices/ ; Исходный источник: GlobalPetrolPrices (страновые значения только там, где они были явно помечены как страновые); Jet/мазут: н/д | AF58: Массовые оценки/медианы удалены в ходе аудита. Сохранившиеся исходные числовые значения не считаются подтверждёнными автоматически; требуется первичная проверка источника. Обновление 16.09.2026: Потребление и доли: EIA, petroleum and other liquids, 2024; включает биотопливо. Jet/мазут: национальные сопоставимые цены не найдены; исходные значения сохранены. | AG58: Бензин: проверено GPP; Дизель: проверено GPP; LPG: н/д; Jet/керосин: нет сопоставимой национальной цены; Мазут: нет сопоставимой национальной цены | AH58: KH | AI58: KHM | AJ58: ='Сводка НПЗ'!D58 -> 0 | AK58: =IF('Сводка НПЗ'!F58>0,'Сводка НПЗ'!E58,"") | AL58: ='Сводка НПЗ'!G58 -> 0 | AM58: 2019-02-18 | AN58: Свежие число и мощность не подтверждены | AO58: 2024 | AP58: 2025 | AQ58: 2025 | AR58: 2026-09-16
A59: 58 | B59: Luxembourg | C59: Люксембург | D59: 47046.575 | E59: 2025 | F59: =IF(AND(ISNUMBER(D59),ISNUMBER(E59)),D59*(DATE(E59+1,1,1)-DATE(E59,1,1))/1000000,"н/д") -> 17.172 | G59: 50.523993 | H59: 20.372117 | I59: 0.81062194 | J59: 54.882833 | K59: 0 | L59: 0 | M59: 2025 | N59: 0 | O59: 0 | P59: 101.15783 | Q59: 2025 | R59: 0.63787819 | S59: 2025 | T59: 2.2572382 | U59: 2025 | V59: 2.191 | W59: 2.451 | X59: н/д | Y59: 0.914 | Z59: н/д | AA59: Бензин/дизель/LPG: USD/л; Jet/мазут: исходные единицы | AB59: Бензин: 2026-09-14; Дизель: 2026-09-14; LPG: 2026-09-14; исходные даты для непроверенных значений: бензин: 2026-09-14; дизель/LPG: 2026-09-07; Jet/мазут: н/д | AC59: https://api.eia.gov/v2/international/data/?frequency=annual&facets[productId][]=53&facets[activityId][]=1&facets[unit][]=TBPD ; https://api.eia.gov/v2/international/data/?frequency=annual&facets[productId][]=57&facets[activityId][]=1&facets[unit][]=TBPD ; https://api.eia.gov/v2/international/data/?frequency=annual&facets[productId][]=58&facets[activityId][]=1&facets[unit][]=TBPD ; https://www.jodidata.org/_resources/files/downloads/oil-data/annual-csv/secondary/2025.csv ; Исходный источник: https://www.jodidata.org/oil/database/data-downloads.aspx ; https://www.worldometers.info/oil/oil-consumption-by-country/ | AD59: https://api.worldbank.org/v2/country/LUX/indicator/NY.GDP.MKTP.CD?format=json ; https://api.worldbank.org/v2/country/LUX/indicator/NY.GDP.MKTP.KD.ZG?format=json ; https://api.worldbank.org/v2/country/LUX/indicator/FP.CPI.TOTL.ZG?format=json ; Исходный источник: https://data.worldbank.org/ | AE59: https://www.globalpetrolprices.com/Luxembourg/gasoline_prices/ ; https://www.globalpetrolprices.com/Luxembourg/diesel_prices/ ; https://www.globalpetrolprices.com/Luxembourg/lpg_prices/ ; Исходный источник: GlobalPetrolPrices (страновые значения только там, где они были явно помечены как страновые); Jet/мазут: н/д | AF59: Массовые оценки/медианы удалены в ходе аудита. Сохранившиеся исходные числовые значения не считаются подтверждёнными автоматически; требуется первичная проверка источника. Обновление 16.09.2026: Потребление и доли: JODI, нефтепродукты TOTPRODS, 12 месяцев 2025. Jet/мазут: национальные сопоставимые цены не найдены; исходные значения сохранены. | AG59: Бензин: проверено GPP; Дизель: проверено GPP; LPG: проверено GPP; Jet/керосин: нет сопоставимой национальной цены; Мазут: нет сопоставимой национальной цены | AH59: LU | AI59: LUX | AJ59: ='Сводка НПЗ'!D59 -> 0 | AK59: =IF('Сводка НПЗ'!F59>0,'Сводка НПЗ'!E59,"") | AL59: ='Сводка НПЗ'!G59 -> 0 | AM59: 2019-02-18 | AN59: Свежие число и мощность не подтверждены | AO59: 2025 | AP59: 2025 | AQ59: 2025 | AR59: 2026-09-16
A60: 59 | B60: United Arab Emirates | C60: Объединённые Арабские Эмираты | D60: 879803.95 | E60: 2024 | F60: =IF(AND(ISNUMBER(D60),ISNUMBER(E60)),D60*(DATE(E60+1,1,1)-DATE(E60,1,1))/1000000,"н/д") -> 322.00825 | G60: 8.5437103 | H60: 22.332166 | I60: 3.0256509 | J60: 24.067265 | K60: 40.828051 | L60: 4339251.1 | M60: 2025 | N60: 3771219.2 | O60: 551000 | P60: 552.32492 | Q60: 2024 | R60: 3.991812 | S60: 2024 | T60: 1.2508652 | U60: 2025 | V60: 1.005 | W60: 1.171 | X60: н/д | Y60: н/д | Z60: н/д | AA60: Бензин/дизель/LPG: USD/л; Jet/мазут: исходные единицы | AB60: Бензин: 2026-09-14; Дизель: 2026-09-14; исходные даты для непроверенных значений: бензин: 2026-09-14; дизель/LPG: 2026-09-07; Jet/мазут: н/д | AC60: https://api.eia.gov/v2/international/data/?frequency=annual&facets[productId][]=53&facets[activityId][]=1&facets[unit][]=TBPD ; https://api.eia.gov/v2/international/data/?frequency=annual&facets[productId][]=57&facets[activityId][]=1&facets[unit][]=TBPD ; https://api.eia.gov/v2/international/data/?frequency=annual&facets[productId][]=58&facets[activityId][]=1&facets[unit][]=TBPD ; https://api.eia.gov/v2/international/data/?frequency=annual&facets[productId][]=5&facets[activityId][]=2&facets[unit][]=TBPD ; Исходный источник: https://www.jodidata.org/oil/database/data-downloads.aspx ; https://www.worldometers.info/oil/ | AD60: https://api.worldbank.org/v2/country/ARE/indicator/NY.GDP.MKTP.CD?format=json ; https://api.worldbank.org/v2/country/ARE/indicator/NY.GDP.MKTP.KD.ZG?format=json ; https://api.worldbank.org/v2/country/ARE/indicator/FP.CPI.TOTL.ZG?format=json ; Исходный источник: https://data.worldbank.org/ | AE60: https://www.globalpetrolprices.com/United-Arab-Emirates/gasoline_prices/ ; https://www.globalpetrolprices.com/United-Arab-Emirates/diesel_prices/ ; Исходный источник: GlobalPetrolPrices (страновые значения только там, где они были явно помечены как страновые); Jet/мазут: н/д | AF60: Массовые оценки/медианы удалены в ходе аудита. Сохранившиеся исходные числовые значения не считаются подтверждёнными автоматически; требуется первичная проверка источника. Обновление 16.09.2026: Потребление и доли: EIA, petroleum and other liquids, 2024; включает биотопливо. Jet/мазут: национальные сопоставимые цены не найдены; исходные значения сохранены. | AG60: Бензин: проверено GPP; Дизель: проверено GPP; LPG: н/д; Jet/керосин: нет сопоставимой национальной цены; Мазут: нет сопоставимой национальной цены | AH60: AE | AI60: ARE | AJ60: ='Сводка НПЗ'!D60 -> 5 | AK60: =IF('Сводка НПЗ'!F60>0,'Сводка НПЗ'!E60,"") -> 631300 | AL60: ='Сводка НПЗ'!G60 -> 0 | AM60: 2019-02-18 | AN60: Мощность: вторичная публикация EI; число НПЗ не подтверждено | AO60: 2024 | AP60: 2025 | AQ60: 2025 | AR60: 2026-09-16
A61: 60 | B61: Belgium | C61: Бельгия | D61: 625000 | E61: 2025 | F61: =IF(AND(ISNUMBER(D61),ISNUMBER(E61)),D61*(DATE(E61+1,1,1)-DATE(E61,1,1))/1000000,"н/д") -> 228.125 | G61: 29.787678 | H61: 10.508559 | I61: 13.556427 | J61: 13.633911 | K61: 16.636405 | L61: 24697.603 | M61: 2025 | N61: 0 | O61: 0 | P61: 725.46646 | Q61: 2025 | R61: 0.98311797 | S61: 2025 | T61: 2.4670554 | U61: 2025 | V61: 2.289 | W61: 2.759 | X61: н/д | Y61: 1.09 | Z61: н/д | AA61: Бензин/дизель/LPG: USD/л; Jet/мазут: исходные единицы | AB61: Бензин: 2026-09-14; Дизель: 2026-09-14; LPG: 2026-09-14; исходные даты для непроверенных значений: бензин: 2026-09-14; дизель/LPG: 2026-09-07; Jet/мазут: н/д | AC61: https://api.eia.gov/v2/international/data/?frequency=annual&facets[productId][]=53&facets[activityId][]=1&facets[unit][]=TBPD ; https://api.eia.gov/v2/international/data/?frequency=annual&facets[productId][]=57&facets[activityId][]=1&facets[unit][]=TBPD ; https://api.eia.gov/v2/international/data/?frequency=annual&facets[productId][]=58&facets[activityId][]=1&facets[unit][]=TBPD ; https://www.jodidata.org/_resources/files/downloads/oil-data/annual-csv/secondary/2025.csv ; Исходный источник: https://www.jodidata.org/oil/database/data-downloads.aspx | AD61: https://api.worldbank.org/v2/country/BEL/indicator/NY.GDP.MKTP.CD?format=json ; https://api.worldbank.org/v2/country/BEL/indicator/NY.GDP.MKTP.KD.ZG?format=json ; https://api.worldbank.org/v2/country/BEL/indicator/FP.CPI.TOTL.ZG?format=json ; Исходный источник: https://data.worldbank.org/ | AE61: https://www.globalpetrolprices.com/Belgium/gasoline_prices/ ; https://www.globalpetrolprices.com/Belgium/diesel_prices/ ; https://www.globalpetrolprices.com/Belgium/lpg_prices/ ; Исходный источник: GlobalPetrolPrices (страновые значения только там, где они были явно помечены как страновые); Jet/мазут: н/д | AF61: Массовые оценки/медианы удалены в ходе аудита. Сохранившиеся исходные числовые значения не считаются подтверждёнными автоматически; требуется первичная проверка источника. Обновление 16.09.2026: Потребление и доли: JODI, нефтепродукты TOTPRODS, 12 месяцев 2025. Jet/мазут: национальные сопоставимые цены не найдены; исходные значения сохранены. | AG61: Бензин: проверено GPP; Дизель: проверено GPP; LPG: проверено GPP; Jet/керосин: нет сопоставимой национальной цены; Мазут: нет сопоставимой национальной цены | AH61: BE | AI61: BEL | AJ61: ='Сводка НПЗ'!D61 -> 4 | AK61: =IF('Сводка НПЗ'!F61>0,'Сводка НПЗ'!E61,"") -> 767000 | AL61: ='Сводка НПЗ'!G61 -> 0 | AM61: 2019-02-18 | AN61: Проверен первичный источник; см. охват | AO61: 2025 | AP61: 2025 | AQ61: 2025 | AR61: 2026-09-16
A62: 61 | B62: Georgia | C62: Грузия | D62: 41821.918 | E62: 2025 | F62: =IF(AND(ISNUMBER(D62),ISNUMBER(E62)),D62*(DATE(E62+1,1,1)-DATE(E62,1,1))/1000000,"н/д") -> 15.265 | G62: 31.558467 | H62: 40.704225 | I62: 7.8270554 | J62: 24.540583 | K62: н/д | L62: 223.46849 | M62: 2025 | N62: 223.46849 | O62: 0 | P62: 38.143613 | Q62: 2025 | R62: 7.461615 | S62: 2025 | T62: 3.8692132 | U62: 2025 | V62: 1.546 | W62: 1.773 | X62: н/д | Y62: н/д | Z62: н/д | AA62: Бензин/дизель/LPG: USD/л; Jet/мазут: исходные единицы | AB62: Бензин: 2026-09-14; Дизель: 2026-09-14; исходные даты для непроверенных значений: бензин: 2026-09-14; дизель/LPG: 2026-09-07; Jet/мазут: н/д | AC62: https://api.eia.gov/v2/international/data/?frequency=annual&facets[productId][]=53&facets[activityId][]=1&facets[unit][]=TBPD ; https://api.eia.gov/v2/international/data/?frequency=annual&facets[productId][]=57&facets[activityId][]=1&facets[unit][]=TBPD ; https://api.eia.gov/v2/international/data/?frequency=annual&facets[productId][]=58&facets[activityId][]=1&facets[unit][]=TBPD ; https://www.jodidata.org/_resources/files/downloads/oil-data/annual-csv/secondary/2025.csv ; Исходный источник: https://www.jodidata.org/oil/database/data-downloads.aspx ; https://www.worldometers.info/oil/georgia-oil/ | AD62: https://api.worldbank.org/v2/country/GEO/indicator/NY.GDP.MKTP.CD?format=json ; https://api.worldbank.org/v2/country/GEO/indicator/NY.GDP.MKTP.KD.ZG?format=json ; https://api.worldbank.org/v2/country/GEO/indicator/FP.CPI.TOTL.ZG?format=json ; Исходный источник: https://data.worldbank.org/ | AE62: https://www.globalpetrolprices.com/Georgia/gasoline_prices/ ; https://www.globalpetrolprices.com/Georgia/diesel_prices/ ; Исходный источник: GlobalPetrolPrices (страновые значения только там, где они были явно помечены как страновые); Jet/мазут: н/д | AF62: Массовые оценки/медианы удалены в ходе аудита. Сохранившиеся исходные числовые значения не считаются подтверждёнными автоматически; требуется первичная проверка источника. Обновление 16.09.2026: Потребление и доли: JODI, нефтепродукты TOTPRODS, 12 месяцев 2025. Jet/мазут: национальные сопоставимые цены не найдены; исходные значения сохранены. | AG62: Бензин: проверено GPP; Дизель: проверено GPP; LPG: н/д; Jet/керосин: нет сопоставимой национальной цены; Мазут: нет сопоставимой национальной цены | AH62: GE | AI62: GEO | AJ62: ='Сводка НПЗ'!D62 -> 0 | AK62: =IF('Сводка НПЗ'!F62>0,'Сводка НПЗ'!E62,"") | AL62: ='Сводка НПЗ'!G62 -> 0 | AM62: 2019-02-18 | AN62: Свежие число и мощность не подтверждены | AO62: 2025 | AP62: 2025 | AQ62: 2025 | AR62: 2026-09-16
A63: 62 | B63: North Macedonia | C63: Северная Македония | D63: 23521.695 | E63: 2024 | F63: =IF(AND(ISNUMBER(D63),ISNUMBER(E63)),D63*(DATE(E63+1,1,1)-DATE(E63,1,1))/1000000,"н/д") -> 8.6089404 | G63: 65.516199 | H63: 11.326413 | I63: 8.2418811 | J63: 0.55419543 | K63: 5.430137 | L63: 0 | M63: 2025 | N63: 0 | O63: 0 | P63: 19.1012 | Q63: 2025 | R63: 3.4870662 | S63: 2025 | T63: 4.0724918 | U63: 2025 | V63: 1.887 | W63: 1.859 | X63: н/д | Y63: 0.882 | Z63: н/д | AA63: Бензин/дизель/LPG: USD/л; Jet/мазут: исходные единицы | AB63: Бензин: 2026-09-14; Дизель: 2026-09-14; LPG: 2026-09-14; исходные даты для непроверенных значений: бензин: 2026-09-14; дизель/LPG: 2026-09-07; Jet/мазут: н/д | AC63: https://api.eia.gov/v2/international/data/?frequency=annual&facets[productId][]=53&facets[activityId][]=1&facets[unit][]=TBPD ; https://api.eia.gov/v2/international/data/?frequency=annual&facets[productId][]=57&facets[activityId][]=1&facets[unit][]=TBPD ; https://api.eia.gov/v2/international/data/?frequency=annual&facets[productId][]=58&facets[activityId][]=1&facets[unit][]=TBPD ; https://api.eia.gov/v2/international/data/?frequency=annual&facets[productId][]=5&facets[activityId][]=2&facets[unit][]=TBPD ; Исходный источник: https://www.jodidata.org/oil/database/data-downloads.aspx | AD63: https://api.worldbank.org/v2/country/MKD/indicator/NY.GDP.MKTP.CD?format=json ; https://api.worldbank.org/v2/country/MKD/indicator/NY.GDP.MKTP.KD.ZG?format=json ; https://api.worldbank.org/v2/country/MKD/indicator/FP.CPI.TOTL.ZG?format=json ; Исходный источник: https://data.worldbank.org/ | AE63: https://www.globalpetrolprices.com/Macedonia/gasoline_prices/ ; https://www.globalpetrolprices.com/Macedonia/diesel_prices/ ; https://www.globalpetrolprices.com/Macedonia/lpg_prices/ ; Исходный источник: GlobalPetrolPrices (страновые значения только там, где они были явно помечены как страновые); Jet/мазут: н/д | AF63: Массовые оценки/медианы удалены в ходе аудита. Сохранившиеся исходные числовые значения не считаются подтверждёнными автоматически; требуется первичная проверка источника. Обновление 16.09.2026: Потребление и доли: EIA, petroleum and other liquids, 2024; включает биотопливо. Jet/мазут: национальные сопоставимые цены не найдены; исходные значения сохранены. | AG63: Бензин: проверено GPP; Дизель: проверено GPP; LPG: проверено GPP; Jet/керосин: нет сопоставимой национальной цены; Мазут: нет сопоставимой национальной цены | AH63: MK | AI63: MKD | AJ63: ='Сводка НПЗ'!D63 -> 1 | AK63: =IF('Сводка НПЗ'!F63>0,'Сводка НПЗ'!E63,"") -> 50000 | AL63: ='Сводка НПЗ'!G63 -> 0 | AM63: 2019-02-18 | AN63: Свежие число и мощность не подтверждены | AO63: 2024 | AP63: 2025 | AQ63: 2025 | AR63: 2026-09-16
A64: 63 | B64: Albania | C64: Албания | D64: 24655.328 | E64: 2024 | F64: =IF(AND(ISNUMBER(D64),ISNUMBER(E64)),D64*(DATE(E64+1,1,1)-DATE(E64,1,1))/1000000,"н/д") -> 9.0238501 | G64: 53.965992 | H64: 8.435977 | I64: 21.655271 | J64: 5.9039727 | K64: 1.0360927 | L64: 12156.395 | M64: 2025 | N64: 12156.395 | O64: 0 | P64: 30.540188 | Q64: 2025 | R64: 3.7889384 | S64: 2025 | T64: 2.1461855 | U64: 2025 | V64: 2.578 | W64: 2.754 | X64: н/д | Y64: 0.868 | Z64: н/д | AA64: Бензин/дизель/LPG: USD/л; Jet/мазут: исходные единицы | AB64: Бензин: 2026-09-14; Дизель: 2026-09-14; LPG: 2026-09-14; исходные даты для непроверенных значений: бензин: 2026-09-14; дизель/LPG: 2026-09-07; Jet/мазут: н/д | AC64: https://api.eia.gov/v2/international/data/?frequency=annual&facets[productId][]=53&facets[activityId][]=1&facets[unit][]=TBPD ; https://api.eia.gov/v2/international/data/?frequency=annual&facets[productId][]=57&facets[activityId][]=1&facets[unit][]=TBPD ; https://api.eia.gov/v2/international/data/?frequency=annual&facets[productId][]=58&facets[activityId][]=1&facets[unit][]=TBPD ; https://api.eia.gov/v2/international/data/?frequency=annual&facets[productId][]=5&facets[activityId][]=2&facets[unit][]=TBPD ; Исходный источник: https://www.jodidata.org/oil/database/data-downloads.aspx ; https://www.worldometers.info/oil/oil-reserves-by-country/ | AD64: https://api.worldbank.org/v2/country/ALB/indicator/NY.GDP.MKTP.CD?format=json ; https://api.worldbank.org/v2/country/ALB/indicator/NY.GDP.MKTP.KD.ZG?format=json ; https://api.worldbank.org/v2/country/ALB/indicator/FP.CPI.TOTL.ZG?format=json ; Исходный источник: https://data.worldbank.org/ | AE64: https://www.globalpetrolprices.com/Albania/gasoline_prices/ ; https://www.globalpetrolprices.com/Albania/diesel_prices/ ; https://www.globalpetrolprices.com/Albania/lpg_prices/ ; Исходный источник: GlobalPetrolPrices (страновые значения только там, где они были явно помечены как страновые); Jet/мазут: н/д | AF64: Массовые оценки/медианы удалены в ходе аудита. Сохранившиеся исходные числовые значения не считаются подтверждёнными автоматически; требуется первичная проверка источника. Обновление 16.09.2026: Потребление и доли: EIA, petroleum and other liquids, 2024; включает биотопливо. Jet/мазут: национальные сопоставимые цены не найдены; исходные значения сохранены. | AG64: Бензин: проверено GPP; Дизель: проверено GPP; LPG: проверено GPP; Jet/керосин: нет сопоставимой национальной цены; Мазут: нет сопоставимой национальной цены | AH64: AL | AI64: ALB | AJ64: ='Сводка НПЗ'!D64 -> 2 | AK64: =IF('Сводка НПЗ'!F64>0,'Сводка НПЗ'!E64,"") -> 26300 | AL64: ='Сводка НПЗ'!G64 -> 0 | AM64: 2019-02-18 | AN64: Свежие число и мощность не подтверждены | AO64: 2024 | AP64: 2025 | AQ64: 2025 | AR64: 2026-09-16
A65: 64 | B65: Azerbaijan | C65: Азербайджан | D65: 119098.63 | E65: 2025 | F65: =IF(AND(ISNUMBER(D65),ISNUMBER(E65)),D65*(DATE(E65+1,1,1)-DATE(E65,1,1))/1000000,"н/д") -> 43.471 | G65: 31.79867 | H65: 31.774056 | I65: 5.8972648 | J65: 25.183042 | K65: 3.2895494 | L65: 566627.94 | M65: 2025 | N65: 560620.97 | O65: 984.03361 | P65: 75.937647 | Q65: 2025 | R65: 1.4498559 | S65: 2025 | T65: 5.6220879 | U65: 2025 | V65: 0.676 | W65: 0.647 | X65: н/д | Y65: 0.412 | Z65: н/д | AA65: Бензин/дизель/LPG: USD/л; Jet/мазут: исходные единицы | AB65: Бензин: 2026-09-14; Дизель: 2026-09-14; LPG: 2026-09-14; исходные даты для непроверенных значений: бензин: 2026-09-14; дизель/LPG: 2026-09-07; Jet/мазут: н/д | AC65: https://api.eia.gov/v2/international/data/?frequency=annual&facets[productId][]=53&facets[activityId][]=1&facets[unit][]=TBPD ; https://api.eia.gov/v2/international/data/?frequency=annual&facets[productId][]=57&facets[activityId][]=1&facets[unit][]=TBPD ; https://api.eia.gov/v2/international/data/?frequency=annual&facets[productId][]=58&facets[activityId][]=1&facets[unit][]=TBPD ; https://www.jodidata.org/_resources/files/downloads/oil-data/annual-csv/secondary/2025.csv ; Исходный источник: https://www.jodidata.org/oil/database/data-downloads.aspx ; https://www.worldometers.info/oil/azerbaijan-oil/ | AD65: https://api.worldbank.org/v2/country/AZE/indicator/NY.GDP.MKTP.CD?format=json ; https://api.worldbank.org/v2/country/AZE/indicator/NY.GDP.MKTP.KD.ZG?format=json ; https://api.worldbank.org/v2/country/AZE/indicator/FP.CPI.TOTL.ZG?format=json ; Исходный источник: https://data.worldbank.org/ | AE65: https://www.globalpetrolprices.com/Azerbaijan/gasoline_prices/ ; https://www.globalpetrolprices.com/Azerbaijan/diesel_prices/ ; https://www.globalpetrolprices.com/Azerbaijan/lpg_prices/ ; Исходный источник: GlobalPetrolPrices (страновые значения только там, где они были явно помечены как страновые); Jet/мазут: н/д | AF65: Массовые оценки/медианы удалены в ходе аудита. Сохранившиеся исходные числовые значения не считаются подтверждёнными автоматически; требуется первичная проверка источника. Обновление 16.09.2026: Потребление и доли: JODI, нефтепродукты TOTPRODS, 12 месяцев 2025. Jet/мазут: национальные сопоставимые цены не найдены; исходные значения сохранены. | AG65: Бензин: проверено GPP; Дизель: проверено GPP; LPG: проверено GPP; Jet/керосин: нет сопоставимой национальной цены; Мазут: нет сопоставимой национальной цены | AH65: AZ | AI65: AZE | AJ65: ='Сводка НПЗ'!D65 -> 2 | AK65: =IF('Сводка НПЗ'!F65>0,'Сводка НПЗ'!E65,"") -> 439000 | AL65: ='Сводка НПЗ'!G65 -> 0 | AM65: 2019-02-18 | AN65: Мощность: вторичная публикация EI; число НПЗ не подтверждено | AO65: 2025 | AP65: 2025 | AQ65: 2025 | AR65: 2026-09-16
A66: 65 | B66: Kosovo | C66: Республика Косово | D66: 18263.753 | E66: 2024 | F66: =IF(AND(ISNUMBER(D66),ISNUMBER(E66)),D66*(DATE(E66+1,1,1)-DATE(E66,1,1))/1000000,"н/д") -> 6.6845338 | G66: 74.641741 | H66: 8.8290753 | I66: 4.1762485 | J66: 0.71374244 | K66: 1.4985892 | L66: н/д | M66: н/д | N66: н/д | O66: н/д | P66: 12.456403 | Q66: 2025 | R66: 3.5921714 | S66: 2025 | T66: 3.8595387 | U66: 2025 | V66: н/д | W66: н/д | X66: н/д | Y66: н/д | Z66: н/д | AA66: бензин/дизель/LPG/Jet: USD/л; мазут: USD/т | AB66: бензин: 2026-09-14; дизель/LPG: 2026-09-07; Jet/мазут: н/д | AC66: https://api.eia.gov/v2/international/data/?frequency=annual&facets[productId][]=5&facets[activityId][]=2&facets[unit][]=TBPD ; Исходный источник: https://www.jodidata.org/oil/database/data-downloads.aspx | AD66: https://api.worldbank.org/v2/country/XKX/indicator/NY.GDP.MKTP.CD?format=json ; https://api.worldbank.org/v2/country/XKX/indicator/NY.GDP.MKTP.KD.ZG?format=json ; https://api.worldbank.org/v2/country/XKX/indicator/FP.CPI.TOTL.ZG?format=json ; Исходный источник: https://data.worldbank.org/ | AE66: GlobalPetrolPrices (страновые значения только там, где они были явно помечены как страновые); Jet/мазут: н/д | AF66: Массовые оценки/медианы удалены в ходе аудита. Сохранившиеся исходные числовые значения не считаются подтверждёнными автоматически; требуется первичная проверка источника. Обновление 16.09.2026: Потребление и доли: EIA, petroleum and other liquids, 2024; включает биотопливо. Jet/мазут: национальные сопоставимые цены не найдены; исходные значения сохранены. | AG66: Бензин: н/д; Дизель: н/д; LPG: н/д; Jet/керосин: нет сопоставимой национальной цены; Мазут: нет сопоставимой национальной цены | AH66: н/д | AI66: н/д | AJ66: ='Сводка НПЗ'!D66 -> 0 | AK66: =IF('Сводка НПЗ'!F66>0,'Сводка НПЗ'!E66,"") | AL66: ='Сводка НПЗ'!G66 -> 0 | AM66: 2019-02-18 | AN66: Свежие число и мощность не подтверждены | AO66: 2024 | AR66: 2026-09-16
A67: 66 | B67: Turkey | C67: Турция | D67: 1194361.6 | E67: 2025 | F67: =IF(AND(ISNUMBER(D67),ISNUMBER(E67)),D67*(DATE(E67+1,1,1)-DATE(E67,1,1))/1000000,"н/д") -> 435.942 | G67: 46.934092 | H67: 11.038796 | I67: 10.462676 | J67: 24.577664 | K67: 0.38172509 | L67: 142570.43 | M67: 2025 | N67: 124615.69 | O67: 0 | P67: 1597.2932 | Q67: 2025 | R67: 3.6046251 | S67: 2025 | T67: 34.881163 | U67: 2025 | V67: 1.651 | W67: 1.966 | X67: н/д | Y67: 0.688 | Z67: н/д | AA67: Бензин/дизель/LPG: USD/л; Jet/мазут: исходные единицы | AB67: Бензин: 2026-09-14; Дизель: 2026-09-14; LPG: 2026-09-14; исходные даты для непроверенных значений: бензин: 2026-09-14; дизель/LPG: 2026-09-07; Jet/мазут: н/д | AC67: https://api.eia.gov/v2/international/data/?frequency=annual&facets[productId][]=53&facets[activityId][]=1&facets[unit][]=TBPD ; https://api.eia.gov/v2/international/data/?frequency=annual&facets[productId][]=57&facets[activityId][]=1&facets[unit][]=TBPD ; https://api.eia.gov/v2/international/data/?frequency=annual&facets[productId][]=58&facets[activityId][]=1&facets[unit][]=TBPD ; https://www.jodidata.org/_resources/files/downloads/oil-data/annual-csv/secondary/2025.csv ; Исходный источник: https://www.jodidata.org/oil/database/data-downloads.aspx | AD67: https://api.worldbank.org/v2/country/TUR/indicator/NY.GDP.MKTP.CD?format=json ; https://api.worldbank.org/v2/country/TUR/indicator/NY.GDP.MKTP.KD.ZG?format=json ; https://api.worldbank.org/v2/country/TUR/indicator/FP.CPI.TOTL.ZG?format=json ; Исходный источник: https://data.worldbank.org/ | AE67: https://www.globalpetrolprices.com/Turkey/gasoline_prices/ ; https://www.globalpetrolprices.com/Turkey/diesel_prices/ ; https://www.globalpetrolprices.com/Turkey/lpg_prices/ ; Исходный источник: GlobalPetrolPrices (страновые значения только там, где они были явно помечены как страновые); Jet/мазут: н/д | AF67: Массовые оценки/медианы удалены в ходе аудита. Сохранившиеся исходные числовые значения не считаются подтверждёнными автоматически; требуется первичная проверка источника. Обновление 16.09.2026: Потребление и доли: JODI, нефтепродукты TOTPRODS, 12 месяцев 2025. Jet/мазут: национальные сопоставимые цены не найдены; исходные значения сохранены. | AG67: Бензин: проверено GPP; Дизель: проверено GPP; LPG: проверено GPP; Jet/керосин: нет сопоставимой национальной цены; Мазут: нет сопоставимой национальной цены | AH67: TR | AI67: TUR | AJ67: ='Сводка НПЗ'!D67 -> 6 | AK67: =IF('Сводка НПЗ'!F67>0,'Сводка НПЗ'!E67,"") -> 651000 | AL67: ='Сводка НПЗ'!G67 -> 0 | AM67: 2019-02-18 | AN67: Мощность: вторичная публикация EI; число НПЗ не подтверждено | AO67: 2025 | AP67: 2025 | AQ67: 2025 | AR67: 2026-09-16
A68: 67 | B68: Spain | C68: Испания | D68: 1310465.8 | E68: 2025 | F68: =IF(AND(ISNUMBER(D68),ISNUMBER(E68)),D68*(DATE(E68+1,1,1)-DATE(E68,1,1))/1000000,"н/д") -> 478.32 | G68: 47.510867 | H68: 12.419196 | I68: 4.8090818 | J68: 25.518732 | K68: 10.411534 | L68: 77267.371 | M68: 2025 | N68: 26.50411 | O68: 2000 | P68: 1906.4533 | Q68: 2025 | R68: 2.824954 | S68: 2025 | T68: 2.6999329 | U68: 2025 | V68: 2.196 | W68: 2.176 | X68: н/д | Y68: 1.265 | Z68: н/д | AA68: Бензин/дизель/LPG: USD/л; Jet/мазут: исходные единицы | AB68: Бензин: 2026-09-14; Дизель: 2026-09-14; LPG: 2026-09-14; исходные даты для непроверенных значений: бензин: 2026-09-14; дизель/LPG: 2026-09-07; Jet/мазут: н/д | AC68: https://api.eia.gov/v2/international/data/?frequency=annual&facets[productId][]=53&facets[activityId][]=1&facets[unit][]=TBPD ; https://api.eia.gov/v2/international/data/?frequency=annual&facets[productId][]=57&facets[activityId][]=1&facets[unit][]=TBPD ; https://api.eia.gov/v2/international/data/?frequency=annual&facets[productId][]=58&facets[activityId][]=1&facets[unit][]=TBPD ; https://www.jodidata.org/_resources/files/downloads/oil-data/annual-csv/secondary/2025.csv ; Исходный источник: https://www.jodidata.org/oil/database/data-downloads.aspx | AD68: https://api.worldbank.org/v2/country/ESP/indicator/NY.GDP.MKTP.CD?format=json ; https://api.worldbank.org/v2/country/ESP/indicator/NY.GDP.MKTP.KD.ZG?format=json ; https://api.worldbank.org/v2/country/ESP/indicator/FP.CPI.TOTL.ZG?format=json ; Исходный источник: https://data.worldbank.org/ | AE68: https://www.globalpetrolprices.com/Spain/gasoline_prices/ ; https://www.globalpetrolprices.com/Spain/diesel_prices/ ; https://www.globalpetrolprices.com/Spain/lpg_prices/ ; Исходный источник: GlobalPetrolPrices (страновые значения только там, где они были явно помечены как страновые); Jet/мазут: н/д | AF68: Массовые оценки/медианы удалены в ходе аудита. Сохранившиеся исходные числовые значения не считаются подтверждёнными автоматически; требуется первичная проверка источника. Обновление 16.09.2026: Потребление и доли: JODI, нефтепродукты TOTPRODS, 12 месяцев 2025. Jet/мазут: национальные сопоставимые цены не найдены; исходные значения сохранены. | AG68: Бензин: проверено GPP; Дизель: проверено GPP; LPG: проверено GPP; Jet/керосин: нет сопоставимой национальной цены; Мазут: нет сопоставимой национальной цены | AH68: ES | AI68: ESP | AJ68: ='Сводка НПЗ'!D68 -> 9 | AK68: =IF('Сводка НПЗ'!F68>0,'Сводка НПЗ'!E68,"") -> 1270000 | AL68: ='Сводка НПЗ'!G68 -> 0 | AM68: 2019-02-18 | AN68: Проверен первичный источник; см. охват | AO68: 2025 | AP68: 2025 | AQ68: 2025 | AR68: 2026-09-16
A69: 68 | B69: Laos | C69: Лаос | D69: 23517.037 | E69: 2024 | F69: =IF(AND(ISNUMBER(D69),ISNUMBER(E69)),D69*(DATE(E69+1,1,1)-DATE(E69,1,1))/1000000,"н/д") -> 8.6072355 | G69: 70.437644 | H69: 19.370531 | I69: 3.7433519 | J69: 5.1275435 | K69: 0.55720009 | L69: 0 | M69: 2025 | N69: 0 | O69: 0 | P69: 18.30297 | Q69: 2025 | R69: 4.5376056 | S69: 2025 | T69: 7.7422694 | U69: 2025 | V69: 1.672 | W69: 1.398 | X69: н/д | Y69: н/д | Z69: н/д | AA69: Бензин/дизель/LPG: USD/л; Jet/мазут: исходные единицы | AB69: Бензин: 2026-09-14; Дизель: 2026-09-14; исходные даты для непроверенных значений: бензин: 2026-09-14; дизель/LPG: 2026-09-07; Jet/мазут: н/д | AC69: https://api.eia.gov/v2/international/data/?frequency=annual&facets[productId][]=53&facets[activityId][]=1&facets[unit][]=TBPD ; https://api.eia.gov/v2/international/data/?frequency=annual&facets[productId][]=57&facets[activityId][]=1&facets[unit][]=TBPD ; https://api.eia.gov/v2/international/data/?frequency=annual&facets[productId][]=58&facets[activityId][]=1&facets[unit][]=TBPD ; https://api.eia.gov/v2/international/data/?frequency=annual&facets[productId][]=5&facets[activityId][]=2&facets[unit][]=TBPD ; Исходный источник: https://www.jodidata.org/oil/database/data-downloads.aspx | AD69: https://api.worldbank.org/v2/country/LAO/indicator/NY.GDP.MKTP.CD?format=json ; https://api.worldbank.org/v2/country/LAO/indicator/NY.GDP.MKTP.KD.ZG?format=json ; https://api.worldbank.org/v2/country/LAO/indicator/FP.CPI.TOTL.ZG?format=json ; Исходный источник: https://data.worldbank.org/ | AE69: https://www.globalpetrolprices.com/Laos/gasoline_prices/ ; https://www.globalpetrolprices.com/Laos/diesel_prices/ ; Исходный источник: GlobalPetrolPrices (страновые значения только там, где они были явно помечены как страновые); Jet/мазут: н/д | AF69: Массовые оценки/медианы удалены в ходе аудита. Сохранившиеся исходные числовые значения не считаются подтверждёнными автоматически; требуется первичная проверка источника. Обновление 16.09.2026: Потребление и доли: EIA, petroleum and other liquids, 2024; включает биотопливо. Jet/мазут: национальные сопоставимые цены не найдены; исходные значения сохранены. | AG69: Бензин: проверено GPP; Дизель: проверено GPP; LPG: н/д; Jet/керосин: нет сопоставимой национальной цены; Мазут: нет сопоставимой национальной цены | AH69: LA | AI69: LAO | AJ69: ='Сводка НПЗ'!D69 -> 0 | AK69: =IF('Сводка НПЗ'!F69>0,'Сводка НПЗ'!E69,"") | AL69: ='Сводка НПЗ'!G69 -> 0 | AM69: 2019-02-18 | AN69: Свежие число и мощность не подтверждены | AO69: 2024 | AP69: 2025 | AQ69: 2025 | AR69: 2026-09-16
A70: 69 | B70: Kyrgyzstan | C70: Киргизия | D70: 30018.959 | E70: 2024 | F70: =IF(AND(ISNUMBER(D70),ISNUMBER(E70)),D70*(DATE(E70+1,1,1)-DATE(E70,1,1))/1000000,"н/д") -> 10.986939 | G70: 33.906244 | H70: 47.48871 | I70: 9.4223559 | J70: 1.0132409 | K70: 4.1940618 | L70: 5543.4027 | M70: 2025 | N70: 5543.4027 | O70: 0 | P70: 22.623752 | Q70: 2025 | R70: 11.09602 | S70: 2025 | T70: 8.2149601 | U70: 2025 | V70: 1.25 | W70: 1.162 | X70: н/д | Y70: н/д | Z70: н/д | AA70: Бензин/дизель/LPG: USD/л; Jet/мазут: исходные единицы | AB70: Бензин: 2026-09-14; Дизель: 2026-09-14; исходные даты для непроверенных значений: бензин: 2026-09-14; дизель/LPG: 2026-09-07; Jet/мазут: н/д | AC70: https://api.eia.gov/v2/international/data/?frequency=annual&facets[productId][]=53&facets[activityId][]=1&facets[unit][]=TBPD ; https://api.eia.gov/v2/international/data/?frequency=annual&facets[productId][]=57&facets[activityId][]=1&facets[unit][]=TBPD ; https://api.eia.gov/v2/international/data/?frequency=annual&facets[productId][]=58&facets[activityId][]=1&facets[unit][]=TBPD ; https://api.eia.gov/v2/international/data/?frequency=annual&facets[productId][]=5&facets[activityId][]=2&facets[unit][]=TBPD ; Исходный источник: https://www.jodidata.org/oil/database/data-downloads.aspx ; https://www.worldometers.info/oil/ | AD70: https://api.worldbank.org/v2/country/KGZ/indicator/NY.GDP.MKTP.CD?format=json ; https://api.worldbank.org/v2/country/KGZ/indicator/NY.GDP.MKTP.KD.ZG?format=json ; https://api.worldbank.org/v2/country/KGZ/indicator/FP.CPI.TOTL.ZG?format=json ; Исходный источник: https://data.worldbank.org/ | AE70: https://www.globalpetrolprices.com/Kyrgyzstan/gasoline_prices/ ; https://www.globalpetrolprices.com/Kyrgyzstan/diesel_prices/ ; Исходный источник: GlobalPetrolPrices (страновые значения только там, где они были явно помечены как страновые); Jet/мазут: н/д | AF70: Массовые оценки/медианы удалены в ходе аудита. Сохранившиеся исходные числовые значения не считаются подтверждёнными автоматически; требуется первичная проверка источника. Обновление 16.09.2026: Потребление и доли: EIA, petroleum and other liquids, 2024; включает биотопливо. Jet/мазут: национальные сопоставимые цены не найдены; исходные значения сохранены. | AG70: Бензин: проверено GPP; Дизель: проверено GPP; LPG: н/д; Jet/керосин: нет сопоставимой национальной цены; Мазут: нет сопоставимой национальной цены | AH70: KG | AI70: KGZ | AJ70: ='Сводка НПЗ'!D70 -> 1 | AK70: =IF('Сводка НПЗ'!F70>0,'Сводка НПЗ'!E70,"") | AL70: ='Сводка НПЗ'!G70 -> 1 | AM70: 2019-02-18 | AN70: Свежие число и мощность не подтверждены | AO70: 2024 | AP70: 2025 | AQ70: 2025 | AR70: 2026-09-16
A71: 70 | B71: Armenia | C71: Армения | D71: 18819.425 | E71: 2024 | F71: =IF(AND(ISNUMBER(D71),ISNUMBER(E71)),D71*(DATE(E71+1,1,1)-DATE(E71,1,1))/1000000,"н/д") -> 6.8879094 | G71: 17.484994 | H71: 26.326049 | I71: 37.32081 | J71: 11.659914 | K71: 0 | L71: 0 | M71: 2025 | N71: 0 | O71: 0 | P71: 29.243453 | Q71: 2025 | R71: 7.2 | S71: 2025 | T71: 3.3069334 | U71: 2025 | V71: 1.648 | W71: 1.867 | X71: н/д | Y71: 0.686 | Z71: н/д | AA71: Бензин/дизель/LPG: USD/л; Jet/мазут: исходные единицы | AB71: Бензин: 2026-09-14; Дизель: 2026-09-14; LPG: 2026-09-14; исходные даты для непроверенных значений: бензин: 2026-09-14; дизель/LPG: 2026-09-07; Jet/мазут: н/д | AC71: https://api.eia.gov/v2/international/data/?frequency=annual&facets[productId][]=53&facets[activityId][]=1&facets[unit][]=TBPD ; https://api.eia.gov/v2/international/data/?frequency=annual&facets[productId][]=57&facets[activityId][]=1&facets[unit][]=TBPD ; https://api.eia.gov/v2/international/data/?frequency=annual&facets[productId][]=58&facets[activityId][]=1&facets[unit][]=TBPD ; https://api.eia.gov/v2/international/data/?frequency=annual&facets[productId][]=5&facets[activityId][]=2&facets[unit][]=TBPD ; Исходный источник: https://www.jodidata.org/oil/database/data-downloads.aspx | AD71: https://api.worldbank.org/v2/country/ARM/indicator/NY.GDP.MKTP.CD?format=json ; https://api.worldbank.org/v2/country/ARM/indicator/NY.GDP.MKTP.KD.ZG?format=json ; https://api.worldbank.org/v2/country/ARM/indicator/FP.CPI.TOTL.ZG?format=json ; Исходный источник: https://data.worldbank.org/ | AE71: https://www.globalpetrolprices.com/Armenia/gasoline_prices/ ; https://www.globalpetrolprices.com/Armenia/diesel_prices/ ; https://www.globalpetrolprices.com/Armenia/lpg_prices/ ; Исходный источник: GlobalPetrolPrices (страновые значения только там, где они были явно помечены как страновые); Jet/мазут: н/д | AF71: Массовые оценки/медианы удалены в ходе аудита. Сохранившиеся исходные числовые значения не считаются подтверждёнными автоматически; требуется первичная проверка источника. Обновление 16.09.2026: Потребление и доли: EIA, petroleum and other liquids, 2024; включает биотопливо. Jet/мазут: национальные сопоставимые цены не найдены; исходные значения сохранены. | AG71: Бензин: проверено GPP; Дизель: проверено GPP; LPG: проверено GPP; Jet/керосин: нет сопоставимой национальной цены; Мазут: нет сопоставимой национальной цены | AH71: AM | AI71: ARM | AJ71: ='Сводка НПЗ'!D71 -> 0 | AK71: =IF('Сводка НПЗ'!F71>0,'Сводка НПЗ'!E71,"") | AL71: ='Сводка НПЗ'!G71 -> 0 | AM71: 2019-02-18 | AN71: Свежие число и мощность не подтверждены | AO71: 2024 | AP71: 2025 | AQ71: 2025 | AR71: 2026-09-16
A72: 71 | B72: Denmark | C72: Дания | D72: 141057.53 | E72: 2025 | F72: =IF(AND(ISNUMBER(D72),ISNUMBER(E72)),D72*(DATE(E72+1,1,1)-DATE(E72,1,1))/1000000,"н/д") -> 51.486 | G72: 50.263644 | H72: 18.988948 | I72: 1.3743542 | J72: 32.293827 | K72: 4.309521 | L72: 79279.098 | M72: 2025 | N72: 71810.642 | O72: 0 | P72: 462.52666 | Q72: 2025 | R72: 2.9284328 | S72: 2025 | T72: 1.8936737 | U72: 2025 | V72: 3.004 | W72: 3.143 | X72: н/д | Y72: н/д | Z72: н/д | AA72: Бензин/дизель/LPG: USD/л; Jet/мазут: исходные единицы | AB72: Бензин: 2026-09-14; Дизель: 2026-09-14; исходные даты для непроверенных значений: бензин: 2026-09-14; дизель/LPG: 2026-09-07; Jet/мазут: н/д | AC72: https://api.eia.gov/v2/international/data/?frequency=annual&facets[productId][]=53&facets[activityId][]=1&facets[unit][]=TBPD ; https://api.eia.gov/v2/international/data/?frequency=annual&facets[productId][]=57&facets[activityId][]=1&facets[unit][]=TBPD ; https://api.eia.gov/v2/international/data/?frequency=annual&facets[productId][]=58&facets[activityId][]=1&facets[unit][]=TBPD ; https://www.jodidata.org/_resources/files/downloads/oil-data/annual-csv/secondary/2025.csv ; Исходный источник: https://www.jodidata.org/oil/database/data-downloads.aspx | AD72: https://api.worldbank.org/v2/country/DNK/indicator/NY.GDP.MKTP.CD?format=json ; https://api.worldbank.org/v2/country/DNK/indicator/NY.GDP.MKTP.KD.ZG?format=json ; https://api.worldbank.org/v2/country/DNK/indicator/FP.CPI.TOTL.ZG?format=json ; Исходный источник: https://data.worldbank.org/ | AE72: https://www.globalpetrolprices.com/Denmark/gasoline_prices/ ; https://www.globalpetrolprices.com/Denmark/diesel_prices/ ; Исходный источник: GlobalPetrolPrices (страновые значения только там, где они были явно помечены как страновые); Jet/мазут: н/д | AF72: Массовые оценки/медианы удалены в ходе аудита. Сохранившиеся исходные числовые значения не считаются подтверждёнными автоматически; требуется первичная проверка источника. Обновление 16.09.2026: Потребление и доли: JODI, нефтепродукты TOTPRODS, 12 месяцев 2025. Jet/мазут: национальные сопоставимые цены не найдены; исходные значения сохранены. | AG72: Бензин: проверено GPP; Дизель: проверено GPP; LPG: н/д; Jet/керосин: нет сопоставимой национальной цены; Мазут: нет сопоставимой национальной цены | AH72: DK | AI72: DNK | AJ72: ='Сводка НПЗ'!D72 -> 2 | AK72: =IF('Сводка НПЗ'!F72>0,'Сводка НПЗ'!E72,"") -> 178000 | AL72: ='Сводка НПЗ'!G72 -> 0 | AM72: 2019-02-18 | AN72: Проверен первичный источник; см. охват | AO72: 2025 | AP72: 2025 | AQ72: 2025 | AR72: 2026-09-16
A73: 72 | B73: Libya | C73: Ливия | D73: 222799.41 | E73: 2024 | F73: =IF(AND(ISNUMBER(D73),ISNUMBER(E73)),D73*(DATE(E73+1,1,1)-DATE(E73,1,1))/1000000,"н/д") -> 81.544583 | G73: 23.09956 | H73: 51.04321 | I73: 3.8839121 | J73: 1.8066812 | K73: 11.836919 | L73: 1382021.5 | M73: 2025 | N73: 1363041.1 | O73: 20000 | P73: 48.09891 | Q73: 2025 | R73: 13.371708 | S73: 2025 | T73: 1.8416667 | U73: 2025 | V73: 0.024 | W73: 0.024 | X73: н/д | Y73: н/д | Z73: н/д | AA73: Бензин/дизель/LPG: USD/л; Jet/мазут: исходные единицы | AB73: Бензин: 2026-09-14; Дизель: 2026-09-14; исходные даты для непроверенных значений: бензин: 2026-09-14; дизель/LPG: 2026-09-07; Jet/мазут: н/д | AC73: https://api.eia.gov/v2/international/data/?frequency=annual&facets[productId][]=53&facets[activityId][]=1&facets[unit][]=TBPD ; https://api.eia.gov/v2/international/data/?frequency=annual&facets[productId][]=57&facets[activityId][]=1&facets[unit][]=TBPD ; https://api.eia.gov/v2/international/data/?frequency=annual&facets[productId][]=58&facets[activityId][]=1&facets[unit][]=TBPD ; https://api.eia.gov/v2/international/data/?frequency=annual&facets[productId][]=5&facets[activityId][]=2&facets[unit][]=TBPD ; Исходный источник: https://www.jodidata.org/oil/database/data-downloads.aspx | AD73: https://api.worldbank.org/v2/country/LBY/indicator/NY.GDP.MKTP.CD?format=json ; https://api.worldbank.org/v2/country/LBY/indicator/NY.GDP.MKTP.KD.ZG?format=json ; https://api.worldbank.org/v2/country/LBY/indicator/FP.CPI.TOTL.ZG?format=json ; Исходный источник: https://data.worldbank.org/ | AE73: https://www.globalpetrolprices.com/Libya/gasoline_prices/ ; https://www.globalpetrolprices.com/Libya/diesel_prices/ ; Исходный источник: GlobalPetrolPrices (страновые значения только там, где они были явно помечены как страновые); Jet/мазут: н/д | AF73: Массовые оценки/медианы удалены в ходе аудита. Сохранившиеся исходные числовые значения не считаются подтверждёнными автоматически; требуется первичная проверка источника. Обновление 16.09.2026: Потребление и доли: EIA, petroleum and other liquids, 2024; включает биотопливо. Jet/мазут: национальные сопоставимые цены не найдены; исходные значения сохранены. | AG73: Бензин: проверено GPP; Дизель: проверено GPP; LPG: н/д; Jet/керосин: нет сопоставимой национальной цены; Мазут: нет сопоставимой национальной цены | AH73: LY | AI73: LBY | AJ73: ='Сводка НПЗ'!D73 -> 5 | AK73: =IF('Сводка НПЗ'!F73>0,'Сводка НПЗ'!E73,"") -> 380000 | AL73: ='Сводка НПЗ'!G73 -> 0 | AM73: 2019-02-18 | AN73: Свежие число и мощность не подтверждены | AO73: 2024 | AP73: 2025 | AQ73: 2025 | AR73: 2026-09-16
A74: 73 | B74: Tunisia | C74: Тунис | D74: 102583.56 | E74: 2025 | F74: =IF(AND(ISNUMBER(D74),ISNUMBER(E74)),D74*(DATE(E74+1,1,1)-DATE(E74,1,1))/1000000,"н/д") -> 37.443 | G74: 39.981305 | H74: 20.476458 | I74: 20.942766 | J74: 12.190797 | K74: 2.5345191 | L74: 28112.779 | M74: 2025 | N74: 25326.027 | O74: 3022.5041 | P74: 57.502837 | Q74: 2025 | R74: 2.4931101 | S74: 2025 | T74: 5.151002 | U74: 2025 | V74: 0.862 | W74: 0.753 | X74: н/д | Y74: н/д | Z74: н/д | AA74: Бензин/дизель/LPG: USD/л; Jet/мазут: исходные единицы | AB74: Бензин: 2026-09-14; Дизель: 2026-09-14; исходные даты для непроверенных значений: бензин: 2026-09-14; дизель/LPG: 2026-09-07; Jet/мазут: н/д | AC74: https://api.eia.gov/v2/international/data/?frequency=annual&facets[productId][]=53&facets[activityId][]=1&facets[unit][]=TBPD ; https://api.eia.gov/v2/international/data/?frequency=annual&facets[productId][]=57&facets[activityId][]=1&facets[unit][]=TBPD ; https://api.eia.gov/v2/international/data/?frequency=annual&facets[productId][]=58&facets[activityId][]=1&facets[unit][]=TBPD ; https://www.jodidata.org/_resources/files/downloads/oil-data/annual-csv/secondary/2025.csv ; Исходный источник: https://www.jodidata.org/oil/database/data-downloads.aspx | AD74: https://api.worldbank.org/v2/country/TUN/indicator/NY.GDP.MKTP.CD?format=json ; https://api.worldbank.org/v2/country/TUN/indicator/NY.GDP.MKTP.KD.ZG?format=json ; https://api.worldbank.org/v2/country/TUN/indicator/FP.CPI.TOTL.ZG?format=json ; Исходный источник: https://data.worldbank.org/ | AE74: https://www.globalpetrolprices.com/Tunisia/gasoline_prices/ ; https://www.globalpetrolprices.com/Tunisia/diesel_prices/ ; Исходный источник: GlobalPetrolPrices (страновые значения только там, где они были явно помечены как страновые); Jet/мазут: н/д | AF74: Массовые оценки/медианы удалены в ходе аудита. Сохранившиеся исходные числовые значения не считаются подтверждёнными автоматически; требуется первичная проверка источника. Обновление 16.09.2026: Потребление и доли: JODI, нефтепродукты TOTPRODS, 12 месяцев 2025. Jet/мазут: национальные сопоставимые цены не найдены; исходные значения сохранены. | AG74: Бензин: проверено GPP; Дизель: проверено GPP; LPG: н/д; Jet/керосин: нет сопоставимой национальной цены; Мазут: нет сопоставимой национальной цены | AH74: TN | AI74: TUN | AJ74: ='Сводка НПЗ'!D74 -> 1 | AK74: =IF('Сводка НПЗ'!F74>0,'Сводка НПЗ'!E74,"") -> 34000 | AL74: ='Сводка НПЗ'!G74 -> 0 | AM74: 2019-02-18 | AN74: Свежие число и мощность не подтверждены | AO74: 2025 | AP74: 2025 | AQ74: 2025 | AR74: 2026-09-16
A75: 74 | B75: Romania | C75: Румыния | D75: 229707.22 | E75: 2025 | F75: =IF(AND(ISNUMBER(D75),ISNUMBER(E75)),D75*(DATE(E75+1,1,1)-DATE(E75,1,1))/1000000,"н/д") -> 83.843137 | G75: 61.820301 | H75: 16.135429 | I75: 9.3803742 | J75: н/д | K75: 0.16155168 | L75: 69525.368 | M75: 2025 | N75: 51548.052 | O75: 2026.1068 | P75: 428.67798 | Q75: 2025 | R75: 0.67782984 | S75: 2025 | T75: 7.1890336 | U75: 2025 | V75: 2.19 | W75: 2.33 | X75: н/д | Y75: 1.028 | Z75: н/д | AA75: Бензин/дизель/LPG: USD/л; Jet/мазут: исходные единицы | AB75: Бензин: 2026-09-14; Дизель: 2026-09-14; LPG: 2026-09-14; исходные даты для непроверенных значений: бензин: 2026-09-14; дизель/LPG: 2026-09-07; Jet/мазут: н/д | AC75: https://api.eia.gov/v2/international/data/?frequency=annual&facets[productId][]=53&facets[activityId][]=1&facets[unit][]=TBPD ; https://api.eia.gov/v2/international/data/?frequency=annual&facets[productId][]=57&facets[activityId][]=1&facets[unit][]=TBPD ; https://api.eia.gov/v2/international/data/?frequency=annual&facets[productId][]=58&facets[activityId][]=1&facets[unit][]=TBPD ; https://www.jodidata.org/_resources/files/downloads/oil-data/annual-csv/secondary/2025.csv ; Исходный источник: https://www.jodidata.org/oil/database/data-downloads.aspx ; https://www.worldometers.info/oil/romania-oil/ | AD75: https://api.worldbank.org/v2/country/ROU/indicator/NY.GDP.MKTP.CD?format=json ; https://api.worldbank.org/v2/country/ROU/indicator/NY.GDP.MKTP.KD.ZG?format=json ; https://api.worldbank.org/v2/country/ROU/indicator/FP.CPI.TOTL.ZG?format=json ; Исходный источник: https://data.worldbank.org/ | AE75: https://www.globalpetrolprices.com/Romania/gasoline_prices/ ; https://www.globalpetrolprices.com/Romania/diesel_prices/ ; https://www.globalpetrolprices.com/Romania/lpg_prices/ ; Исходный источник: GlobalPetrolPrices (страновые значения только там, где они были явно помечены как страновые); Jet/мазут: н/д | AF75: Массовые оценки/медианы удалены в ходе аудита. Сохранившиеся исходные числовые значения не считаются подтверждёнными автоматически; требуется первичная проверка источника. Обновление 16.09.2026: Потребление и доли: JODI, нефтепродукты TOTPRODS, 12 месяцев 2025. Jet/мазут: национальные сопоставимые цены не найдены; исходные значения сохранены. | AG75: Бензин: проверено GPP; Дизель: проверено GPP; LPG: проверено GPP; Jet/керосин: нет сопоставимой национальной цены; Мазут: нет сопоставимой национальной цены | AH75: RO | AI75: ROU | AJ75: ='Сводка НПЗ'!D75 -> 10 | AK75: =IF('Сводка НПЗ'!F75>0,'Сводка НПЗ'!E75,"") -> 493000 | AL75: ='Сводка НПЗ'!G75 -> 0 | AM75: 2019-02-18 | AN75: Проверен первичный источник; см. охват | AO75: 2025 | AP75: 2025 | AQ75: 2025 | AR75: 2026-09-16
A76: 75 | B76: Hungary | C76: Венгрия | D76: 177671.23 | E76: 2025 | F76: =IF(AND(ISNUMBER(D76),ISNUMBER(E76)),D76*(DATE(E76+1,1,1)-DATE(E76,1,1))/1000000,"н/д") -> 64.85 | G76: 43.59815 | H76: 20.079337 | I76: 6.0459522 | J76: 10.522868 | K76: 0.28843485 | L76: 46421.284 | M76: 2025 | N76: 23419.825 | O76: 5983.4904 | P76: 246.49021 | Q76: 2025 | R76: 0.50954231 | S76: 2025 | T76: 4.4119845 | U76: 2025 | V76: 1.887 | W76: 2.139 | X76: н/д | Y76: 1.119 | Z76: н/д | AA76: Бензин/дизель/LPG: USD/л; Jet/мазут: исходные единицы | AB76: Бензин: 2026-09-14; Дизель: 2026-09-14; LPG: 2026-09-14; исходные даты для непроверенных значений: бензин: 2026-09-14; дизель/LPG: 2026-09-07; Jet/мазут: н/д | AC76: https://api.eia.gov/v2/international/data/?frequency=annual&facets[productId][]=53&facets[activityId][]=1&facets[unit][]=TBPD ; https://api.eia.gov/v2/international/data/?frequency=annual&facets[productId][]=57&facets[activityId][]=1&facets[unit][]=TBPD ; https://api.eia.gov/v2/international/data/?frequency=annual&facets[productId][]=58&facets[activityId][]=1&facets[unit][]=TBPD ; https://www.jodidata.org/_resources/files/downloads/oil-data/annual-csv/secondary/2025.csv ; Исходный источник: https://www.jodidata.org/oil/database/data-downloads.aspx | AD76: https://api.worldbank.org/v2/country/HUN/indicator/NY.GDP.MKTP.CD?format=json ; https://api.worldbank.org/v2/country/HUN/indicator/NY.GDP.MKTP.KD.ZG?format=json ; https://api.worldbank.org/v2/country/HUN/indicator/FP.CPI.TOTL.ZG?format=json ; Исходный источник: https://data.worldbank.org/ | AE76: https://www.globalpetrolprices.com/Hungary/gasoline_prices/ ; https://www.globalpetrolprices.com/Hungary/diesel_prices/ ; https://www.globalpetrolprices.com/Hungary/lpg_prices/ ; Исходный источник: GlobalPetrolPrices (страновые значения только там, где они были явно помечены как страновые); Jet/мазут: н/д | AF76: Массовые оценки/медианы удалены в ходе аудита. Сохранившиеся исходные числовые значения не считаются подтверждёнными автоматически; требуется первичная проверка источника. Обновление 16.09.2026: Потребление и доли: JODI, нефтепродукты TOTPRODS, 12 месяцев 2025. Jet/мазут: национальные сопоставимые цены не найдены; исходные значения сохранены. | AG76: Бензин: проверено GPP; Дизель: проверено GPP; LPG: проверено GPP; Jet/керосин: нет сопоставимой национальной цены; Мазут: нет сопоставимой национальной цены | AH76: HU | AI76: HUN | AJ76: ='Сводка НПЗ'!D76 -> 2 | AK76: =IF('Сводка НПЗ'!F76>0,'Сводка НПЗ'!E76,"") -> 161000 | AL76: ='Сводка НПЗ'!G76 -> 1 | AM76: 2019-02-18 | AN76: Проверен первичный источник; см. охват | AO76: 2025 | AP76: 2025 | AQ76: 2025 | AR76: 2026-09-16
A77: 76 | B77: Slovakia | C77: Словакия | D77: 96410.959 | E77: 2025 | F77: =IF(AND(ISNUMBER(D77),ISNUMBER(E77)),D77*(DATE(E77+1,1,1)-DATE(E77,1,1))/1000000,"н/д") -> 35.19 | G77: 44.369935 | H77: 17.024865 | I77: 4.2193805 | J77: 2.687127 | K77: 4.5822677 | L77: 8949.8331 | M77: 2025 | N77: 18.556164 | O77: 0 | P77: 154.53007 | Q77: 2025 | R77: 0.80741869 | S77: 2025 | T77: 4.0004282 | U77: 2025 | V77: 2.048 | W77: 2.202 | X77: н/д | Y77: 0.925 | Z77: н/д | AA77: Бензин/дизель/LPG: USD/л; Jet/мазут: исходные единицы | AB77: Бензин: 2026-09-14; Дизель: 2026-09-14; LPG: 2026-09-14; исходные даты для непроверенных значений: бензин: 2026-09-14; дизель/LPG: 2026-09-07; Jet/мазут: н/д | AC77: https://api.eia.gov/v2/international/data/?frequency=annual&facets[productId][]=53&facets[activityId][]=1&facets[unit][]=TBPD ; https://api.eia.gov/v2/international/data/?frequency=annual&facets[productId][]=57&facets[activityId][]=1&facets[unit][]=TBPD ; https://api.eia.gov/v2/international/data/?frequency=annual&facets[productId][]=58&facets[activityId][]=1&facets[unit][]=TBPD ; https://www.jodidata.org/_resources/files/downloads/oil-data/annual-csv/secondary/2025.csv ; Исходный источник: https://www.jodidata.org/oil/database/data-downloads.aspx | AD77: https://api.worldbank.org/v2/country/SVK/indicator/NY.GDP.MKTP.CD?format=json ; https://api.worldbank.org/v2/country/SVK/indicator/NY.GDP.MKTP.KD.ZG?format=json ; https://api.worldbank.org/v2/country/SVK/indicator/FP.CPI.TOTL.ZG?format=json ; Исходный источник: https://data.worldbank.org/ | AE77: https://www.globalpetrolprices.com/Slovakia/gasoline_prices/ ; https://www.globalpetrolprices.com/Slovakia/diesel_prices/ ; https://www.globalpetrolprices.com/Slovakia/lpg_prices/ ; Исходный источник: GlobalPetrolPrices (страновые значения только там, где они были явно помечены как страновые); Jet/мазут: н/д | AF77: Массовые оценки/медианы удалены в ходе аудита. Сохранившиеся исходные числовые значения не считаются подтверждёнными автоматически; требуется первичная проверка источника. Обновление 16.09.2026: Потребление и доли: JODI, нефтепродукты TOTPRODS, 12 месяцев 2025. Jet/мазут: национальные сопоставимые цены не найдены; исходные значения сохранены. | AG77: Бензин: проверено GPP; Дизель: проверено GPP; LPG: проверено GPP; Jet/керосин: нет сопоставимой национальной цены; Мазут: нет сопоставимой национальной цены | AH77: SK | AI77: SVK | AJ77: ='Сводка НПЗ'!D77 -> 1 | AK77: =IF('Сводка НПЗ'!F77>0,'Сводка НПЗ'!E77,"") -> 110000 | AL77: ='Сводка НПЗ'!G77 -> 0 | AM77: 2019-02-18 | AN77: Проверен первичный источник; см. охват | AO77: 2025 | AP77: 2025 | AQ77: 2025 | AR77: 2026-09-16
A78: 77 | B78: Poland | C78: Польша | D78: 751827.4 | E78: 2025 | F78: =IF(AND(ISNUMBER(D78),ISNUMBER(E78)),D78*(DATE(E78+1,1,1)-DATE(E78,1,1))/1000000,"н/д") -> 274.417 | G78: 51.439277 | H78: 18.851201 | I78: 10.75808 | J78: 8.4193618 | K78: 2.9262947 | L78: 44534.861 | M78: 2025 | N78: 16541.195 | O78: 1000 | P78: 1035.4918 | Q78: 2025 | R78: 3.572725 | S78: 2025 | T78: 3.8141953 | U78: 2025 | V78: 2.076 | W78: 2.271 | X78: н/д | Y78: 0.787 | Z78: н/д | AA78: Бензин/дизель/LPG: USD/л; Jet/мазут: исходные единицы | AB78: Бензин: 2026-09-14; Дизель: 2026-09-14; LPG: 2026-09-14; исходные даты для непроверенных значений: бензин: 2026-09-14; дизель/LPG: 2026-09-07; Jet/мазут: н/д | AC78: https://api.eia.gov/v2/international/data/?frequency=annual&facets[productId][]=53&facets[activityId][]=1&facets[unit][]=TBPD ; https://api.eia.gov/v2/international/data/?frequency=annual&facets[productId][]=57&facets[activityId][]=1&facets[unit][]=TBPD ; https://api.eia.gov/v2/international/data/?frequency=annual&facets[productId][]=58&facets[activityId][]=1&facets[unit][]=TBPD ; https://www.jodidata.org/_resources/files/downloads/oil-data/annual-csv/secondary/2025.csv ; Исходный источник: https://www.jodidata.org/oil/database/data-downloads.aspx | AD78: https://api.worldbank.org/v2/country/POL/indicator/NY.GDP.MKTP.CD?format=json ; https://api.worldbank.org/v2/country/POL/indicator/NY.GDP.MKTP.KD.ZG?format=json ; https://api.worldbank.org/v2/country/POL/indicator/FP.CPI.TOTL.ZG?format=json ; Исходный источник: https://data.worldbank.org/ | AE78: https://www.globalpetrolprices.com/Poland/gasoline_prices/ ; https://www.globalpetrolprices.com/Poland/diesel_prices/ ; https://www.globalpetrolprices.com/Poland/lpg_prices/ ; Исходный источник: GlobalPetrolPrices (страновые значения только там, где они были явно помечены как страновые); Jet/мазут: н/д | AF78: Массовые оценки/медианы удалены в ходе аудита. Сохранившиеся исходные числовые значения не считаются подтверждёнными автоматически; требуется первичная проверка источника. Обновление 16.09.2026: Потребление и доли: JODI, нефтепродукты TOTPRODS, 12 месяцев 2025. Jet/мазут: национальные сопоставимые цены не найдены; исходные значения сохранены. | AG78: Бензин: проверено GPP; Дизель: проверено GPP; LPG: проверено GPP; Jet/керосин: нет сопоставимой национальной цены; Мазут: нет сопоставимой национальной цены | AH78: PL | AI78: POL | AJ78: ='Сводка НПЗ'!D78 -> 4 | AK78: =IF('Сводка НПЗ'!F78>0,'Сводка НПЗ'!E78,"") -> 496500 | AL78: ='Сводка НПЗ'!G78 -> 2 | AM78: 2019-02-18 | AN78: Проверен первичный источник; см. охват | AO78: 2025 | AP78: 2025 | AQ78: 2025 | AR78: 2026-09-16
